Workbook
Name ACCIONES: '[1]Shares Outstanding'!$C$3:$D$104
Name ACCIONES: '[1]Shares Outstanding'!$C$3:$D$104
Name ACCIONES: '[2]Shares Outstanding'!$C$3:$D$104
Name Debt_Sc: '[2]Tipos de Cambio'!#REF!
Name EERR: '[3]Consolidated Income Statement'!$C$4:$BU$228
Name EERR: '[3]Consolidated Income Statement'!$C$4:$BU$228
Name EERR: '[3]Consolidated Income Statement'!$C$4:$BU$228
Name EERR: '[3]Consolidated Income Statement'!$C$4:$BU$228
Name EERR3: '[1]P&L'!$D$4:$BV$236
Name EERR3: '[1]P&L'!$D$4:$BV$236
Name EERR3: '[2]P&L'!$D$4:$BV$236
Name Periodos: '[1]Tipos de Cambio'!$B$4:$C$82
Name Periodos: '[1]Tipos de Cambio'!$B$4:$C$82
Name Periodos: '[2]Tipos de Cambio'!$B$4:$C$82
Name Sch_Debt: '[2]Tipos de Cambio'!#REF!
Name TC: '[2]Tipos de Cambio'!#REF!
Name TC: '[1]Tipos de Cambio'!#REF!
Name TC: '[2]Tipos de Cambio'!#REF!
Name TC: '[1]Tipos de Cambio'!#REF!
Name TC: '[2]Tipos de Cambio'!#REF!

Sheet Forecast Drivers
A1: Forecast Drivers
A6: Income statement items | C6: Computation strategy | E6: 2019 | F6: 2020 | G6: 2021 | H6: 2022E | I6: 2023F | J6: 2024F | K6: 2025F | L6: 2026F | M6: 2027F
A7: Brazilian (TAM) Revenues | B7: Domestic Brazilian RPks | C7: Regressed quarterly ln(RPKs) over quarterly ln(real GDP_(t-1)) and ln(Jet fuel price_(t-1) To find elasticities: \epsilon_1=3.62, \epsilon_2=-0.19 | E7: {=TRANSPOSE('Domestic, Brazil estimate'!$B$53:$B$61)} -> 96449372986 | F7: 48695532564 | G7: 66373162099 | H7: 9.6237179e+10 | I7: 9.9065545e+10 | J7: 1.0728522e+11 | K7: 1.1262227e+11 | L7: 1.1677253e+11 | M7: 1.2107574e+11
C8: Growth Rates | E8: - | F8: =F7/E7-1 -> -0.4951182 | G8: =G7/F7-1 -> 0.36302364 | H8: =H7/G7-1 -> 0.44994115 | I8: =I7/H7-1 -> 0.029389528 | J8: =J7/I7-1 -> 0.0829721 | K8: =K7/J7-1 -> 0.049746371 | L8: =L7/K7-1 -> 0.036851174 | M8: =M7/L7-1 -> 0.036851174
C9: Real Gdp Brazil forecasted for 2022-2027 | E9: - | F9: - | G9: - | H9: 0.01 | I9: 0.01 | J9: 0.01 | K9: 0.01 | L9: 0.01 | M9: 0.01
C10: JET FUEL US$ per gallon | E10: 1.86 | F10: 1.1 | G10: 1.69 | H10: 3.43 | I10: 3.1 | J10: 2.38 | K10: 2.38 | L10: 2.38 | M10: =L10 -> 2.38
C11: CAGR 2022-2027, 5 years | D11: ='Domestic, Brazil estimate'!B22 -> 0.04699076
C12: CAGR 8 years 2019-2028, Latam Estimate | D12: =4.1% -> 0.041
C13: CAGR 8 Years 2019-2028 our estimate | D13: ='Domestic, Brazil estimate'!B23 -> 0.033497113
C14: R^2 regression | D14: ='Regression_Brazil '!B90 -> 0.96339276
C15: Recovery Rate market to pre pandemic Levels (2019) vs 2022 | D15: ='Domestic, Brazil estimate'!C13/'Domestic, Brazil estimate'!C10 -> 0.99779995
B17: Market share computation | C17: Assuming Latam and its LCC competitors will keep their actual RPKs as of 2021, their future market share will be driven by their contribution to the market growth. This contribution is estimated by a backward looking smoothed average, reduced by a future competition factor.
C18: (q1+q2+q3)2022/(q1+q2+q3)2019 | D18: =SUM(SS!BM79:BO79)/SUM(SS!AX79:AZ79) -> 0.99955011
C20: Market Share
C21: GOL+AZUL | E21: =Bra_Mkt_Sh!J59 -> 0.61190547 | F21: =Bra_Mkt_Sh!K59 -> 0.67056147 | G21: =Bra_Mkt_Sh!L59 -> 0.68429229 | H21: =Bra_Mkt_Sh!M59 -> 0.65547068 | I21: =Bra_Mkt_Sh!N59 -> 0.65750203 | J21: =Bra_Mkt_Sh!O59 -> 0.66167288 | K21: =Bra_Mkt_Sh!P59 -> 0.6633594 | L21: =Bra_Mkt_Sh!Q59 -> 0.66456434 | M21: =Bra_Mkt_Sh!R59 -> 0.66572645
C22: LATAM | E22: =Bra_Mkt_Sh!J60 -> 0.34715698 | F22: =Bra_Mkt_Sh!K60 -> 0.32492315 | G22: =Bra_Mkt_Sh!L60 -> 0.30506082 | H22: =Bra_Mkt_Sh!M60 -> 0.34050995 | I22: =Bra_Mkt_Sh!N60 -> 0.33830785 | J22: =Bra_Mkt_Sh!O60 -> 0.33215957 | K22: =Bra_Mkt_Sh!P60 -> 0.32839588 | L22: =Bra_Mkt_Sh!Q60 -> 0.32570689 | M22: =Bra_Mkt_Sh!R60 -> 0.32311348
C23: OTHERS | E23: =Bra_Mkt_Sh!J61 -> 0.04093755 | F23: =Bra_Mkt_Sh!K61 -> 0.0045153745 | G23: =Bra_Mkt_Sh!L61 -> 0.010646895 | H23: =Bra_Mkt_Sh!M61 -> 0.0040193713 | I23: =Bra_Mkt_Sh!N61 -> 0.0041901209 | J23: =Bra_Mkt_Sh!O61 -> 0.0061675494 | K23: =Bra_Mkt_Sh!P61 -> 0.0082447229 | L23: =Bra_Mkt_Sh!Q61 -> 0.0097287652 | M23: =Bra_Mkt_Sh!R61 -> 0.011160062
C25: Latam RPKs (mil) | E25: =Bra_Mkt_Sh!J65 -> 33483073 | F25: =Bra_Mkt_Sh!K65 -> 15822306 | G25: =Bra_Mkt_Sh!L65 -> 20247851 | H25: =Bra_Mkt_Sh!M65 -> 32769717 | I25: =Bra_Mkt_Sh!N65 -> 33514652 | J25: =Bra_Mkt_Sh!O65 -> 35635813 | K25: =Bra_Mkt_Sh!P65 -> 36984690 | L25: =Bra_Mkt_Sh!Q65 -> 38033619 | M25: =Bra_Mkt_Sh!R65 -> 39121204
C26: With our estimates Latam recovers in 2022 vs 2019 | D26: =H25/E25 -> 0.97869504
B29: Real Yield per RPk and Revenues in BRL | C29: We considered real yield per RPK constant to the mean level from 2019-2021
C30: Revenues Brazil USDm | E30: 3949.8 | F30: 1304 | G30: 1664.5
C31: Yield Per RPK USD | E31: =E30/(E25/1000) -> 0.11796408 | F31: =F30/(F25/1000) -> 0.082415294 | G31: =G30/(G25/1000) -> 0.082206255
C32: USDBRL | E32: 3.9776027 | F32: 5.3540347 | G32: 5.4278
C33: Nominal Yield per RPK RBL | E33: =E30*E32/(E25/1000) -> 0.46921426 | F33: =F30*F32/(F25/1000) -> 0.44125435 | G33: =G30*G32/(G25/1000) -> 0.44619911 | H33: =H37*(1+H36) -> 0.44351344 | I33: =I37*(1+I36) -> 0.4652456 | J33: =J37*(1+J36) -> 0.4815292 | K33: =K37*(1+K36) -> 0.4971789 | L33: =L37*(1+L36) -> 0.51333721 | M33: =M37*(1+M36) -> 0.53002067
C34: Inflation | E34: 0.0373 | F34: 0.0321 | G34: 0.083 | H34: 0.065 | I34: 0.049 | J34: 0.035 | K34: 0.0325 | L34: 0.0325 | M34: 0.0325
C35: Cumulated inflation (constant 2018) | E35: 0.0373 | F35: 0.07059733 | G35: 0.15945691 | H35: 0.23482161 | I35: 0.29532787 | J35: 0.34066434 | K35: 0.38423593 | L35: 0.4292236 | M35: 0.47567337
C36: Cumulated inflation (constant 2021) | E36: - | F36: - | G36: - | H36: =H34 -> 0.065 | I36: =(1+H36)*(1+I34)-1 -> 0.117185 | J36: =(1+I36)*(1+J34)-1 -> 0.15628647 | K36: =(1+J36)*(1+K34)-1 -> 0.19386579 | L36: =(1+K36)*(1+L34)-1 -> 0.23266642 | M36: =(1+L36)*(1+M34)-1 -> 0.27272808
C37: Real Yield per RPK BRL (constant 2018) | E37: =E33/(1+E35) -> 0.45234191 | F37: =F33/(1+F35) -> 0.41215715 | G37: =G33/(1+G35) -> 0.38483458 | H37: =AVERAGE($E$37:$G$37) -> 0.41644455 | I37: =AVERAGE($E$37:$G$37) -> 0.41644455 | J37: =AVERAGE($E$37:$G$37) -> 0.41644455 | K37: =AVERAGE($E$37:$G$37) -> 0.41644455 | L37: =AVERAGE($E$37:$G$37) -> 0.41644455 | M37: =AVERAGE($E$37:$G$37) -> 0.41644455
C38: Revenues mln BRL | E38: =E30*E32 -> 15710.735 | F38: =F30*F32 -> 6981.6613 | G38: =G30*G32 -> 9034.5731 | H38: =H33*H25/1000 -> 14533.81 | I38: =I33*I25/1000 -> 15592.544 | J38: =J33*J25/1000 -> 17159.684 | K38: =K33*K25/1000 -> 18388.007 | L38: =L33*L25/1000 -> 19524.072 | M38: =M33*M25/1000 -> 20735.047
C39: growth rate % | F39: =F38/E38-1 -> -0.55561206 | G39: =G38/F38-1 -> 0.29404345 | H39: =H38/G38-1 -> 0.60868809 | I39: =I38/H38-1 -> 0.072846286 | J39: =J38/I38-1 -> 0.10050574 | K39: =K38/J38-1 -> 0.071581891 | L39: =L38/K38-1 -> 0.061782932 | M39: =M38/L38-1 -> 0.062024687
C40: CAGR 2020-2027 | D40: =(M38/E38)^(1/8)-1 -> 0.03529368
C41: CAGR 2022-2027, 5 years | D41: =(M38/I38)^(1/5)-1 -> 0.058662686
B43: Futures | C43: We convert Brazilian Revenues in $ by using futures on the exchange rate
C44: Futures BRL/USD | H44: =1/Futures_provvisorio!B3 -> 5.3561864 | I44: =1/AVERAGE(Futures_provvisorio!B4:B15) -> 5.5437494 | J44: =1/AVERAGE(Futures_provvisorio!B16:B27) -> 5.9161387 | K44: =1/AVERAGE(Futures_provvisorio!B28:B39) -> 6.2904621 | L44: =1/AVERAGE(Futures_provvisorio!B40:B51) -> 6.6644452 | M44: =1/AVERAGE(Futures_provvisorio!B52:B62) -> 7.0226961
B46: Brazilian Rev $mil | C46: Brazilian Rev in $mln | H46: =H38/H44 -> 2713.4623 | I46: =I38/I44 -> 2812.6351 | J46: =J38/J44 -> 2900.4872 | K46: =K38/K44 -> 2923.1568 | L46: =L38/L44 -> 2929.587 | M46: =M38/M44 -> 2952.5764
A50: SSC Revenues (USD) | B50: SSC number of passengers | C50: Regressed yearly ln(Number of Passengers) over yearly ln(real GDP_t) and ln(Jet fuel price_t) To find elasticities: \epsilon_1=2.44, \epsilon_2=-0.35 | E50: =SSC_Mkt_Sh!K25 -> 58822802 | F50: =SSC_Mkt_Sh!L25 -> 21481765 | G50: =SSC_Mkt_Sh!M25 -> 41531109 | H50: =SSC_Mkt_Sh!N25 -> 61695850 | I50: =SSC_Mkt_Sh!O25 -> 65504040 | J50: =SSC_Mkt_Sh!P25 -> 73662984 | K50: =SSC_Mkt_Sh!Q25 -> 75470842 | L50: =SSC_Mkt_Sh!R25 -> 77323069 | M50: =SSC_Mkt_Sh!S25 -> 79220753
C51: Growth Rates | F51: =F50/E50-1 -> -0.63480548 | G51: =G50/F50-1 -> 0.93331921 | H51: =H50/G50-1 -> 0.48553341 | I51: =I50/H50-1 -> 0.061725216 | J51: =J50/I50-1 -> 0.12455636 | K51: =K50/J50-1 -> 0.024542282 | L51: =L50/K50-1 -> 0.024542282 | M51: =M50/L50-1 -> 0.024542282
C52: Real SSC GDP forecasted for 2022-2027 | H52: 0.01 | I52: 0.01 | J52: 0.01 | K52: 0.01 | L52: 0.01 | M52: 0.01
C53: JET FUEL US$ per gallon | H53: 3.43 | I53: 3.1 | J53: 2.38 | K53: 2.38 | L53: 2.38 | M53: =L53 -> 2.38
C54: CAGR 2022-2027, 5 years | D54: =(M50/H50)^(1/5)-1 -> 0.051275645
C55: CAGR 8 years 2019-2028, Latam Estimate | D55: =4.1% -> 0.041
C56: CAGR 8 Years 2020-2027 our estimate | D56: =(M50/E50)^(1/8)-1 -> 0.037914687
C57: R^2 regression | D57: =SSC_regression!K10 -> 0.98403155
C58: Recovery Rate market to pre pandemic Levels (2019) vs 2022 | D58: =H50/E50 -> 1.0488424
B60: Market share computation | C60: Assuming Latam, Avianca and their LCC competitors will keep their actual Number of Passengers as of 2021, their future market share will be driven by their contribution to the market growth. This contribution is estimated by a backword looking smoothed average.
C62: Market Share
C63: =SSC_Mkt_Sh!A54 -> LATAM | E63: =SSC_Mkt_Sh!K54 -> 0.39640235 | F63: =SSC_Mkt_Sh!L54 -> 0.41564546 | G63: =SSC_Mkt_Sh!M54 -> 0.40412995 | H63: =SSC_Mkt_Sh!N54 -> 0.38649271 | I63: =SSC_Mkt_Sh!O54 -> 0.38438087 | J63: =SSC_Mkt_Sh!P54 -> 0.38059135 | K63: =SSC_Mkt_Sh!Q54 -> 0.37986256 | L63: =SSC_Mkt_Sh!R54 -> 0.37915123 | M63: =SSC_Mkt_Sh!S54 -> 0.37845693
C64: =SSC_Mkt_Sh!A55 -> LOW COST CARRIERS | E64: =SSC_Mkt_Sh!K55 -> 0.28651847 | F64: =SSC_Mkt_Sh!L55 -> 0.34612012 | G64: =SSC_Mkt_Sh!M55 -> 0.34663341 | H64: =SSC_Mkt_Sh!N55 -> 0.40462054 | I64: =SSC_Mkt_Sh!O55 -> 0.41156379 | J64: =SSC_Mkt_Sh!P55 -> 0.42402285 | K64: =SSC_Mkt_Sh!Q55 -> 0.42641894 | L64: =SSC_Mkt_Sh!R55 -> 0.42875764 | M64: =SSC_Mkt_Sh!S55 -> 0.43104032
C65: =SSC_Mkt_Sh!A56 -> AVIANCA | E65: =SSC_Mkt_Sh!K56 -> 0.26203779 | F65: =SSC_Mkt_Sh!L56 -> 0.20381193 | G65: =SSC_Mkt_Sh!M56 -> 0.2194064 | H65: =SSC_Mkt_Sh!N56 -> 0.16707703 | I65: =SSC_Mkt_Sh!O56 -> 0.16081122 | J65: =SSC_Mkt_Sh!P56 -> 0.14956779 | K65: =SSC_Mkt_Sh!Q56 -> 0.14740548 | L65: =SSC_Mkt_Sh!R56 -> 0.14529497 | M65: =SSC_Mkt_Sh!S56 -> 0.14323501
C66: =SSC_Mkt_Sh!A57 -> OTHERS | E66: =SSC_Mkt_Sh!K57 -> 0.055041394 | F66: =SSC_Mkt_Sh!L57 -> 0.034422497 | G66: =SSC_Mkt_Sh!M57 -> 0.029830241 | H66: =SSC_Mkt_Sh!N57 -> 0.041809719 | I66: =SSC_Mkt_Sh!O57 -> 0.043244115 | J66: =SSC_Mkt_Sh!P57 -> 0.045818013 | K66: =SSC_Mkt_Sh!Q57 -> 0.046313019 | L66: =SSC_Mkt_Sh!R57 -> 0.046796167 | M66: =SSC_Mkt_Sh!S57 -> 0.047267742
C68: Latam Passengers | E68: =SSC_Mkt_Sh!K29 -> 23317497 | F68: =SSC_Mkt_Sh!L29 -> 8928798 | G68: =SSC_Mkt_Sh!M29 -> 16783965 | H68: =H63*H50 -> 23844996 | I68: =I63*I50 -> 25178500 | J68: =J63*J50 -> 28035495 | K68: =K63*K50 -> 28668547 | L68: =L63*L50 -> 29317136 | M68: =M63*M50 -> 29981643
C69: With our estimates Latam recovers in 2022 vs 2019 | D69: =H68/E68 -> 1.0226225
B72: Revenue per passenger | C72: Peru Revenues mln | E72: 802 | F72: 297.5 | G72: 503.6
C73: Colombia Revenues mln | E73: 380.4 | F73: 177 | G73: 368.5
C74: Ecuador Revenues mln | E74: 203.3 | F74: 112.6 | G74: 163
C75: Chile Revenues mln | E75: 1547 | F75: 638.2 | G75: 794.1
C76: Revenues SSC USD mln | E76: =SUM(E72:E75) -> 2932.7 | F76: =SUM(F72:F75) -> 1225.3 | G76: =SUM(G72:G75) -> 1829.2
C79: Average revenue per passenger USD | E79: =E76*10^6/E68 -> 125.7725 | F79: =F76*10^6/F68 -> 137.23012 | G79: =G76*10^6/G68 -> 108.98497 | H79: =I79/(1+H80) -> 119.72631 | I79: =J79/(1+I80) -> 128.9213 | J79: =K79/(1+J80) -> 132.60844 | K79: =L79/(1+K80) -> 135.6054 | L79: =M79/(1+L80) -> 138.3175 | M79: =AVERAGE(E79,G79)*(1+M81) -> 141.08385
C80: Inflation USA | H80: 0.0768 | I80: 0.0286 | J80: 0.0226 | K80: 0.02 | L80: 0.02 | M80: 0.02
C81: cumulated inflation USA | H81: =H80 -> 0.0768 | I81: =(1+H81)*(1+I80)-1 -> 0.10759648 | J81: =(1+I81)*(1+J80)-1 -> 0.13262816 | K81: =(1+J81)*(1+K80)-1 -> 0.15528072 | L81: =(1+K81)*(1+L80)-1 -> 0.17838634 | M81: =(1+L81)*(1+M80)-1 -> 0.20195406
C82: Real revenues per passenger USD | E82: - | F82: - | G82: - | H82: =AVERAGE($E$79:$G$79) -> 123.99587 | I82: =AVERAGE($E$79:$G$79) -> 123.99587 | J82: =AVERAGE($E$79:$G$79) -> 123.99587 | K82: =AVERAGE($E$79:$G$79) -> 123.99587 | L82: =AVERAGE($E$79:$G$79) -> 123.99587 | M82: =AVERAGE($E$79:$G$79) -> 123.99587
B84: Revenues mln | C84: Revenues USDmln | E84: =E68*E79/1000000 -> 2932.7 | F84: =F68*F79/1000000 -> 1225.3 | G84: =G68*G79/1000000 -> 1829.2 | H84: =H68*H79/1000000 -> 2854.8735 | I84: =I68*I79/1000000 -> 3246.0448 | J84: =J68*J79/1000000 -> 3717.7433 | K84: =K68*K79/1000000 -> 3887.6097 | L84: =L68*L79/1000000 -> 4055.0731 | M84: =M68*M79/1000000 -> 4229.9258
C85: CAGR (2020-2017) | D85: =(M84/H84)^(1/5)-1 -> 0.081805472
C86: CAGR (2019-2027) | D86: =(M84/E84)^(1/8)-1 -> 0.04684682
A88: International Revenues | B88: International Passengers | C88: Due to the difficulty of the estimate we applied 2,7% CAGR (2019-2028) as in industry reports (IATA) and LATAM to the number of passengers. We forecast full recovery of the international sector in 2023, due to (1) actual and potential travel restriction, (2) because we forecast a structural gap 15% in business travel to persist among the forecast horizon. | E88: =Int_Mkt_Sh!T14 -> 63150964 | F88: =Int_Mkt_Sh!U14 -> 17018290 | G88: =Int_Mkt_Sh!V14 -> 18479699 | H88: =Int_Mkt_Sh!W14 -> 24639599 | I88: =Int_Mkt_Sh!X14 -> 47363223 | J88: =Int_Mkt_Sh!Y14 -> 63150964 | K88: =Int_Mkt_Sh!Z14 -> 67800750 | L88: =Int_Mkt_Sh!AA14 -> 72792899 | M88: =Int_Mkt_Sh!AB14 -> 78152618
C89: Growth Rates | F89: =F88/E88-1 -> -0.73051417 | G89: =G88/F88-1 -> 0.085872846 | H89: =H88/G88-1 -> 0.33333333 | I89: =I88/H88-1 -> 0.92224003 | J89: =J88/I88-1 -> 0.33333333 | K89: =K88/J88-1 -> 0.073629698 | L89: =L88/K88-1 -> 0.073629698 | M89: =M88/L88-1 -> 0.073629698
C90: CAGR 2022-2027, 5 years | D90: =(M88/H88)^(1/5)-1 -> 0.25968507
C91: CAGR 8 years 2019-2028, Latam Estimate | D91: =4.1% -> 0.041
C92: CAGR 8 Years 2020-2027 our estimate | D92: =(M88/E88)^(1/8)-1 -> 0.027
C94: Recovery Rate market to pre pandemic Levels (2019) vs 2022 | D94: =H88/E88 -> 0.39016979
B96: Market Share andGlobal Alliances | C96: Assuming Latam will benefit from the Join Venture with Delta, for being the first mover in proposing such a close alliance and for the similairty of the two airlines' value proposition, we expect Latam to gain a total of 7% of the International South American Market within 2025, and then stabilizing due to the rise of the new LCC group Abra and other alliances between North and South american airlines.
C97: Market Share
C98: Joint venture LATAM Delta | E98: =Int_Mkt_Sh!C5 -> 0.30845618 | F98: =Int_Mkt_Sh!D5 -> 0.29432916 | G98: =Int_Mkt_Sh!E5 -> 0.20521514 | H98: =Int_Mkt_Sh!F5 -> 0.2052477 | I98: =Int_Mkt_Sh!G5 -> 0.2752477 | J98: =Int_Mkt_Sh!H5 -> 0.3052477 | K98: =Int_Mkt_Sh!I5 -> 0.3052477 | L98: =Int_Mkt_Sh!J5 -> 0.3052477 | M98: =Int_Mkt_Sh!K5 -> 0.3052477
C99: =Int_Mkt_Sh!A8 -> Abra group | E99: =Int_Mkt_Sh!C8 -> 0.17050956 | F99: =Int_Mkt_Sh!D8 -> 0.14956503 | G99: =Int_Mkt_Sh!E8 -> 0.1489448 | H99: =Int_Mkt_Sh!F8 -> 0.28272309 | I99: =Int_Mkt_Sh!G8 -> 0.25272309 | J99: =Int_Mkt_Sh!H8 -> 0.24272309 | K99: =Int_Mkt_Sh!I8 -> 0.25272309 | L99: =Int_Mkt_Sh!J8 -> 0.28272309 | M99: =Int_Mkt_Sh!K8 -> 0.29272309
C100: =Int_Mkt_Sh!A11 -> Copa Holdings | E100: =Int_Mkt_Sh!C11 -> 0.036601547 | F100: =Int_Mkt_Sh!D11 -> 0.043024534 | G100: =Int_Mkt_Sh!E11 -> 0.12499782 | H100: =Int_Mkt_Sh!F11 -> 0.10086714 | I100: =Int_Mkt_Sh!G11 -> 0.090867135 | J100: =Int_Mkt_Sh!H11 -> 0.085867135 | K100: =Int_Mkt_Sh!I11 -> 0.085867135 | L100: =Int_Mkt_Sh!J11 -> 0.085867135 | M100: =Int_Mkt_Sh!K11 -> 0.085867135
C101: =Int_Mkt_Sh!A14 -> Jet Smart | E101: =Int_Mkt_Sh!C14 -> 0.0090639471 | F101: =Int_Mkt_Sh!D14 -> 0.015284203 | G101: =Int_Mkt_Sh!E14 -> 0.011019876 | H101: =Int_Mkt_Sh!F14 -> 0.020714661 | I101: =Int_Mkt_Sh!G14 -> 0.020714661 | J101: =Int_Mkt_Sh!H14 -> 0.020714661 | K101: =Int_Mkt_Sh!I14 -> 0.020714661 | L101: =Int_Mkt_Sh!J14 -> 0.020714661 | M101: =Int_Mkt_Sh!K14 -> 0.020714661
C102: =Int_Mkt_Sh!A17 -> American Airlines | E102: =Int_Mkt_Sh!C17 -> 0.04347324 | F102: =Int_Mkt_Sh!D17 -> 0.050153805 | G102: =Int_Mkt_Sh!E17 -> 0.12049698 | H102: =Int_Mkt_Sh!F17 -> 0.072666224 | I102: =Int_Mkt_Sh!G17 -> 0.062666224 | J102: =Int_Mkt_Sh!H17 -> 0.057666224 | K102: =Int_Mkt_Sh!I17 -> 0.052666224 | L102: =Int_Mkt_Sh!J17 -> 0.052666224 | M102: =Int_Mkt_Sh!K17 -> 0.055166224
C103: =Int_Mkt_Sh!A20 -> United Airlines | E103: =Int_Mkt_Sh!C20 -> 0.022141816 | F103: =Int_Mkt_Sh!D20 -> 0.025728554 | G103: =Int_Mkt_Sh!E20 -> 0.032756053 | H103: =Int_Mkt_Sh!F20 -> 0.015392781 | I103: =Int_Mkt_Sh!G20 -> 0.012892781 | J103: =Int_Mkt_Sh!H20 -> 0.012892781 | K103: =Int_Mkt_Sh!I20 -> 0.012892781 | L103: =Int_Mkt_Sh!J20 -> 0.010392781 | M103: =Int_Mkt_Sh!K20 -> 0.012892781
C104: =Int_Mkt_Sh!A23 -> OTHERS | E104: =Int_Mkt_Sh!C23 -> 0.38938858 | F104: =Int_Mkt_Sh!D23 -> 0.39392971 | G104: =Int_Mkt_Sh!E23 -> 0.33647572 | H104: =Int_Mkt_Sh!F23 -> 0.26752329 | I104: =Int_Mkt_Sh!G23 -> 0.25002329 | J104: =Int_Mkt_Sh!H23 -> 0.24002329 | K104: =Int_Mkt_Sh!I23 -> 0.23502329 | L104: =Int_Mkt_Sh!J23 -> 0.20752329 | M104: =Int_Mkt_Sh!K23 -> 0.19252329
C106: Latam | E106: =Int_Mkt_Sh!S18 -> 0.29948473 | F106: =Int_Mkt_Sh!T18 -> 0.29264907 | G106: =Int_Mkt_Sh!U18 -> 0.27591979 | H106: =Int_Mkt_Sh!V18 -> 0.1800499 | I106: =Int_Mkt_Sh!W18 -> 0.18764017 | J106: =Int_Mkt_Sh!X18 -> 0.25163509 | K106: =Int_Mkt_Sh!Y18 -> 0.27906149 | L106: =Int_Mkt_Sh!Z18 -> 0.27906149 | M106: =Int_Mkt_Sh!AA18 -> 0.27906149
B108: Revenue per passenger | C108: Argentina | E108: 585 | F108: 172.2 | G108: 75.5
C109: United States | E109: 1004.2 | F109: 505.1 | G109: 578
C110: Europe | E110: 726.2 | F110: 338.6 | G110: 376.9
C111: Asia Pacific and rest of Latin Maerica | E111: 872.2 | F111: 378.4 | G111: 360 | H111: 474
C112: International Revenues USDm | E112: =SUM(E108:E111) -> 3187.6 | F112: =SUM(F108:F111) -> 1394.3 | G112: =SUM(G108:G111) -> 1390.4
C113: LATAM International Passengers | E113: =Int_Mkt_Sh!T19 -> 18481071 | F113: =Int_Mkt_Sh!U19 -> 4695683 | G113: =Int_Mkt_Sh!V19 -> 3327268 | H113: =Int_Mkt_Sh!W19 -> 4623378.4 | I113: =Int_Mkt_Sh!X19 -> 11918249 | J113: =Int_Mkt_Sh!Y19 -> 17623002 | K113: =Int_Mkt_Sh!Z19 -> 18920579 | L113: =Int_Mkt_Sh!AA19 -> 20313695 | M113: =Int_Mkt_Sh!AB19 -> 21809386
C114: Average revenue per passenger | E114: =E112*10^6/E113 -> 172.47918 | F114: =F112*10^6/F113 -> 296.93231 | G114: =G112*10^6/G113 -> 417.88038 | H114: 474 | I114: =I120 -> 267.45539 | J114: =J120*(1+J116) -> 204.93391 | K114: =K120*(1+K116) -> 199.21345 | L114: =L120*(1+L116) -> 203.18048 | M114: =M120*(1+M116) -> 207.31998
C115: Inflation
C116: Cumulated inflation USA (2021) | H116: 0.0768 | I116: 0.108 | J116: 0.133 | K116: 0.155 | L116: 0.178 | M116: 0.202
C117: Real revenues per passenger | E117: =E114/(E113*E10) -> 5.0176065e-06 | F117: =F114/(F113*F10) -> 5.7486518e-05 | G117: =G114/(G113*G10) -> 7.4315172e-05 | H117: =(G117)*100 -> 0.0074315172 | I117: =(0.001%)*100 -> 0.001 | J117: =(0.001%)*100 -> 0.001 | K117: =(0.001%)*100 -> 0.001 | L117: =(0.001%)*100 -> 0.001 | M117: =(E118*(1.13))*100 -> 0.0010546005
E118: =E114/E113 -> 9.3327482e-06 | F118: =F114/F113 -> 6.3235169e-05 | G118: =G114/G113 -> 0.00012559264
E119: =E118*E113 -> 172.47918 | H119: =H114/H113 -> 0.00010252243 | I119: =H119*(1+$L$120) -> 0.017785508 | J119: =I119*(1+$L$120) -> 3.0854153 | K119: =J119*(1+$L$120) -> 535.25533 | L119: =K119*(1+$L$120) -> 92855.656 | M119: =E118 -> 9.3327482e-06
E120: =E117*E113*E10 -> 172.47918 | H120: =H114/(1+H116) -> 440.19316 | I120: =$E$114*$E$113/I113 -> 267.45539 | J120: =$E$114*$E$113/J113 -> 180.87724 | K120: =$E$120 -> 172.47918 | L120: =$E$120 -> 172.47918 | M120: =$E$120 -> 172.47918
K121: =J122*(1+K116) -> 4171.3412 | L121: =K122*(1+L116) -> 4440.1574 | M121: =L122*(1+M116) -> 4961.0702
B122: Revenues mln | C122: Nominal Revenues International mln | E122: =E112 -> 3187.6 | F122: =F112 -> 1394.3 | G122: =G112 -> 1390.4 | H122: =H113*H114/(10^6) -> 2191.4814 | I122: =I113*I114/(10^6) -> 3187.6 | J122: =J113*J114/(10^6) -> 3611.5508 | K122: =K113*K114/(10^6) -> 3769.2338 | L122: =L113*L114/(10^6) -> 4127.3462 | M122: =M113*M114/(10^6) -> 4521.5214
I123: =$E$113/$I$113*$E$114 -> 267.45539 | J123: =$E$113/$I$113*$E$114 -> 267.45539 | K123: =$E$113/$I$113*$E$114 -> 267.45539 | L123: =$E$113/$I$113*$E$114 -> 267.45539 | M123: =$E$113/$I$113*$E$114 -> 267.45539
H124: CAGR | I124: =(M120/H120)^(1/5)-1 -> -0.17087754
H125: 100
A126: TOTAL REVENUES | E126: =E122+E84+E46 -> 6120.3 | F126: =F122+F84+F46 -> 2619.6 | G126: =G122+G84+G46 -> 3219.6 | H126: =H122+H84+H46 -> 7759.8172 | I126: =I122+I84+I46 -> 9246.2799 | J126: =J122+J84+J46 -> 10229.781 | K126: =K122+K84+K46 -> 10580 | L126: =L122+L84+L46 -> 11112.006 | M126: =M122+M84+M46 -> 11704.024
H127: =+H122/H126 -> 0.28241404 | I127: =+I122/I126 -> 0.34474405 | J127: =+J122/J126 -> 0.35304282 | K127: =+K122/K126 -> 0.35626027 | L127: =+L122/L126 -> 0.37143123 | M127: =+M122/M126 -> 0.38632197
...

Sheet Pro_Forma IS
A1: Item | C1: 2017 | D1: 2018 | E1: 2019 | F1: 2020 | G1: 2021 | H1: 2022E | I1: 2023F | J1: 2024F | K1: 2025F | L1: 2026F | M1: 2027F
C2: 2017 | D2: 2018 | E2: 2019 | F2: 2020 | G2: 2021 | H2: 2022 | I2: 2023 | J2: 2024 | K2: 2025 | L2: 2026 | M2: 2027
B3: REVENUES 000$
B4: Net Passenger Revenue | C4: =SS!AL9 -> 8494477 | D4: =SS!AW9 -> 8708988 | E4: =SS!BB9 -> 9005629 | F4: =SS!BG9 -> 2713774 | G4: =SS!BL9 -> 3342380.6 | H4: ='Forecast Drivers'!H126*10^3 -> 7759817.2 | I4: ='Forecast Drivers'!I126*10^3 -> 9246279.9 | J4: ='Forecast Drivers'!J126*10^3 -> 10229781 | K4: ='Forecast Drivers'!K126*10^3 -> 10580000 | L4: ='Forecast Drivers'!L126*10^3 -> 11112006 | M4: ='Forecast Drivers'!M126*10^3 -> 11704024
B5: Net Cargo Revenue | C5: =Margin!I4 -> 1119430 | D5: =Margin!J4 -> 1186468 | E5: =Margin!K4 -> 1064434 | F5: =Margin!L4 -> 1209893 | G5: =Margin!M4 -> 1541634.6 | H5: ='Drivers Cargo'!H24*10^3 -> 1852457.2 | I5: ='Drivers Cargo'!I24*10^3 -> 2057815.6 | J5: ='Drivers Cargo'!J24*10^3 -> 1793929.6 | K5: ='Drivers Cargo'!K24*10^3 -> 1854026.3 | L5: ='Drivers Cargo'!L24*10^3 -> 1714244.3 | M5: ='Drivers Cargo'!M24*10^3 -> 1771671.4
B6: Other | C6: =Margin!I5 -> 549889 | D6: =Margin!J5 -> 472758 | E6: =Margin!K5 -> 360864 | F6: =Margin!L5 -> 411002 | G6: =Margin!M5 -> 227331.16 | H6: - | I6: - | J6: - | K6: - | L6: - | M6: -
B7: TOTAL OPERATING REVENUES | C7: =SUM(C4:C6) -> 10163796 | D7: =SUM(D4:D6) -> 10368214 | E7: =SUM(E4:E6) -> 10430927 | F7: =SUM(F4:F6) -> 4334669 | G7: =SUM(G4:G6) -> 5111346.3 | H7: =SUM(H4:H6) -> 9612274.4 | I7: =SUM(I4:I6) -> 11304095 | J7: =SUM(J4:J6) -> 12023711 | ... M7: =SUM(M4:M6) -> 13475695
B9: EXPENSES
B10: Wages and Benefits | C10: =Margin!I9 -> -2023634 | D10: =Margin!J9 -> -1819969 | E10: =Margin!K9 -> -1794762 | F10: =Margin!L9+150000 -> -812060 | G10: =Margin!M9 -> -1041899.8 | H10: =E10*(1-27%) -> -1310176.3 | I10: =$H$10/$H$7*I7*(1.02) -> -1571591.1 | J10: =$H$10/$H$7*J7*(1.02) -> -1671638.1 | K10: =$H$10/$H$7*K7*(1.02) -> -1728683.7 | L10: =$H$10/$H$7*L7*(1.02) -> -1783214 | M10: =$H$10/$H$7*M7*(1.02) -> -1873505.2
B11: Aircraft fuel | C11: =Margin!I10 -> -2318815 | D11: =Margin!J10 -> -2983028 | E11: =Margin!K10 -> -2929008 | F11: =Margin!L10 -> -1045343 | G11: =Margin!M10 -> -1487776.5 | H11: =-(SUM('Forecast Drivers'!H25,'Forecast Drivers'!H68,'Forecast Drivers'!H113)/SUM('Forecast Drivers'!$E$25,'Forecast Drivers'!$E$68,'Forecast Drivers'!$E$113))*ABS($E$11)*'Forecast Drivers'!H10/'Forecast Drivers'!$E$10*((1-5.3%)^(1/9))^(H2-$G$2) -> -4367234.7 | I11: =-(SUM('Forecast Drivers'!I25,'Forecast Drivers'!I68,'Forecast Drivers'!I113)/SUM('Forecast Drivers'!$E$25,'Forecast Drivers'!$E$68,'Forecast Drivers'!$E$113))*ABS($E$11)*'Forecast Drivers'!I10/'Forecast Drivers'!$E$10*((1-5.3%)^(1/9))^(I2-$G$2) -> -4523759.4 | J11: =-(SUM('Forecast Drivers'!J25,'Forecast Drivers'!J68,'Forecast Drivers'!J113)/SUM('Forecast Drivers'!$E$25,'Forecast Drivers'!$E$68,'Forecast Drivers'!$E$113))*ABS($E$11)*'Forecast Drivers'!J10/'Forecast Drivers'!$E$10*((1-5.3%)^(1/9))^(J2-$G$2) -> -3974406.7 | K11: =-(SUM('Forecast Drivers'!K25,'Forecast Drivers'!K68,'Forecast Drivers'!K113)/SUM('Forecast Drivers'!$E$25,'Forecast Drivers'!$E$68,'Forecast Drivers'!$E$113))*ABS($E$11)*'Forecast Drivers'!K10/'Forecast Drivers'!$E$10*((1-5.3%)^(1/9))^(K2-$G$2) -> -4109796.3 | L11: =-(SUM('Forecast Drivers'!L25,'Forecast Drivers'!L68,'Forecast Drivers'!L113)/SUM('Forecast Drivers'!$E$25,'Forecast Drivers'!$E$68,'Forecast Drivers'!$E$113))*ABS($E$11)*'Forecast Drivers'!L10/'Forecast Drivers'!$E$10*((1-5.3%)^(1/9))^(L2-$G$2) -> -4234285.2 | M11: =-(SUM('Forecast Drivers'!M25,'Forecast Drivers'!M68,'Forecast Drivers'!M113)/SUM('Forecast Drivers'!$E$25,'Forecast Drivers'!$E$68,'Forecast Drivers'!$E$113))*ABS($E$11)*'Forecast Drivers'!M10/'Forecast Drivers'!$E$10*((1-5.3%)^(1/9))^(M2-$G$2) -> -4364667.2
B12: Selling expenses | C12: =Margin!I11+(Margin!I17-SUM(C18:C19)) -> -395521 | D12: =Margin!J11+(Margin!J17-SUM(D18:D19)) -> -142719 | E12: =Margin!K11+(Margin!K17-SUM(E18:E19)) -> -354679 | F12: =Margin!L11+(Margin!L17-SUM(F18:F19)-150000) -> -34992 | G12: =Margin!M11+(Margin!M17-SUM(G18:G19)) -> -73315.183 | H12: =-SUM('Forecast Drivers'!H25,'Forecast Drivers'!H68,'Forecast Drivers'!H113)/SUM('Forecast Drivers'!$E$25,'Forecast Drivers'!$E$68,'Forecast Drivers'!$E$113)*ABS($E$12) -> -288514.77 | I12: =-SUM('Forecast Drivers'!I25,'Forecast Drivers'!I68,'Forecast Drivers'!I113)/SUM('Forecast Drivers'!$E$25,'Forecast Drivers'!$E$68,'Forecast Drivers'!$E$113)*ABS($E$12) -> -332675.81 | J12: =-SUM('Forecast Drivers'!J25,'Forecast Drivers'!J68,'Forecast Drivers'!J113)/SUM('Forecast Drivers'!$E$25,'Forecast Drivers'!$E$68,'Forecast Drivers'!$E$113)*ABS($E$12) -> -383006.86 | K12: =-SUM('Forecast Drivers'!K25,'Forecast Drivers'!K68,'Forecast Drivers'!K113)/SUM('Forecast Drivers'!$E$25,'Forecast Drivers'!$E$68,'Forecast Drivers'!$E$113)*ABS($E$12) -> -398457.79 | L12: =-SUM('Forecast Drivers'!L25,'Forecast Drivers'!L68,'Forecast Drivers'!L113)/SUM('Forecast Drivers'!$E$25,'Forecast Drivers'!$E$68,'Forecast Drivers'!$E$113)*ABS($E$12) -> -413018.89 | M12: =-SUM('Forecast Drivers'!M25,'Forecast Drivers'!M68,'Forecast Drivers'!M113)/SUM('Forecast Drivers'!$E$25,'Forecast Drivers'!$E$68,'Forecast Drivers'!$E$113)*ABS($E$12) -> -428320.37
B13: Depreciation and Amortization | C13: =Margin!I12 -> -1001625 | D13: =Margin!J12 -> -1372628 | E13: =Margin!K12 -> -1469976 | F13: =Margin!L12 -> -1389387 | G13: =Margin!M12 -> -1165394.2 | H13: =-'Capex.'!AV94 -> -1183741.6 | I13: =-'Capex.'!AW94 -> -1248559.3 | J13: =-'Capex.'!AX94 -> -1275538.5 | K13: =-'Capex.'!AY94 -> -1319446.7 | L13: =-'Capex.'!AZ94 -> -1363935.4 | M13: =-'Capex.'!BA94 -> -1424148.7
B14: Other Rental and Landing Fees | C14: =Margin!I13 -> -1172129 | D14: =Margin!J13 -> -1206881 | E14: =Margin!K13 -> -1275859 | F14: =Margin!L13 -> -720004 | G14: =Margin!M13 -> -755187.96 | H14: =-(SUM('Forecast Drivers'!H25,'Forecast Drivers'!H68,'Forecast Drivers'!H113)/SUM('Forecast Drivers'!$E$25,'Forecast Drivers'!$E$68,'Forecast Drivers'!$E$113))*ABS($E$14) -> -1037851.6 | I14: =-(SUM('Forecast Drivers'!I25,'Forecast Drivers'!I68,'Forecast Drivers'!I113)/SUM('Forecast Drivers'!$E$25,'Forecast Drivers'!$E$68,'Forecast Drivers'!$E$113))*ABS($E$14) -> -1196708.6 | J14: =-(SUM('Forecast Drivers'!J25,'Forecast Drivers'!J68,'Forecast Drivers'!J113)/SUM('Forecast Drivers'!$E$25,'Forecast Drivers'!$E$68,'Forecast Drivers'!$E$113))*ABS($E$14) -> -1377760.6 | K14: =-(SUM('Forecast Drivers'!K25,'Forecast Drivers'!K68,'Forecast Drivers'!K113)/SUM('Forecast Drivers'!$E$25,'Forecast Drivers'!$E$68,'Forecast Drivers'!$E$113))*ABS($E$14) -> -1433341 | L14: =-(SUM('Forecast Drivers'!L25,'Forecast Drivers'!L68,'Forecast Drivers'!L113)/SUM('Forecast Drivers'!$E$25,'Forecast Drivers'!$E$68,'Forecast Drivers'!$E$113))*ABS($E$14) -> -1485720.5 | M14: =-(SUM('Forecast Drivers'!M25,'Forecast Drivers'!M68,'Forecast Drivers'!M113)/SUM('Forecast Drivers'!$E$25,'Forecast Drivers'!$E$68,'Forecast Drivers'!$E$113))*ABS($E$14) -> -1540763.3
B15: Passenger Services | C15: =Margin!I14 -> -288662 | D15: =Margin!J14 -> -280279 | E15: =Margin!K14 -> -261330 | F15: =Margin!L14 -> -97689 | G15: =Margin!M14 -> -77362.938 | H15: =-SUM('Forecast Drivers'!H25,'Forecast Drivers'!H68,'Forecast Drivers'!H113)/SUM('Forecast Drivers'!$E$25,'Forecast Drivers'!$E$68,'Forecast Drivers'!$E$113)*ABS($E$15) -> -212579.73 | I15: =-SUM('Forecast Drivers'!I25,'Forecast Drivers'!I68,'Forecast Drivers'!I113)/SUM('Forecast Drivers'!$E$25,'Forecast Drivers'!$E$68,'Forecast Drivers'!$E$113)*ABS($E$15)*1.05 -> -257373.79 | J15: =-SUM('Forecast Drivers'!J25,'Forecast Drivers'!J68,'Forecast Drivers'!J113)/SUM('Forecast Drivers'!$E$25,'Forecast Drivers'!$E$68,'Forecast Drivers'!$E$113)*ABS($E$15)*1.05 -> -296312.27 | K15: =-SUM('Forecast Drivers'!K25,'Forecast Drivers'!K68,'Forecast Drivers'!K113)/SUM('Forecast Drivers'!$E$25,'Forecast Drivers'!$E$68,'Forecast Drivers'!$E$113)*ABS($E$15)*1.05 -> -308265.85 | L15: =-SUM('Forecast Drivers'!L25,'Forecast Drivers'!L68,'Forecast Drivers'!L113)/SUM('Forecast Drivers'!$E$25,'Forecast Drivers'!$E$68,'Forecast Drivers'!$E$113)*ABS($E$15)*1.05 -> -319531.01 | M15: =-SUM('Forecast Drivers'!M25,'Forecast Drivers'!M68,'Forecast Drivers'!M113)/SUM('Forecast Drivers'!$E$25,'Forecast Drivers'!$E$68,'Forecast Drivers'!$E$113)*ABS($E$15)*1.05 -> -331368.95
B16: Aircraft Rentals | C16: =Margin!I15 -> -579552 | D16: =Margin!J15 -> 0 | E16: =Margin!K15 -> 0 | F16: =Margin!L15 -> 0 | G16: =Margin!M15 -> -120629 | H16: -197000 | I16: -109000 | J16: -15000
B17: Aircraft maintenance | C17: =Margin!I16 -> -430824 | D17: =Margin!J16 -> -366627 | E17: =Margin!K16 -> -444612 | F17: =Margin!L16 -> -472382 | G17: =Margin!M16 -> -533738.55 | H17: =-SUM('Forecast Drivers'!H25,'Forecast Drivers'!H68,'Forecast Drivers'!H113)/SUM('Forecast Drivers'!$E$25,'Forecast Drivers'!$E$68,'Forecast Drivers'!$E$113)*ABS(E17) -> -361671.06 | I17: =-SUM('Forecast Drivers'!I25,'Forecast Drivers'!I68,'Forecast Drivers'!I113)/SUM('Forecast Drivers'!$E$25,'Forecast Drivers'!$E$68,'Forecast Drivers'!$E$113)*ABS(F17) -> -443076.88 | J17: =-SUM('Forecast Drivers'!J25,'Forecast Drivers'!J68,'Forecast Drivers'!J113)/SUM('Forecast Drivers'!$E$25,'Forecast Drivers'!$E$68,'Forecast Drivers'!$E$113)*ABS(G17) -> -576367.71 | K17: =-SUM('Forecast Drivers'!K25,'Forecast Drivers'!K68,'Forecast Drivers'!K113)/SUM('Forecast Drivers'!$E$25,'Forecast Drivers'!$E$68,'Forecast Drivers'!$E$113)*ABS(H17) -> -406312.89 | L17: =-SUM('Forecast Drivers'!L25,'Forecast Drivers'!L68,'Forecast Drivers'!L113)/SUM('Forecast Drivers'!$E$25,'Forecast Drivers'!$E$68,'Forecast Drivers'!$E$113)*ABS(I17) -> -515957.02 | M17: =-SUM('Forecast Drivers'!M25,'Forecast Drivers'!M68,'Forecast Drivers'!M113)/SUM('Forecast Drivers'!$E$25,'Forecast Drivers'!$E$68,'Forecast Drivers'!$E$113)*ABS(J17) -> -696037.91
B18: Administrative expenses | C18: -873000 | D18: -952800 | E18: -736300 | F18: -735200 | G18: -439494 | H18: =-SUM('Forecast Drivers'!H25,'Forecast Drivers'!H68,'Forecast Drivers'!H113)/SUM('Forecast Drivers'!$E$25,'Forecast Drivers'!$E$68,'Forecast Drivers'!$E$113)*ABS(E18) -> -598945.6 | I18: =-SUM('Forecast Drivers'!I25,'Forecast Drivers'!I68,'Forecast Drivers'!I113)/SUM('Forecast Drivers'!$E$25,'Forecast Drivers'!$E$68,'Forecast Drivers'!$E$113)*ABS(F18) -> -689590.46 | J18: =-SUM('Forecast Drivers'!J25,'Forecast Drivers'!J68,'Forecast Drivers'!J113)/SUM('Forecast Drivers'!$E$25,'Forecast Drivers'!$E$68,'Forecast Drivers'!$E$113)*ABS(G18) -> -474595.94 | K18: =-SUM('Forecast Drivers'!K25,'Forecast Drivers'!K68,'Forecast Drivers'!K113)/SUM('Forecast Drivers'!$E$25,'Forecast Drivers'!$E$68,'Forecast Drivers'!$E$113)*ABS(H18) -> -672874.73 | L18: =-SUM('Forecast Drivers'!L25,'Forecast Drivers'!L68,'Forecast Drivers'!L113)/SUM('Forecast Drivers'!$E$25,'Forecast Drivers'!$E$68,'Forecast Drivers'!$E$113)*ABS(I18) -> -803018.75 | M18: =-SUM('Forecast Drivers'!M25,'Forecast Drivers'!M68,'Forecast Drivers'!M113)/SUM('Forecast Drivers'!$E$25,'Forecast Drivers'!$E$68,'Forecast Drivers'!$E$113)*ABS(J18) -> -573135.45
B19: General expenses | C19: -365500 | D19: -356300 | E19: -422800 | F19: -692900 | G19: -535824 | H19: =AVERAGE($E$19:$G$19) -> -550508 | I19: =H19*1.02 -> -561518.16 | J19: =I19*1.02 -> -572748.52 | K19: =J19*1.02 -> -584203.49 | L19: =K19*1.02 -> -595887.56 | M19: =L19*1.02 -> -607805.31
B20: TOTAL OPERATING EXPENSES | C20: =SUM(C10:C19) -> -9449262 | D20: =SUM(D10:D19) -> -9481231 | E20: =SUM(E10:E19) -> -9689326 | F20: =SUM(F10:F19) -> -5999957 | G20: =SUM(G10:G19) -> -6230622.2 | H20: =SUM(H10:H19) -> -10108223 | I20: =SUM(I10:I19) -> -10933854 | J20: =SUM(J10:J19) -> -10617375 | ... M20: =SUM(M10:M19) -> -11839752
B22: OPERATING INCOME (LOSS) | C22: =C7+C20 -> 714534 | D22: =D7+D20 -> 886983 | E22: =E7+E20 -> 741601 | F22: =F7+F20 -> -1665288 | G22: =G7+G20 -> -1119275.8 | H22: =H7+H20 -> -495948.82 | I22: =I7+I20 -> 370241.95 | J22: =J7+J20 -> 1406335.7 | ... M22: =M7+M20 -> 1635942.6
B23: Operating Margin | C23: =C22/C7 -> 0.070301883 | D23: =D22/D7 -> 0.085548292 | E23: =E22/E7 -> 0.071096366 | F23: =F22/F7 -> -0.38417882 | G23: =G22/G7 -> -0.21897867 | H23: =H22/H7 -> -0.051595366 | I23: =I22/I7 -> 0.032752904 | J23: =J22/J7 -> 0.11696354 | ... M23: =M22/M7 -> 0.1213995
H24: 1158 | I24: 2003 | J24: 2429 | K24: 2773 | L24: 3087 | M24: 3310
B25: EBITDAR | C25: =C22-C16-C13 -> 2295711 | D25: =D22-D16-D13 -> 2259611 | E25: =E22-E16-E13 -> 2211577 | F25: =F22-F16-F13 -> -275901 | G25: =G22-G16-G13 -> 166747.32 | H25: =H7+SUM(H10:H12,H14:H15,H17:H19) -> 884792.78 | I25: =I7+SUM(I10:I12,I14:I15,I17:I19) -> 1727801.3 | J25: =J7+SUM(J10:J12,J14:J15,J17:J19) -> 2696874.3 | K25: =K7+SUM(K10:K12,K14:K15,K17:K19) -> 2792090.8 | L25: =L7+SUM(L10:L12,L14:L15,L17:L19) -> 2675617.7 | M25: =M7+SUM(M10:M12,M14:M15,M17:M19) -> 3060091.2
B26: EBITDAR margin | C26: =C25/C7 -> 0.22587142 | D26: =D25/D7 -> 0.21793638 | E26: =E25/E7 -> 0.21202114 | F26: =F25/F7 -> -0.063649843 | G26: =G25/G7 -> 0.032622974 | H26: =H25/H7 -> 0.092048222 | I26: =I25/I7 -> 0.15284737 | J26: =J25/J7 -> 0.22429633 | ... M26: =M25/M7 -> 0.22708226
B28: EBITDA | C28: =C25+C16 -> 1716159 | D28: =D25+D16 -> 2259611 | E28: =E25+E16 -> 2211577 | F28: =F25+F16 -> -275901 | G28: =G25+G16 -> 46118.32 | H28: =H25+H16 -> 687792.78 | I28: =I25+I16 -> 1618801.3 | J28: =J25+J16 -> 2681874.3 | ... M28: =M25+M16 -> 3060091.2
B29: EBITDA Margin | C29: =C28/C7 -> 0.1688502 | D29: =D28/D7 -> 0.21793638 | E29: =E28/E7 -> 0.21202114 | F29: =F28/F7 -> -0.063649843 | G29: =G28/G7 -> 0.0090227344 | H29: =H28/H7 -> 0.071553593 | I29: =I28/I7 -> 0.14320485 | J29: =J28/J7 -> 0.2230488 | ... M29: =M28/M7 -> 0.22708226
B31: EBIT | C31: =C7+C20 -> 714534 | D31: =D7+D20 -> 886983 | E31: =E7+E20 -> 741601 | F31: =F7+F20 -> -1665288 | G31: =G7+G20 -> -1119275.8 | H31: =H7+H20 -> -495948.82 | I31: =I7+I20 -> 370241.95 | J31: =J7+J20 -> 1406335.7 | ... M31: =M7+M20 -> 1635942.6
B32: EBIT Margin | C32: =C31/C7 -> 0.070301883 | D32: =D31/D7 -> 0.085548292 | E32: =E31/E7 -> 0.071096366 | F32: =F31/F7 -> -0.38417882 | G32: =G31/G7 -> -0.21897867 | H32: =H31/H7 -> -0.051595366 | I32: =I31/I7 -> 0.032752904 | J32: =J31/J7 -> 0.11696354 | ... M32: =M31/M7 -> 0.1213995
B34: OTHER INCOME ( EXPENSE )
B35: Interest Expense Gross | H35: =-Sch_Deb!P43 -> -769659.25 | I35: =-Sch_Deb!Q43 -> #REF! | J35: =-Sch_Deb!R43 -> #REF! | K35: =-Sch_Deb!S43 -> #REF! | L35: =-Sch_Deb!T43 -> #REF! | M35: =-Sch_Deb!U43 -> #REF!
B36: Tax shield
B37: Interest expense net
B39: PROFIT BEFORE TAX AND MINORITY INTEREST | H39: =H31+H35 -> -1265608.1 | I39: =I31+I35 -> #REF! | J39: =J31+J35 -> #REF! | K39: =K31+K35 -> #REF! | L39: =L31+L35 -> #REF! | M39: =M31+M35 -> #REF!
B41: Income Tax Expense | H41: =-26%*H39 -> 329058.1 | I41: =-26%*I39 -> #REF! | J41: =-26%*J39 -> #REF! | K41: =-26%*K39 -> #REF! | L41: =-26%*L39 -> #REF! | M41: =-26%*M39 -> #REF!
B43: PROFIT BEFORE MINORITY INTEREST | H43: =H39+H41 -> -936549.97 | I43: =I39+I41 -> #REF! | J43: =J39+J41 -> #REF! | K43: =K39+K41 -> #REF! | L43: =L39+L41 -> #REF! | M43: =M39+M41 -> #REF!
B44: Attributable to:
B45: Shareholders
B46: Minority Interest
B49: PROFIT FOR THE YEAR
B50: Net Margin

Sheet Pro_Forma BS
A1: (in US$ millions except per share and capital stock data) | C1: 2017 | D1: 2018 | E1: 2019 | F1: 2020 | G1: 2021 | H1: 2022E | I1: 2023F | J1: 2024F | K1: 2025F | L1: 2026F | M1: 2027F
C2: 2017 | D2: 2018 | E2: 2019 | F2: 2020 | G2: 2021 | H2: 2022 | I2: 2023 | J2: 2024 | K2: 2025 | L2: 2026 | M2: 2027
B3: ASSETS | C3: 18797972 | D3: 20078722 | E3: 21087806 | F3: 15650090 | G3: 13312434
B4: Cash, and cash equivalents | C4: 1142004 | D4: 1081642 | E4: 1072579 | F4: 1695841 | G4: 1046835
B5: Other financial assets | C5: 559919 | D5: 383984 | E5: 499504 | F5: 50250 | G5: 101138
B6: Other non-financial assets | C6: 221188 | D6: 290476 | E6: 313449 | F6: 155892 | G6: 108368 | H6: =+'Pro_Forma IS'!H$7*'Working Cap'!$O$49 -> 248522.65 | I6: =+'Pro_Forma IS'!I$7*'Working Cap'!$O$49 -> 292264.2 | J6: =+'Pro_Forma IS'!J$7*'Working Cap'!$O$49 -> 310869.66 | K6: =+'Pro_Forma IS'!K$7*'Working Cap'!$O$49 -> 321478.25 | L6: =+'Pro_Forma IS'!L$7*'Working Cap'!$O$49 -> 331619.1 | M6: =+'Pro_Forma IS'!M$7*'Working Cap'!$O$49 -> 348410.3
B7: Trade and other accounts receivable | C7: 1214050 | D7: 1162582 | E7: 1244348 | F7: 599381 | G7: 902672 | H7: =+'Working Cap'!AI$15 -> 1091172.2 | I7: =+'Working Cap'!AJ$15 -> 1283225.4 | J7: =+'Working Cap'!AK$15 -> 1364915.2 | K7: =+'Working Cap'!AL$15 -> 1411493.7 | L7: =+'Working Cap'!AM$15 -> 1456018.4 | M7: =+'Working Cap'!AN$15 -> 1529742.5
B8: Accounts receivable from related entities | C8: 2582 | D8: 2931 | E8: 19645 | F8: 158 | G8: 724 | H8: 0 | I8: 0 | J8: 0 | K8: 0 | L8: 0 | M8: 0
B9: Inventories | C9: 236666 | D9: 279344 | E9: 354232 | F9: 323574 | G9: 287337 | H9: =-SUM('Pro_Forma IS'!H$11:H$12,'Pro_Forma IS'!H$14:H$19)*('Working Cap'!L$73/360) -> 327838.15 | I9: =-SUM('Pro_Forma IS'!I$11:I$12,'Pro_Forma IS'!I$14:I$19)*('Working Cap'!M$73/360) -> 349339.99 | J9: =-SUM('Pro_Forma IS'!J$11:J$12,'Pro_Forma IS'!J$14:J$19)*('Working Cap'!N$73/360) -> 330244.66 | K9: =-SUM('Pro_Forma IS'!K$11:K$12,'Pro_Forma IS'!K$14:K$19)*('Working Cap'!O$73/360) -> 340709.46 | L9: =-SUM('Pro_Forma IS'!L$11:L$12,'Pro_Forma IS'!L$14:L$19)*('Working Cap'!P$73/360) -> 360263.87 | M9: =-SUM('Pro_Forma IS'!M$11:M$12,'Pro_Forma IS'!M$14:M$19)*('Working Cap'!Q$73/360) -> 367784.8
B10: Tax assets | C10: 77987 | D10: 69134 | E10: 29321 | F10: 42320 | G10: 41264
B11: Non- current assets and disposal groups held for sale | C11: 291103 | D11: 5768 | E11: 485150 | F11: 276122 | G11: 146792 | H11: 0 | I11: 0 | J11: 0 | K11: 0 | L11: 0 | M11: 0
B12: TOTAL CURRENT ASSETS | C12: 3745499 | D12: 3275861 | E12: 4018228 | F12: 3143538 | G12: 2635130 | H12: =+SUM(H4:H11) -> 1667533 | I12: =+SUM(I4:I11) -> 1924829.6 | J12: =+SUM(J4:J11) -> 2006029.5 | K12: =+SUM(K4:K11) -> 2073681.4 | L12: =+SUM(L4:L11) -> 2147901.4 | M12: =+SUM(M4:M11) -> 2245937.6
B13: Property and equipment | C13: 10065335 | D13: 12501809 | E13: 12919618 | F13: 10730269 | G13: 9489867 | H13: =+CAPEX!AV70 -> 9404186.8 | I13: =+CAPEX!AW70 -> 10110376 | J13: =+CAPEX!AX70 -> 10142086 | K13: =+CAPEX!AY70 -> 10413601 | L13: =+CAPEX!AZ70 -> 10651208 | M13: =+CAPEX!BA70 -> 11099610
B14: Goodwill | C14: 2672550 | D14: 2294072 | E14: 2209576 | F14: 0 | G14: 0 | H14: 0 | I14: 0 | J14: 0 | K14: 0 | L14: 0 | M14: 0
B15: Intangible assets other than goodwill | C15: 1617247 | D15: 1441072 | E15: 1448241 | F15: 1046559 | G15: 1018892 | H15: =CAPEX!Z13 -> 1018765 | I15: =CAPEX!AA13 -> 1018765 | J15: =CAPEX!AB13 -> 1018765 | K15: =CAPEX!AC13 -> 1018765 | L15: =CAPEX!AD13 -> 1018765 | M15: =CAPEX!AE13 -> 1018765
B16: Other non- current assets | C16: 697341 | D16: 565908 | E16: 492143 | F16: 729724 | G16: 168545
B17: TOTAL NON-CURRENT ASSETS | C17: 15052473 | D17: 16802861 | E17: 17069578 | F17: 12506552 | G17: 10677304 | H17: =+SUM(H13:H16) -> 10422952 | I17: =+SUM(I13:I16) -> 11129141 | J17: =+SUM(J13:J16) -> 11160851 | K17: =+SUM(K13:K16) -> 11432366 | L17: =+SUM(L13:L16) -> 11669973 | M17: =+SUM(M13:M16) -> 12118375
B19: LIABILITIES AND SHAREHOLDERS' EQUITY | C19: 18797972 | D19: 20078722 | E19: 21087806 | F19: 15650090 | G19: 13312434
B20: Other financial liabilities | C20: 1300949 | D20: 1794286 | E20: 1885660 | F20: 3055730 | G20: 4453451
B21: Trade and other accounts payables | C21: 1695202 | D21: 1674303 | E21: 2222874 | F21: 2322125 | G21: 4860153 | H21: =SUM('Pro_Forma IS'!H$11:H$12,'Pro_Forma IS'!H$14:H$19)*('Working Cap'!$O$68/365) -> -3906955.1 | I21: =SUM('Pro_Forma IS'!I$11:I$12,'Pro_Forma IS'!I$14:I$19)*('Working Cap'!$O$68/365) -> -4163199.7 | J21: =SUM('Pro_Forma IS'!J$11:J$12,'Pro_Forma IS'!J$14:J$19)*('Working Cap'!$O$68/365) -> -3935634.3 | K21: =SUM('Pro_Forma IS'!K$11:K$12,'Pro_Forma IS'!K$14:K$19)*('Working Cap'!$O$68/365) -> -4060346.8 | L21: =SUM('Pro_Forma IS'!L$11:L$12,'Pro_Forma IS'!L$14:L$19)*('Working Cap'!$O$68/365) -> -4293383.2 | M21: =SUM('Pro_Forma IS'!M$11:M$12,'Pro_Forma IS'!M$14:M$19)*('Working Cap'!$O$68/365) -> -4383012.5
B22: Tax liabilities | C22: 3511 | D22: 3738 | E22: 11925 | F22: 656 | G22: 675
B23: Other non-financial liabilities | C23: 2843052 | D23: 2459922 | E23: 2840483 | F23: 2113377 | G23: 3022050 | H23: ='Working Cap'!$D$39*'Pro_Forma IS'!H$4 -> 1301269.8 | I23: ='Working Cap'!$D$39*'Pro_Forma IS'!I$4 -> 1550539.7 | J23: ='Working Cap'!$D$39*'Pro_Forma IS'!J$4 -> 1715466.3 | K23: ='Working Cap'!$D$39*'Pro_Forma IS'!K$4 -> 1774195.7 | L23: ='Working Cap'!$D$39*'Pro_Forma IS'!L$4 -> 1863409.6 | M23: ='Working Cap'!$D$39*'Pro_Forma IS'!M$4 -> 1962686.9
B24: TOTAL CURRENT LIABILITIES | C24: 5842714 | D24: 5932249 | E24: 6960942 | F24: 7491888 | G24: 12336329 | H24: =+SUM(H20:H23) -> -2605685.4 | I24: =+SUM(I20:I23) -> -2612660 | J24: =+SUM(J20:J23) -> -2220168 | K24: =+SUM(K20:K23) -> -2286151.1 | L24: =+SUM(L20:L23) -> -2429973.6 | M24: =+SUM(M20:M23) -> -2420325.6
B25: Other financial liabilities | C25: 6605508 | D25: 8359462 | E25: 8530418 | F25: 7803801 | G25: 5948702
B26: Accounts payable | C26: 498832 | D26: 529277 | E26: 619110 | F26: 651600 | G26: 472426 | H26: 0 | I26: 0 | J26: 0 | K26: 0 | L26: 0 | M26: 0
B27: Other provisions | C27: 374593 | D27: 303495 | E27: 286403 | F27: 396423 | G27: 712581
B28: Deferred tax liabilities | C28: 949697 | D28: 786571 | E28: 616803 | F28: 588359 | G28: 341011
B29: Employee benefits | C29: 101087 | D29: 82365 | E29: 93570 | F29: 384280 | G29: 56233
B30: Other non-financial liabilities | C30: 158305 | D30: 644702 | E30: 851383 | F30: 74116 | G30: 512056 | H30: 0 | I30: 0 | J30: 0 | K30: 0 | L30: 0 | M30: 0
B31: TOTAL NON-CURRENT LIABILITIES | C31: 8688022 | D31: 10705872 | E31: 10997687 | F31: 702008 | G31: 8043009 | H31: =+SUM(H25:H30) -> 0 | I31: =+SUM(I25:I30) -> 0 | J31: =+SUM(J25:J30) -> 0 | K31: =+SUM(K25:K30) -> 0 | L31: =+SUM(L25:L30) -> 0 | M31: =+SUM(M25:M30) -> 0
B33: TOTAL LIABILITIES | C33: 14530736 | D33: 16638121 | E33: 17958629 | F33: 10600587 | G33: 20379338
B35: Share capital | C35: 3146265 | D35: 3146265 | E35: 3146265 | F35: 3146265 | G35: 3146265
B36: Retained earnings | C36: 475118 | D36: 218971 | E36: 352272 | F36: -4193615 | G36: -8841106
B37: Treasury Shares | C37: -178 | D37: -178 | E37: -178 | F37: -178 | G37: -178
B38: Other reserves | C38: 554884 | D38: -4365 | E38: -367577 | F38: -1388185 | G38: -1361529
B39: Equity attributable to the parent company’s equity holders | C39: 4176089 | D39: 3360693 | E39: 3130782 | F39: -2435713 | G39: -7056548
B40: Minority interest | C40: 91147 | D40: 79908 | E40: -1605 | F40: -6673 | G40: -10356
B41: TOTAL NET EQUITY | C41: 4267236 | D41: 3440601 | E41: 3129177 | F41: -2442386 | G41: -7066904 | H41: =+SUM(H35:H40) -> 0 | I41: =+SUM(I35:I40) -> 0 | J41: =+SUM(J35:J40) -> 0 | K41: =+SUM(K35:K40) -> 0 | L41: =+SUM(L35:L40) -> 0 | M41: =+SUM(M35:M40) -> 0
B46: Balance Sheet
B49: (in US$ millions except per share and capital stock data)
B50: Balance Sheet Data Reformulated | C50: 2017 | D50: 2018 | E50: 2019 | F50: 2020 | G50: 2021 | H50: 2022E | I50: 2023F | J50: 2024F | K50: 2025F | L50: 2026F | M50: 2027F
B51: NET ASSETS
B52: Net Invested Capital
B53: Trade and other accounts receivable | C53: 1223523 | D53: 1170894 | E53: 1268718 | F53: 604525 | G53: 915597 | H53: =+'Working Cap'!AI$15 -> 1091172.2 | I53: =+'Working Cap'!AJ$15 -> 1283225.4 | J53: =+'Working Cap'!AK$15 -> 1364915.2 | K53: =+'Working Cap'!AL$15 -> 1411493.7 | L53: =+'Working Cap'!AM$15 -> 1456018.4 | M53: =+'Working Cap'!AN$15 -> 1529742.5
B54: Inventories | C54: 236666 | D54: 279344 | E54: 354232 | F54: 323574 | G54: 287337 | H54: =-SUM('Pro_Forma IS'!H$11:H$12,'Pro_Forma IS'!H$14:H$19)*('Working Cap'!L$73/360) -> 327838.15 | I54: =-SUM('Pro_Forma IS'!I$11:I$12,'Pro_Forma IS'!I$14:I$19)*('Working Cap'!M$73/360) -> 349339.99 | J54: =-SUM('Pro_Forma IS'!J$11:J$12,'Pro_Forma IS'!J$14:J$19)*('Working Cap'!N$73/360) -> 330244.66 | K54: =-SUM('Pro_Forma IS'!K$11:K$12,'Pro_Forma IS'!K$14:K$19)*('Working Cap'!O$73/360) -> 340709.46 | L54: =-SUM('Pro_Forma IS'!L$11:L$12,'Pro_Forma IS'!L$14:L$19)*('Working Cap'!P$73/360) -> 360263.87 | M54: =-SUM('Pro_Forma IS'!M$11:M$12,'Pro_Forma IS'!M$14:M$19)*('Working Cap'!Q$73/360) -> 367784.8
B55: Other non-financial assets | C55: 441995 | D55: 518017 | E55: 518377 | F55: 282674 | G55: 233800 | H55: =+'Pro_Forma IS'!H$7*'Working Cap'!$O$51 -> 475801.91 | I55: =+'Pro_Forma IS'!I$7*'Working Cap'!$O$51 -> 559546.05 | J55: =+'Pro_Forma IS'!J$7*'Working Cap'!$O$51 -> 595166.59 | K55: =+'Pro_Forma IS'!K$7*'Working Cap'!$O$51 -> 615476.97 | L55: =+'Pro_Forma IS'!L$7*'Working Cap'!$O$51 -> 634891.83 | M55: =+'Pro_Forma IS'!M$7*'Working Cap'!$O$51 -> 667038.95
B56: Trade and other account payables | C56: -2194794 | D56: -2203962 | E56: -2842040 | F56: -3370960 | G56: -5994181 | H56: =AVERAGE('Working Cap'!$H$68:$J$68)*SUM('Pro_Forma IS'!H11:H12,'Pro_Forma IS'!H14:H19)/365 -> -2703226.2 | I56: =AVERAGE('Working Cap'!$H$68:$J$68)*SUM('Pro_Forma IS'!I11:I12,'Pro_Forma IS'!I14:I19)/365 -> -2880522.1 | J56: =AVERAGE('Working Cap'!$H$68:$J$68)*SUM('Pro_Forma IS'!J11:J12,'Pro_Forma IS'!J14:J19)/365 -> -2723069.4 | K56: =AVERAGE('Working Cap'!$H$68:$J$68)*SUM('Pro_Forma IS'!K11:K12,'Pro_Forma IS'!K14:K19)/365 -> -2809358.1 | L56: =AVERAGE('Working Cap'!$H$68:$J$68)*SUM('Pro_Forma IS'!L11:L12,'Pro_Forma IS'!L14:L19)/365 -> -2970596.1 | M56: =AVERAGE('Working Cap'!$H$68:$J$68)*SUM('Pro_Forma IS'!M11:M12,'Pro_Forma IS'!M14:M19)/365 -> -3032610.8
B57: Tax assets net of tax liabilities | C57: -493668 | D57: -446889 | E57: -363824 | F57: 222200 | G57: -285132
B58: Employee benefits | C58: -101087 | D58: -82365 | E58: -93570 | F58: -74116 | G58: -56233 | H58: =+G58*('Pro_Forma IS'!H10/'Pro_Forma IS'!G10) -> -70712.308 | I58: =+H58*('Pro_Forma IS'!I10/'Pro_Forma IS'!H10) -> -84821.284 | J58: =+I58*('Pro_Forma IS'!J10/'Pro_Forma IS'!I10) -> -90220.982 | K58: =+J58*('Pro_Forma IS'!K10/'Pro_Forma IS'!J10) -> -93299.822 | L58: =+K58*('Pro_Forma IS'!L10/'Pro_Forma IS'!K10) -> -96242.91 | M58: =+L58*('Pro_Forma IS'!M10/'Pro_Forma IS'!L10) -> -101116.07
B59: Provisions | C59: -377376 | D59: -308289 | E59: -291609 | F59: -612133 | G59: -740453 | H59: =(SUM('Forecast Drivers'!H25,'Forecast Drivers'!H68,'Forecast Drivers'!H113)/SUM('Forecast Drivers'!$E$25,'Forecast Drivers'!$E$68,'Forecast Drivers'!$E$113))*$E$59 -> -237210.28 | I59: =(SUM('Forecast Drivers'!I25,'Forecast Drivers'!I68,'Forecast Drivers'!I113)/SUM('Forecast Drivers'!$E$25,'Forecast Drivers'!$E$68,'Forecast Drivers'!$E$113))*$E$59 -> -273518.48 | J59: =(SUM('Forecast Drivers'!J25,'Forecast Drivers'!J68,'Forecast Drivers'!J113)/SUM('Forecast Drivers'!$E$25,'Forecast Drivers'!$E$68,'Forecast Drivers'!$E$113))*$E$59 -> -314899.52 | K59: =(SUM('Forecast Drivers'!K25,'Forecast Drivers'!K68,'Forecast Drivers'!K113)/SUM('Forecast Drivers'!$E$25,'Forecast Drivers'!$E$68,'Forecast Drivers'!$E$113))*$E$59 -> -327602.92 | L59: =(SUM('Forecast Drivers'!L25,'Forecast Drivers'!L68,'Forecast Drivers'!L113)/SUM('Forecast Drivers'!$E$25,'Forecast Drivers'!$E$68,'Forecast Drivers'!$E$113))*$E$59 -> -339574.73 | M59: =(SUM('Forecast Drivers'!M25,'Forecast Drivers'!M68,'Forecast Drivers'!M113)/SUM('Forecast Drivers'!$E$25,'Forecast Drivers'!$E$68,'Forecast Drivers'!$E$113))*$E$59 -> -352155.25
B60: Other non-financial Liabilties | C60: -2982268 | D60: -3099448 | E60: -3686604 | F60: -2790799 | G60: -2844632 | H60: =-'Working Cap'!$D$39*'Pro_Forma IS'!H$4 -> -1301269.8 | I60: =-'Working Cap'!$D$39*'Pro_Forma IS'!I$4 -> -1550539.7 | J60: =-'Working Cap'!$D$39*'Pro_Forma IS'!J$4 -> -1715466.3 | K60: =-'Working Cap'!$D$39*'Pro_Forma IS'!K$4 -> -1774195.7 | L60: =-'Working Cap'!$D$39*'Pro_Forma IS'!L$4 -> -1863409.6 | M60: =-'Working Cap'!$D$39*'Pro_Forma IS'!M$4 -> -1962686.9
B61: Net Working Capital | C61: -4247009 | D61: -4172698 | E61: -5136320 | F61: -5415035 | G61: =SUM(G53:G56,G58:G60) -> -8198765 | H61: =SUM(H53:H56,H58:H60) -> -2417606.3 | I61: =SUM(I53:I56,I58:I60) -> -2597290 | J61: =SUM(J53:J56,J58:J60) -> -2553329.7 | K61: =SUM(K53:K56,K58:K60) -> -2636776.4 | L61: =SUM(L53:L56,L58:L60) -> -2818649.2 | M61: =SUM(M53:M56,M58:M60) -> -2884002.8
B62: Financial assets | C62: 648009 | D62: 442684 | E62: 546411 | F62: 83390 | G62: 116760 | I62: - | J62: - | K62: - | L62: - | M62: -
B63: Intangible assets other than goodwill | C63: 1617247 | D63: 1441072 | E63: 1448241 | F63: 1046559 | G63: 1018892 | H63: =CAPEX!Z13 -> 1018765 | I63: =CAPEX!AA13 -> 1018765 | J63: =CAPEX!AB13 -> 1018765 | K63: =CAPEX!AC13 -> 1018765 | L63: =CAPEX!AD13 -> 1018765 | M63: =CAPEX!AE13 -> 1018765
B64: Goodwill | C64: 2672550 | D64: 2294072 | E64: 2209576 | F64: - | G64: - | H64: - | I64: - | J64: - | K64: - | L64: - | M64: -
B65: Property, plant and equipment | C65: 10065335 | D65: 12501809 | E65: 12919618 | F65: 10730269 | G65: 9489867 | H65: ='Capex.'!AV70 -> 9404186.8 | I65: ='Capex.'!AW70 -> 10110376 | J65: ='Capex.'!AX70 -> 10142086 | K65: ='Capex.'!AY70 -> 10413601 | L65: ='Capex.'!AZ70 -> 10651208 | M65: ='Capex.'!BA70 -> 11099610
B66: Net Invested Capital | C66: =SUM(C61:C65) -> 10756132 | D66: =SUM(D61:D65) -> 12506939 | E66: =SUM(E61:E65) -> 11987526 | F66: =SUM(F61:F65) -> 6445183 | G66: =SUM(G61:G65) -> 2426754 | H66: =SUM(H61:H65) -> 8005345.6 | I66: =SUM(I61:I65) -> 8531850.5 | J66: =SUM(J61:J65) -> 8607521.1 | ... M66: =SUM(M61:M65) -> 9234372.1
B67: Net Surplus Assets
B68: Non-current assets (or disposal groups) classified as held for sale | C68: 291103 | D68: 5768 | E68: 485150 | F68: 276122 | G68: 146792
B69: Liabilities included in disposal groups classified as held for sale | C69: -15546 | D69: 0 | E69: 0 | F69: 0 | G69: 0 | H69: 0 | I69: 0 | J69: 0 | K69: 0 | L69: 0 | M69: 0
B70: Net non-current assets (or disposal groups) classified as held for sale | C70: 275557 | D70: 5768 | E70: 485150 | F70: 276122 | G70: 146792 | H70: 0 | I70: 0 | J70: 0 | K70: 0 | L70: 0 | M70: 0
B71: Net Invested Capital + Net Surplus Assets | C71: =SUM(C66,C70) -> 11031689 | D71: =SUM(D66,D70) -> 12512707 | E71: =SUM(E66,E70) -> 12472676 | F71: =SUM(F66,F70) -> 6721305 | G71: =SUM(G66,G70) -> 2573546 | H71: =SUM(H66,H70) -> 8005345.6 | I71: =SUM(I66,I70) -> 8531850.5 | J71: =SUM(J66,J70) -> 8607521.1 | ... M71: =SUM(M66,M70) -> 9234372.1
B73: EQUITY
B74: Share capital | C74: 3146265 | D74: 3146265 | E74: 3146265 | F74: 3146265 | G74: 3146265 | H74: =Sch_Deb!P$46 -> 3604476.5 | I74: =Sch_Deb!Q$46 -> 3604476.5 | J74: =Sch_Deb!R$46 -> 3604476.5 | K74: =Sch_Deb!S$46 -> 3604476.5 | L74: =Sch_Deb!T$46 -> 3604476.5 | M74: =Sch_Deb!U$46 -> 3604476.5
B75: Retained earnings/(losses) | C75: 475118 | D75: 218971 | E75: 352272 | F75: -4193615 | G75: -8841106 | H75: =Sch_Deb!P$47 -> 47684.656 | I75: =Sch_Deb!Q$47 -> 95369.313 | J75: =Sch_Deb!R$47 -> 143053.97 | K75: =Sch_Deb!S$47 -> 190738.63 | L75: =Sch_Deb!T$47 -> 238423.28 | M75: =Sch_Deb!U$47 -> 286107.94
B76: Treasury Shares | C76: -178 | D76: -178 | E76: -178 | F76: -178 | G76: -178 | H76: =Sch_Deb!P$48 -> -178 | I76: =Sch_Deb!Q$48 -> -178 | J76: =Sch_Deb!R$48 -> -178 | K76: =Sch_Deb!S$48 -> -178 | L76: =Sch_Deb!T$48 -> -178 | M76: =Sch_Deb!U$48 -> -178
B77: Other reserves | C77: 554884 | D77: -4365 | E77: -367577 | F77: -1388185 | G77: -1361529 | H77: =Sch_Deb!P$49 -> -367577 | I77: =Sch_Deb!Q$49 -> -367577 | J77: =Sch_Deb!R$49 -> -367577 | K77: =Sch_Deb!S$49 -> -367577 | L77: =Sch_Deb!T$49 -> -367577 | M77: =Sch_Deb!U$49 -> -367577
B78: Parent’s ownership interest | C78: 4176089 | D78: 3360693 | E78: 3130782 | F78: -2435713 | G78: -7056548 | H78: =SUM(H74:H77) -> 3284406.2 | I78: =SUM(I74:I77) -> 3332090.8 | J78: =SUM(J74:J77) -> 3379775.5 | K78: =SUM(K74:K77) -> 3427460.1 | L78: =SUM(L74:L77) -> 3475144.8 | M78: =SUM(M74:M77) -> 3522829.5
B79: Non-controlling interest | C79: 91147 | D79: 79908 | E79: -1605 | F79: -6672 | G79: -10356 | H79: =Sch_Deb!P53 -> -8040.6564 | I79: =Sch_Deb!Q53 -> -5725.3128 | J79: =Sch_Deb!R53 -> -3409.9692 | K79: =Sch_Deb!S53 -> -1094.6255 | L79: =Sch_Deb!T53 -> 1220.7181 | M79: =Sch_Deb!U53 -> 3536.0617
B80: Total Equity | C80: =SUM(C78:C79) -> 4267236 | D80: =SUM(D78:D79) -> 3440601 | E80: =SUM(E78:E79) -> 3129177 | F80: =SUM(F78:F79) -> -2442385 | G80: =SUM(G78:G79) -> -7066904 | H80: =SUM(H78:H79) -> 3276365.5 | I80: =SUM(I78:I79) -> 3326365.5 | J80: =SUM(J78:J79) -> 3376365.5 | ... M80: =SUM(M78:M79) -> 3526365.5
B82: NET FINANCIAL POSITION
B83: Total Financial Liabilities | C83: 7906457 | D83: 10153748 | E83: 10416078 | F83: 10859531 | G83: 10402153 | H83: =Sch_Deb!P$30 -> 6705225 | I83: =Sch_Deb!Q$30 -> #REF! | J83: =Sch_Deb!R$30 -> #REF! | K83: =Sch_Deb!S$30 -> #REF! | L83: =Sch_Deb!T$30 -> #REF! | M83: =Sch_Deb!U$30 -> #REF!
B84: Cash and cash equivalents | C84: -1142004 | D84: -1081642 | E84: -1072579 | F84: -1695841 | G84: -1046835 | H84: =-Sch_Deb!P$76 -> -2569464.3 | I84: =-Sch_Deb!Q$76 -> #REF! | J84: =-Sch_Deb!R$76 -> #REF! | K84: =-Sch_Deb!S$76 -> #REF! | L84: =-Sch_Deb!T$76 -> #REF! | M84: =-Sch_Deb!U$76 -> #REF!
B85: Net Financial Position | C85: 6764453 | D85: 9072106 | E85: 9343499 | F85: 9163690 | G85: 9355318 | H85: =SUM(H83:H84) -> 4135760.7 | I85: =SUM(I83:I84) -> #REF! | J85: =SUM(J83:J84) -> #REF! | K85: =SUM(K83:K84) -> #REF! | L85: =SUM(L83:L84) -> #REF! | M85: =SUM(M83:M84) -> #REF!
B86: Equity+Net Financial Position | C86: 11031689 | D86: 12512707 | E86: 12472676 | F86: 6721305 | G86: 2288414 | H86: =SUM(H80,H85) -> 7412126.3 | I86: =SUM(I80,I85) -> #REF! | J86: =SUM(J80,J85) -> #REF! | K86: =SUM(K80,K85) -> #REF! | L86: =SUM(L80,L85) -> #REF! | M86: =SUM(M80,M85) -> #REF!
H87: =H71-H86 -> 593219.34 | I87: =I71-I86 -> #REF! | J87: =J71-J86 -> #REF! | K87: =K71-K86 -> #REF! | L87: =L71-L86 -> #REF! | M87: =M71-M86 -> #REF!
H88: =H86-H71 -> -593219.34 | I88: =I86-I71 -> #REF! | J88: =J86-J71 -> #REF! | K88: =K86-K71 -> #REF! | L88: =L86-L71 -> #REF! | M88: =M86-M71 -> #REF!
H89: =H88/H66 -> -0.074102902 | I89: =I88/I66 -> #REF! | J89: =J88/J66 -> #REF! | K89: =K88/K66 -> #REF! | L89: =L88/L66 -> #REF! | M89: =M88/M66 -> #REF!

Sheet Cash Flow
I3: 2022 | J3: 2023 | K3: 2024 | L3: 2025 | M3: 2026 | N3: 2027 | O3: 2028 | P3: 2029 | Q3: 2030 | R3: 2031 | S3: 2032 | T3: 2033 | U3: 2034 | V3: 2035 | W3: 2036 | X3: 2037
E4: 2018 | F4: 2019 | G4: 2020 | H4: 2021 | I4: 2022E | J4: 2023F | K4: 2024F | L4: 2025F | M4: 2026F | N4: 2027F | O4: 2028 FF | P4: 2029 FF | Q4: 2030 FF | R4: 2031 FF | S4: 2032 FF | T4: 2033 FF | U4: 2034 FF | V4: 2035 FF | W4: 2036 FF | X4: 2037 FF
D5: EBITDA | E5: ='Pro_Forma IS'!D28 -> 2259611 | F5: ='Pro_Forma IS'!E28 -> 2211577 | G5: ='Pro_Forma IS'!F28 -> -275901 | H5: ='Pro_Forma IS'!G28 -> 46118.32 | I5: ='Pro_Forma IS'!H28 -> 687792.78 | J5: ='Pro_Forma IS'!I28 -> 1618801.3 | K5: ='Pro_Forma IS'!J28 -> 2681874.3 | L5: ='Pro_Forma IS'!K28 -> 2792090.8 | ... N5: ='Pro_Forma IS'!M28 -> 3060091.2 | O5: =N5 -> 3060091.2 | P5: =O5 -> 3060091.2 | Q5: =P5 -> 3060091.2 | R5: =Q5 -> 3060091.2 | S5: =R5 -> 3060091.2 | T5: =S5 -> 3060091.2 | U5: =T5 -> 3060091.2 | V5: =U5 -> 3060091.2 | ... X5: =W5 -> 3060091.2
D6: -ΔWC | E6: =-('Pro_Forma BS'!D61-'Pro_Forma BS'!C61) -> -74311 | F6: =-('Pro_Forma BS'!E61-'Pro_Forma BS'!D61) -> 963622 | G6: =-('Pro_Forma BS'!F61-'Pro_Forma BS'!E61) -> 278715 | H6: =-('Pro_Forma BS'!G61-'Pro_Forma BS'!F61) -> 2783730 | I6: =-('Pro_Forma BS'!H61-'Pro_Forma BS'!G61) -> -5781158.7 | J6: =-('Pro_Forma BS'!I61-'Pro_Forma BS'!H61) -> 179683.76 | K6: =-('Pro_Forma BS'!J61-'Pro_Forma BS'!I61) -> -43960.305 | L6: =-('Pro_Forma BS'!K61-'Pro_Forma BS'!J61) -> 83446.703 | ... N6: =-('Pro_Forma BS'!M61-'Pro_Forma BS'!L61) -> 65353.6 | O6: =N6-($N$6/5) -> 52282.88 | P6: =O6-($N$6/5) -> 39212.16 | Q6: =P6-($N$6/5) -> 26141.44 | R6: =Q6-($N$6/5) -> 13070.72 | S6: =R6-($N$6/5) -> 0 | T6: =S6-($N$6/5) -> -13070.72 | U6: =T6-($N$6/5) -> -26141.44 | V6: =U6-($N$6/5) -> -39212.16 | ... X6: =W6-($N$6/5) -> -65353.6 | AA6: g | AB6: =2% -> 0.02
D7: -taxes | E7: =IF(26%*'Pro_Forma IS'!D31>0,-26%*'Pro_Forma IS'!D31,0) -> -230615.58 | F7: =IF(26%*'Pro_Forma IS'!E31>0,-26%*'Pro_Forma IS'!E31,0) -> -192816.26 | G7: =IF(26%*'Pro_Forma IS'!F31>0,-26%*'Pro_Forma IS'!F31,0) -> 0 | H7: =IF(26%*'Pro_Forma IS'!G31>0,-26%*'Pro_Forma IS'!G31,0) -> 0 | I7: =-'Pro_Forma IS'!H31*26% -> 128946.69 | J7: =-'Pro_Forma IS'!I31*26% -> -96262.907 | K7: =-'Pro_Forma IS'!J31*26% -> -365647.29 | L7: =-'Pro_Forma IS'!K31*26% -> -382887.47 | M7: =-'Pro_Forma IS'!L31*26% -> -341037.4 | N7: =-'Pro_Forma IS'!M31*26% -> -425345.07 | O7: =N7*(1.02) -> -433851.97 | P7: =O7*(1.02) -> -442529.01 | Q7: =P7*(1.02) -> -451379.59 | R7: =Q7*(1.02) -> -460407.18 | S7: =R7*(1.02) -> -469615.33 | T7: =S7*(1.02) -> -479007.63 | U7: =T7*(1.02) -> -488587.79 | V7: =U7*(1.02) -> -498359.54 | ... X7: =W7*(1.02) -> -518493.27 | AA7: wacc | AB7: =9.57% -> 0.0957
D8: substitution in payment | I8: =Cap_Inc!$M$39 -> 4561861 | J8: =J9/I9-1 -> -5.2285111 | K8: =K9/J9-1 -> 0.33488257 | L8: =L9/K9-1 -> 0.096988356 | M8: =M9/L9-1 -> 0.0095492808 | N8: =N9/M9-1 -> 0.072978384 | O8: =O9/N9-1 -> 0.067680545 | P8: =P9/O9-1 -> 0.062382707 | Q8: =Q9/P9-1 -> 0.057084869 | ... X8: =X9/W9-1 -> 0.02
D9: Cash Flow from operations | E9: =E5+E6+E7 -> 1954684.4 | F9: =F5+F6+F7 -> 2982382.7 | G9: =G5+G6+G7 -> 2814 | H9: =H5+H6+H7 -> 2829848.3 | I9: =I5+I6+I7+I8 -> -402558.28 | J9: =J5+J6+J7 -> 1702222.1 | K9: =K5+K6+K7 -> 2272266.7 | L9: =L5+L6+L7 -> 2492650.1 | M9: =M5+M6+M7 -> 2516453.1 | N9: =N5+N6+N7 -> 2700099.8 | O9: =N9*(1+AJ10) -> 2882844 | P9: =O9*(1+AK10) -> 3062683.6 | Q9: =P9*(1+AL10) -> 3237516.5 | R9: =Q9*(1+AM10) -> 3405177.9 | S9: =R9*(1+AN10) -> 3563481.8 | T9: =S9*(1+AO10) -> 3710266.5 | U9: =T9*(1+AP10) -> 3843441 | V9: =U9*(1+AQ10) -> 3961033.7 | ... X9: =W9*(1+AS10) -> 4142464 | AG9: Target | AH9: 0.02 | AJ9: 1 | AK9: 2 | AL9: 3 | AM9: 4 | AN9: 5 | AO9: 6 | AP9: 7 | AQ9: 8 | AR9: 9 | AS9: 10
D10: -capex | I10: =-CAPEX!AV114 -> -1231085.2 | J10: =-CAPEX!AW114 -> -1954840.7 | K10: =-CAPEX!AX114 -> -1307354.3 | L10: =-CAPEX!AY114 -> -1590993.9 | M10: =-CAPEX!AZ114 -> -1601573.2 | N10: =-CAPEX!BA114 -> -1872582.9 | O10: =(N10-(($N$10-$X$10)/10)) -> #REF! | P10: =(O10-(($N$10-$X$10)/10)) -> #REF! | Q10: =(P10-(($N$10-$X$10)/10)) -> #REF! | R10: =(Q10-(($N$10-$X$10)/10)) -> #REF! | S10: =(R10-(($N$10-$X$10)/10)) -> #REF! | T10: =(S10-(($N$10-$X$10)/10)) -> #REF! | U10: =(T10-(($N$10-$X$10)/10)) -> #REF! | V10: =(U10-(($N$10-$X$10)/10)) -> #REF! | W10: =(V10-(($N$10-$X$10)/10)) -> #REF! | X10: =1.05*$X$21 -> #REF! | AG10: Decrescita | AH10: =(AH11-AH9)/10 -> 0.0052978384 | AJ10: =AH11-$AH$10 -> 0.067680545 | AK10: =AJ10-$AH$10 -> 0.062382707 | AL10: =AK10-$AH$10 -> 0.057084869 | AM10: =AL10-$AH$10 -> 0.05178703 | AN10: =AM10-$AH$10 -> 0.046489192 | AO10: =AN10-$AH$10 -> 0.041191353 | AP10: =AO10-$AH$10 -> 0.035893515 | AQ10: =AP10-$AH$10 -> 0.030595677 | AR10: =AQ10-$AH$10 -> 0.025297838 | AS10: =AR10-$AH$10 -> 0.02
D11: FCF | E11: =SUM(E9:E10) -> 1954684.4 | F11: =SUM(F9:F10) -> 2982382.7 | G11: =SUM(G9:G10) -> 2814 | H11: =SUM(H9:H10) -> 2829848.3 | I11: =SUM(I9:I10) -> -1633643.5 | J11: =SUM(J9:J10) -> -252618.51 | K11: =SUM(K9:K10) -> 964912.38 | L11: =SUM(L9:L10) -> 901656.22 | ... N11: =SUM(N9:N10) -> 827516.85 | O11: =M11*(1+O12) -> 976799.5 | P11: =O11*(1+P12) -> 1037734.9 | Q11: =P11*(1+Q12) -> 1096973.9 | R11: =Q11*(1+R12) -> 1153782.9 | S11: =R11*(1+S12) -> 1207421.3 | T11: =S11*(1+T12) -> 1257156.6 | U11: =T11*(1+U12) -> 1302280.4 | V11: =U11*(1+V12) -> 1342124.5 | W11: =V11*(1+W12) -> 1376077.4 | X11: =W11*(1+X12) -> 1403598.9 | AG11: Start | AH11: =N8 -> 0.072978384
D12: Adjusted Free cash flow | I12: =I11+CAPEX!AV112 -> -1259643.5 | J12: =J11+CAPEX!AW112 -> 845381.49 | K12: =K11+CAPEX!AX112 -> 1412912.4 | L12: =L11+CAPEX!AY112 -> 1641656.2 | M12: =M11+CAPEX!AZ112 -> 1664879.9 | N12: =N11+CAPEX!BA112 -> 1847516.9 | O12: =AJ10 -> 0.067680545 | P12: =AK10 -> 0.062382707 | Q12: =AL10 -> 0.057084869 | R12: =AM10 -> 0.05178703 | S12: =AN10 -> 0.046489192 | T12: =AO10 -> 0.041191353 | U12: =AP10 -> 0.035893515 | V12: =AQ10 -> 0.030595677 | ... X12: =AS10 -> 0.02 | Y12: =X11*(1+AB6)/(AB7-AB6) -> 18912430
D13: Financing Flow | I13: =1.0957^(I3-2021) -> 1.0957 | J13: =1.0957^(J3-2021) -> 1.2005585 | K13: =1.0957^(K3-2021) -> 1.3154519 | L13: =1.0957^(L3-2021) -> 1.4413407 | M13: =1.0957^(M3-2021) -> 1.579277 | N13: =1.0957^(N3-2021) -> 1.7304138 | O13: =1.0957^(O3-2021) -> 1.8960144 | P13: =1.0957^(P3-2021) -> 2.077463 | ... X13: =1.0957^(X3-2021) -> 4.3158524
D14: Δcash | G14: 4425087.3 | I14: =I11/I13 -> -1490958.8 | J14: =J11/J13 -> -210417.5 | K14: =K11/K13 -> 733521.58 | L14: =L11/L13 -> 625567.73 | M14: =M11/M13 -> 579303.02 | N14: =N11/N13 -> 478219.05 | O14: =O11/O13 -> 515185.7 | P14: =P11/P13 -> 499520.28 | ... X14: =X11/X13 -> 325219.4 | Y14: =Y12/X13 -> 4382084.4 | AA14: =Z24 -> 10142573 | AB14: 0.0917 | AC14: 0.0937 | AD14: 0.0957 | AE14: =AD14+0.002 -> 0.0977 | AF14: =AE14+0.002 -> 0.0997 | AG14: =AF14+0.002 -> 0.1017 | AH14: =AG14+0.002 -> 0.1037
N15: =M11/(0.1-0.02) -> 11435999 | AA15: 0.014
D16: Enterprise Value | E16: =I16*1.0957^(10.5/12) -> 10142573 | H16: =Y14/I16 -> 0.46801827 | I16: =SUM(I14:Y14) -> 9363062.8 | J16: =SUM(I14:N14)+(M11/(0.096-0.03))/N13 -> 8725930.1 | N16: =N15/N13 -> 6608823.3 | O16: =N5/M5-1 -> 0.14369526 | P16: =P11/O11-1 -> 0.062382707 | Q16: =Q11/P11-1 -> 0.057084869 | R16: =R11/Q11-1 -> 0.05178703 | S16: =S11/R11-1 -> 0.046489192 | AA16: 0.016
D17: (+) Net Debt (Financial liab. - Cash & equivalents) | E17: =H17 -> -4135760.7 | G17: (-) Net Debt | H17: =-Sch_Deb!P80 -> -4135760.7 | K17: =K5/J5-1 -> 0.65670381 | L17: =L5/K5-1 -> 0.041096847 | M17: =M5/L5-1 -> -0.0417154 | N17: =N5/M5-1 -> 0.14369526 | AA17: 0.018
D18: (-) Other Financial assets (current and non-current) | E18: -175714 | G18: (-) Other Debt-like Items / Employee benefits | H18: -56.862 | I18: 589994732307 | J18: =J11/I11-1 -> -0.84536497 | K18: =K11/J11-1 -> -4.8196424 | L18: =L11/K11-1 -> -0.065556376 | M18: =M11/L11-1 -> 0.014666017 | N18: =N11/M11-1 -> -0.095491305 | AA18: 0.02
D19: (+) Other debt-like items (Employee benefits) | E19: 56862 | G19: (+) Other Financial Assets | H19: 175,714,000 | M19: Amm.to | N19: ='Pro_Forma IS'!M13 -> -1424148.7 | AA19: 0.022
D20: (+) Minority Interests | E20: -13377 | G20: (-) Minority Interests | H20: 13.377 | M20: coeff. Amm.to | N20: =-N19/SUM('Pro_Forma BS'!M63:M65) -> 0.11751977 | AA20: 0.024
D21: (-) Investments in associates | E21: 0 | G21: (+) Investments in Associates | H21: 0 | M21: D&A | O21: =($N$19+$N$20*N10) -> -1644214.2 | P21: =($N$19+$N$20*O10) -> #REF! | Q21: =($N$19+$N$20*P10) -> #REF! | R21: =($N$19+$N$20*Q10) -> #REF! | S21: =($N$19+$N$20*R10) -> #REF! | T21: =($N$19+$N$20*S10) -> #REF! | U21: =($N$19+$N$20*T10) -> #REF! | V21: =($N$19+$N$20*U10) -> #REF! | ... X21: =($N$19+$N$20*W10) -> #REF! | AA21: 0.026
D22: (+) Surplus assets | E22: 13567 | J22: =J9/I9-1 -> -5.2285111 | K22: =K9/J9-1 -> 0.33488257 | L22: =L9/K9-1 -> 0.096988356 | M22: =M9/L9-1 -> 0.0095492808 | N22: =N9/M9-1 -> 0.072978384
D23: Equity Value Implied | E23: =E16+SUM(E17:E22) -> 5888150.2
D24: Prezzo per share | E24: =E23*10^3/I18 -> 0.0099800047 | Q24: EV/EBTDA | R24: =10.64 -> 10.64 | Z24: =(I11/(1+AB7)^1+J11/(1+AB7)^2+K11/(1+AB7)^3+L11/(1+AB7)^4+M11/(1+AB7)^5+N11/(1+AB7)^6+O11/(1+AB7)^7+P11/(1+AB7)^8+Q11/(1+AB7)^9+R11/(1+AB7)^10+S11/(1+AB7)^11+T11/(1+AB7)^12+U11/(1+AB7)^13+V11/(1+AB7)^14+W11/(1+AB7)^15+X11/(1+AB7)^16+((X11*(1+AB6))/(AB7-AB6)/(1+AB7)^16))*(1+AB7)^(10.5/12) -> 10142573
I25: -1399 | J25: -205 | K25: 664 | L25: 917 | M25: 1080 | N25: 785 | O25: =M25/(0.1-0.02) -> 13500 | R25: =R24*N5 -> 32559371 | Z25: =I11/(1+E35)^I35+J11/(1+E35)^J35+K11/(1+E35)^K35+L11/(1+E35)^L35+M11/(1+E35)^M35+N11/(1+E35)^N35+O11/(1+E35)^O35+P11/(1+E35)^P35+Q11/(1+E35)^Q35+R11/(1+E35)^R35+S11/(1+E35)^S35+T11/(1+E35)^T35+U11/(1+E35)^U35+V11/(1+E35)^V35+W11/(1+E35)^W35+X11/(1+E35)^X35+(X11*(1+E34)/((E35-E34)*(1+E35)^X35)) -> #DIV/0!
D26: Market cap | E26: =3473888983824 -> 3473888983824 | H26: =SUM(I26:O26) -> 8418.0618 | I26: =I25/(1.1^(I3-2021)) -> -1271.8182 | J26: =J25/(1.1^(J3-2021)) -> -169.42149 | K26: =K25/(1.1^(K3-2021)) -> 498.87303 | L26: =L25/(1.1^(L3-2021)) -> 626.32334 | M26: =M25/(1.1^(M3-2021)) -> 670.59503 | N26: =N25/(1.1^(N3-2021)) -> 443.11204 | O26: =O25/(1.1^(N3-2021)) -> 7620.3981 | R26: =R25/N13 -> 18815945
D27: CamBio pesos USD | E27: 0.0010531189 | R27: =SUM(I14:N14)+R26 -> 19531180 | S27: =1.0982^(11/12)*R27 -> 21282361
D28: Market Cap USD | E28: =E27*E26 -> 3.6584181e+09
E29: =E28/I18 -> 0.0062007641 | J29: =J10/I10-1 -> 0.58790032 | K29: =K10/J10-1 -> -0.33122207 | L29: =L10/K10-1 -> 0.21695693 | M29: =M10/L10-1 -> 0.0066494974 | N29: =N10/M10-1 -> 0.16921472
E30: =E24/E29 -> 1.6094798
G32: 4791086312

Sheet Real GDP Brazil
A1: FRED Graph Observations
A2: Federal Reserve Economic Data | D2: Mean quarterly Growth | E2: =AVERAGE(C14:C118) -> 0.0061714214
A3: Link: https://fred.stlouisfed.org | F3: {=#REF!} -> #REF! | G3: =E2 -> 0.0061714214
A4: Help: https://fredhelp.stlouisfed.org
A5: Economic Research Division | D5: Mean quarterly Growth Last Years, no COVID | E5: =AVERAGE(C81:C108) -> 0.00011813035
A6: Federal Reserve Bank of St. Louis
A9: NGDPRNSAXDCBRQ | B9: Real Gross Domestic Product for Brazil, Domestic Currency, Quarterly, Not Seasonally Adjusted
A11: Frequency: Quarterly
A12: observation_date | B12: NGDPRNSAXDCBRQ | C12: Growth
A13: 35065 | B13: 170920
A14: 35156 | B14: 176708.7 | C14: =B14/B13-1 -> 0.033867891
A15: 35247 | B15: 189844.3 | C15: =B15/B14-1 -> 0.074334767
A16: 35339 | B16: 184112.9 | C16: =B16/B15-1 -> -0.030190003
A17: 35431 | B17: 176732.3 | C17: =B17/B16-1 -> -0.040087359
A18: 35521 | B18: 185109.5 | C18: =B18/B17-1 -> 0.047400503
A19: 35612 | B19: 193244.9 | C19: =B19/B18-1 -> 0.043949122
A20: 35704 | B20: 190996 | C20: =B20/B19-1 -> -0.011637565
A21: 35796 | B21: 178513 | C21: =B21/B20-1 -> -0.06535739
A22: 35886 | B22: 187904 | C22: =B22/B21-1 -> 0.052606813
A23: 35977 | B23: 193932.1 | C23: =B23/B22-1 -> 0.032080743
A24: 36069 | B24: 188256.1 | C24: =B24/B23-1 -> -0.029267976
A25: 36161 | B25: 179883.3 | C25: =B25/B24-1 -> -0.044475584
... A118: 44652 | B118: 310255.1 | C118: =B118/B117-1 -> 0.022625274
B121: =SUM(B114:B117)/SUM(B110:B113)-1 -> 0.047119757
C122: =1.83/1.75-1 -> 0.045714286

Sheet Regression_Brazil 
A1: Date | B1: RPK | C1: GDP | D1: Jet Fuel Price dollar per Gallon | E1: Ln(RPK) | F1: LN(GDP) | G1: LN(fuel) | H1: LN(jet Fuel_t-1)
A2: 36526 | B2: 6331103905 | C2: 187799.5 | D2: 0.77733333 | E2: =LN(B2) -> 22.56874 | F2: =LN(C2) -> 12.14313 | G2: =LN('Real GDP Brazil'!B29) -> 12.14313 | H2: =LN(0.652333333) -> -0.4271996
A3: 36617 | B3: 5853651051 | C3: 194596.6 | D3: 0.75533333 | E3: =LN(B3) -> 22.490331 | F3: =LN(C3) -> 12.178684 | G3: =F3 -> 12.178684 | H3: -0.25188602
A4: 36708 | B4: 6527334337 | C4: 201534.7 | D4: 0.90433333 | E4: =LN(B4) -> 22.599264 | F4: =LN(C4) -> 12.213717 | G4: =F4 -> 12.213717 | H4: -0.28059613
A5: 36800 | B5: 6507878786 | C5: 201179.5 | D5: 0.95766667 | E5: =LN(B5) -> 22.596279 | F5: =LN(C5) -> 12.211953 | G5: =F5 -> 12.211953 | H5: -0.10055726
A6: 36892 | B6: 6474253999 | C6: 194325.7 | D6: 0.811 | E6: =LN(B6) -> 22.591099 | F6: =LN(C6) -> 12.177291 | G6: =F6 -> 12.177291 | H6: -0.043255508
A7: 36982 | B7: 6078702660 | C7: 199123 | D7: 0.786 | E7: =LN(B7) -> 22.528057 | F7: =LN(C7) -> 12.201678 | G7: =F7 -> 12.201678 | H7: -0.20948722
A8: 37073 | B8: 6746361477 | C8: 202464.1 | D8: 0.73766667 | E8: =LN(B8) -> 22.632269 | F8: =LN(C8) -> 12.218318 | G8: =F8 -> 12.218318 | H8: -0.24079849
A9: 37165 | B9: 6800534625 | C9: 200109.7 | D9: 0.56 | E9: =LN(B9) -> 22.640267 | F9: =LN(C9) -> 12.206621 | G9: =F9 -> 12.206621 | H9: -0.30426323
A10: 37257 | B10: 6845593446 | C10: 195252.5 | D10: 0.57133333 | E10: =LN(B10) -> 22.646871 | F10: =LN(C10) -> 12.182049 | G10: =F10 -> 12.182049 | H10: -0.5798185
A11: 37347 | B11: 6548776431 | C11: 203699.3 | D11: 0.66266667 | E11: =LN(B11) -> 22.602544 | F11: =LN(C11) -> 12.2244 | G11: =F11 -> 12.2244 | H11: -0.55978247
A12: 37438 | B12: 7124301197 | C12: 210916.4 | D12: 0.73766667 | E12: =LN(B12) -> 22.686777 | F12: =LN(C12) -> 12.259217 | G12: =F12 -> 12.259217 | H12: -0.41148318
A13: 37530 | B13: 6185844970 | C13: 210460.6 | D13: 0.76966667 | E13: =LN(B13) -> 22.545529 | F13: =LN(C13) -> 12.257054 | G13: =F13 -> 12.257054 | H13: -0.30426323
A14: 37622 | B14: 6726270399 | C14: 200459.9 | D14: 0.945 | E14: =LN(B14) -> 22.629287 | F14: =LN(C14) -> 12.20837 | G14: =F14 -> 12.20837 | H14: -0.26179776
... A81: 43739 | B81: 25572691851 | C81: 303031.7 | D81: 1.8593333 | E81: =LN(B81) -> 23.964791 | F81: =LN(C81) -> 12.621593 | G81: =F81 -> 12.621593 | H81: 0.62183018
A86: OUTPUT RIEPILOGO
A88: Statistica della regressione
A89: R multiplo | B89: 0.98152573
A90: R al quadrato | B90: 0.96339276
A91: R al quadrato corretto | B91: 0.96244192
A92: Errore standard | B92: 0.1005452
A93: Osservazioni | B93: 80
A95: ANALISI VARIANZA
B96: gdl | C96: SQ | D96: MQ | E96: F | F96: Significatività F
A97: Regressione | B97: 2 | C97: 20.485655 | D97: 10.242827 | E97: 1013.2046 | F97: 4.9811367e-56
A98: Residuo | B98: 77 | C98: 0.77841903 | D98: 0.010109338
A99: Totale | B99: 79 | C99: 21.264074
B101: Coefficienti | C101: Errore standard | D101: Stat t | E101: Valore di significatività | F101: Inferiore 95% | G101: Superiore 95% | H101: Inferiore 95,0% | I101: Superiore 95,0%
A102: Intercetta | B102: -21.711508 | C102: 1.414966 | D102: -15.344191 | E102: 3.9636961e-25 | F102: -24.529065 | G102: -18.89395 | H102: -24.529065 | I102: -18.89395
A103: Variabile X 1 | B103: 3.6233619 | C103: 0.11466777 | D103: 31.598783 | E103: 7.6939211e-46 | F103: 3.3950292 | G103: 3.8516946 | H103: 3.3950292 | I103: 3.8516946
A104: Variabile X 2 | B104: -0.19331577 | C104: 0.036856503 | D104: -5.2450925 | E104: 1.3336017e-06 | F104: -0.26670644 | G104: -0.11992509 | H104: -0.26670644 | I104: -0.11992509
A108: OUTPUT RESIDUI
A110: Osservazione | B110: Y prevista | C110: Residui | D110: Residui standard
A111: 1 | B111: 22.370033 | C111: 0.19870789 | D111: 2.0018058
A112: 2 | B112: 22.464966 | C112: 0.025365475 | D112: 0.25553467
A113: 3 | B113: 22.597453 | C113: 0.0018116301 | D113: 0.018250567
A114: 4 | B114: 22.556257 | C114: 0.040022626 | D114: 0.40319246
A115: 5 | B115: 22.419587 | C115: 0.17151249 | D115: 1.7278362
A116: 6 | B116: 22.540085 | C116: -0.012028132 | D116: -0.12117276
A117: 7 | B117: 22.60643 | C117: 0.025838687 | D117: 0.26030186
A118: 8 | B118: 22.576317 | C118: 0.06394986 | D118: 0.64423812
A119: 9 | B119: 22.540553 | C119: 0.1063183 | D119: 1.0710626
A120: 10 | B120: 22.690133 | C120: -0.087589411 | D120: -0.88238563
A121: 11 | B121: 22.787619 | C121: -0.10084185 | D121: -1.0158922
A122: 12 | B122: 22.759053 | C122: -0.21352385 | D122: -2.1510634
... A190: 80 | B190: 23.900881 | C190: 0.063909467 | D190: 0.6438312

Sheet Domestic, Brazil estimate
C1: {=TRANSPOSE('A1-jet Fuel'!C105:D107)} -> q2-2021 | D1: q3-2021 | E1: q4-2021 | F1: Q1-2022 | G1: q2-2022 | H1: q3-2022 | I1: q4-2022 | J1: q1-2023 | K1: q2-2023 | L1: q3-2023 | M1: q4-2023 | N1: q1-2024 | O1: q2-2024 | P1: q3-2024 | Q1: q4-2024 | R1: q1-2025 | S1: q2-2025 | T1: q3-2025 | U1: q4-2025 | V1: q1-2026 | W1: q2-2026 | X1: q3-2026 | Y1: q4-2026 | Z1: q1-2027 | AA1: q2-2027 | AB1: q3-2027 | AC1: q4-2027 | AD1: q1-2028 | AE1: q2-2028 | AF1: q3-2028 | AG1: q4-2028
A2: JET FUEL | B2: USD/gal | C2: 1.7593333 | D2: 1.9023333 | E2: 2.1946667 | F2: ='Forecast Drivers'!H10 -> 3.43 | G2: =F2 -> 3.43 | H2: =G2 -> 3.43 | I2: =4*'Forecast Drivers'!H10-SUM('Domestic, Brazil estimate'!F2:H2) -> 3.43 | J2: ='Forecast Drivers'!I10 -> 3.1 | K2: =J2 -> 3.1 | L2: =K2 -> 3.1 | M2: =L2 -> 3.1 | N2: ='Forecast Drivers'!J10 -> 2.38 | O2: =N2 -> 2.38 | P2: =O2 -> 2.38 | Q2: =P2 -> 2.38 | R2: ='Forecast Drivers'!K10 -> 2.38 | S2: =R2 -> 2.38 | T2: =S2 -> 2.38 | U2: =T2 -> 2.38 | V2: ='Forecast Drivers'!L10 -> 2.38 | W2: =V2 -> 2.38 | X2: =W2 -> 2.38 | Y2: =X2 -> 2.38 | Z2: ='Forecast Drivers'!M10 -> 2.38 | AA2: =Z2 -> 2.38 | AB2: =AA2 -> 2.38 | AC2: =AB2 -> 2.38 | AD2: =AC2 -> 2.38 | AE2: =AD2 -> 2.38 | AF2: =AE2 -> 2.38 | AG2: =AF2 -> 2.38
A3: LN(Jet fuel) | C3: =LN(C2) -> 0.56493495 | D3: =LN(D2) -> 0.6430812 | E3: =LN(E2) -> 0.78603017 | F3: =LN(F2) -> 1.2325603 | G3: =LN(G2) -> 1.2325603 | H3: =LN(H2) -> 1.2325603 | I3: =LN(I2) -> 1.2325603 | J3: =LN(J2) -> 1.1314021 | ... AG3: =LN(AG2) -> 0.86710049
A5: GDP Brasil | E5: ='Real GDP Brazil'!B118 -> 310255.1 | F5: =E5*(1+'Forecast Drivers'!$H$9/4) -> 311030.74 | G5: =F5*(1+'Forecast Drivers'!$H$9/4) -> 311808.31 | H5: =G5*(1+'Forecast Drivers'!$H$9/4) -> 312587.84 | I5: =H5*(1+'Forecast Drivers'!$H$9/4) -> 313369.3 | J5: =I5*(1+'Forecast Drivers'!$I$9/4) -> 314152.73 | K5: =J5*(1+'Forecast Drivers'!$I$9/4) -> 314938.11 | L5: =K5*(1+'Forecast Drivers'!$I$9/4) -> 315725.46 | M5: =L5*(1+'Forecast Drivers'!$I$9/4) -> 316514.77 | N5: =M5*(1+'Forecast Drivers'!$J$9/4) -> 317306.06 | O5: =N5*(1+'Forecast Drivers'!$J$9/4) -> 318099.32 | P5: =O5*(1+'Forecast Drivers'!$J$9/4) -> 318894.57 | Q5: =P5*(1+'Forecast Drivers'!$J$9/4) -> 319691.81 | R5: =Q5*(1+'Forecast Drivers'!$K$9/4) -> 320491.04 | S5: =R5*(1+'Forecast Drivers'!$K$9/4) -> 321292.26 | T5: =S5*(1+'Forecast Drivers'!$K$9/4) -> 322095.49 | U5: =T5*(1+'Forecast Drivers'!$K$9/4) -> 322900.73 | V5: =U5*(1+'Forecast Drivers'!$L$9/4) -> 323707.98 | W5: =V5*(1+'Forecast Drivers'!$L$9/4) -> 324517.25 | X5: =W5*(1+'Forecast Drivers'!$L$9/4) -> 325328.55 | Y5: =X5*(1+'Forecast Drivers'!$L$9/4) -> 326141.87 | Z5: =Y5*(1+'Forecast Drivers'!$M$9/4) -> 326957.22 | AA5: =Z5*(1+'Forecast Drivers'!$M$9/4) -> 327774.62 | AB5: =AA5*(1+'Forecast Drivers'!$M$9/4) -> 328594.05 | AC5: =AB5*(1+'Forecast Drivers'!$M$9/4) -> 329415.54 | AD5: =AC5*(1+'Forecast Drivers'!$M$9/4) -> 330239.08 | AE5: =AD5*(1+'Forecast Drivers'!$M$9/4) -> 331064.67 | AF5: =AE5*(1+'Forecast Drivers'!$M$9/4) -> 331892.34 | AG5: =AF5*(1+'Forecast Drivers'!$M$9/4) -> 332722.07
A6: Ln(Brasil) | E6: =LN(E5) -> 12.64515 | F6: =LN(F5) -> 12.647647 | G6: =LN(G5) -> 12.650144 | H6: =LN(H5) -> 12.652641 | I6: =LN(I5) -> 12.655138 | J6: =LN(J5) -> 12.657635 | K6: =LN(K5) -> 12.660131 | L6: =LN(L5) -> 12.662628 | ... AG6: =LN(AG5) -> 12.715063
A8: Forecast of ln(RPKS) | F8: ='Regression_Brazil '!$B$102+E6*'Regression_Brazil '!$B$103+'Domestic, Brazil estimate'!E3*'Regression_Brazil '!$B$104 -> 23.954496 | G8: ='Regression_Brazil '!$B$102+F6*'Regression_Brazil '!$B$103+'Domestic, Brazil estimate'!F3*'Regression_Brazil '!$B$104 -> 23.877222 | H8: ='Regression_Brazil '!$B$102+G6*'Regression_Brazil '!$B$103+'Domestic, Brazil estimate'!G3*'Regression_Brazil '!$B$104 -> 23.886269 | I8: ='Regression_Brazil '!$B$102+H6*'Regression_Brazil '!$B$103+'Domestic, Brazil estimate'!H3*'Regression_Brazil '!$B$104 -> 23.895316 | J8: ='Regression_Brazil '!$B$102+I6*'Regression_Brazil '!$B$103+'Domestic, Brazil estimate'!I3*'Regression_Brazil '!$B$104 -> 23.904363 | K8: ='Regression_Brazil '!$B$102+J6*'Regression_Brazil '!$B$103+'Domestic, Brazil estimate'!J3*'Regression_Brazil '!$B$104 -> 23.932966 | L8: ='Regression_Brazil '!$B$102+K6*'Regression_Brazil '!$B$103+'Domestic, Brazil estimate'!K3*'Regression_Brazil '!$B$104 -> 23.942013 | M8: ='Regression_Brazil '!$B$102+L6*'Regression_Brazil '!$B$103+'Domestic, Brazil estimate'!L3*'Regression_Brazil '!$B$104 -> 23.95106 | ... AG8: ='Regression_Brazil '!$B$102+AF6*'Regression_Brazil '!$B$103+'Domestic, Brazil estimate'!AF3*'Regression_Brazil '!$B$104 -> 24.183096
A9: RPKs Forecasted | F9: =EXP(F8) -> 2.5310777e+10 | G9: =EXP(G8) -> 2.3428567e+10 | H9: =EXP(H8) -> 2.3641489e+10 | I9: =EXP(I8) -> 2.3856346e+10 | J9: =EXP(J8) -> 2.4073156e+10 | K9: =EXP(K8) -> 2.4771652e+10 | L9: =EXP(L8) -> 2.4996781e+10 | M9: =EXP(M8) -> 2.5223955e+10 | ... AG9: =EXP(AG8) -> 3.1811563e+10
B10: 2019 | C10: =B20 -> 96449372986
A11: Quarterly sum | B11: 2020 | I11: =SUM(F9:I9) -> 9.6237179e+10 | M11: =SUM(J9:M9) -> 9.9065545e+10 | Q11: =SUM(N9:Q9) -> 1.0728522e+11 | U11: =SUM(R9:U9) -> 1.1262227e+11 | Y11: =SUM(V9:Y9) -> 1.1677253e+11 | AC11: =SUM(Z9:AC9) -> 1.2107574e+11 | AG11: =SUM(AD9:AG9) -> 1.2553752e+11
B12: 2021
A13: Forecasted annual series | B13: 2022 | C13: =I11 -> 9.6237179e+10
B14: 2023 | C14: =M11 -> 9.9065545e+10
B15: 2024 | C15: =Q11 -> 1.0728522e+11
B16: 2025 | C16: =U11 -> 1.1262227e+11
B17: 2026 | C17: =Y11 -> 1.1677253e+11
B18: 2027 | C18: =AC11 -> 1.2107574e+11
A19: Estimate | B19: 2028 | C19: =AG11 -> 1.2553752e+11
A20: 2019 RPks | B20: =B53 -> 96449372986
A22: 5 Years Implied CAGR | B22: =(C18/C13)^(1/5)-1 -> 0.04699076
A23: 8 Years GAGR | B23: =(C19/C10)^(1/8)-1 -> 0.033497113
A33: YEAR | B33: RPKs
A34: 2000 | B34: 25219968079
A35: 2001 | B35: 27336355492
A36: 2002 | B36: 26704516044
A37: 2003 | B37: 26099852761
A38: 2004 | B38: 28881235043
A39: 2005 | B39: 35252145026
A40: 2006 | B40: 40441366277
A41: 2007 | B41: 45470884457
A42: 2008 | B42: 49046278775
A43: 2009 | B43: 57194653909
A44: 2010 | B44: 69862011045
A45: 2011 | B45: 81103599006
... A53: 2019 | B53: 96449372986
A54: 2020 | B54: =48695532564 -> 48695532564
A55: 2021 | B55: 66373162099
A56: =B13 -> 2022 | B56: =C13 -> 9.6237179e+10
A57: =B14 -> 2023 | B57: =C14 -> 9.9065545e+10
A58: =B15 -> 2024 | B58: =C15 -> 1.0728522e+11
A59: =B16 -> 2025 | B59: =C16 -> 1.1262227e+11
A60: =B17 -> 2026 | B60: =C17 -> 1.1677253e+11
A61: =B18 -> 2027 | B61: =C18 -> 1.2107574e+11

Sheet Bra_Mkt_Sh
A2: Brazil Domesstic Market
B3: RPK Brazil mil | C3: historical | D3: historical | E3: historical | F3: historical | G3: historical | H3: historical | I3: historical | J3: historical | K3: historical | L3: historical | M3: expected | N3: forecast | O3: forecast | P3: forecast | Q3: forecast | R3: forecast
B4: Ano | C4: 2012 | D4: 2013 | E4: 2014 | F4: 2015 | G4: 2016 | H4: =G4+1 -> 2017 | I4: =H4+1 -> 2018 | J4: =I4+1 -> 2019 | K4: =J4+1 -> 2020 | L4: =K4+1 -> 2021 | M4: =L4+1 -> 2022 | N4: =M4+1 -> 2023 | O4: =N4+1 -> 2024 | ... R4: =Q4+1 -> 2027
B5: Domestica | C5: 86771900 | D5: 87739855 | E5: 93183427 | F5: 94279579 | G5: 88893631 | H5: 91857638 | I5: 95870487 | J5: 96449373 | K5: 48695533 | L5: 66373162 | M5: ='Domestic, Brazil estimate'!B56/1000 -> 96237179 | N5: ='Domestic, Brazil estimate'!B57/1000 -> 99065545 | O5: ='Domestic, Brazil estimate'!B58/1000 -> 1.0728522e+08 | P5: ='Domestic, Brazil estimate'!B59/1000 -> 1.1262227e+08 | Q5: ='Domestic, Brazil estimate'!B60/1000 -> 1.1677253e+08 | R5: ='Domestic, Brazil estimate'!B61/1000 -> 1.2107574e+08 | T5: input
B6: rate g | D6: =D5/C5-1 -> 0.011155171 | E6: =E5/D5-1 -> 0.062042177 | F6: =F5/E5-1 -> 0.011763384 | G6: =G5/F5-1 -> -0.057127407 | H6: =H5/G5-1 -> 0.033343296 | I6: =I5/H5-1 -> 0.043685521 | J6: =J5/I5-1 -> 0.006038211 | K6: =K5/J5-1 -> -0.4951182 | ... R6: =R5/Q5-1 -> 0.036851174
B7: growth | D7: =D5-C5 -> 967955.37 | E7: =E5-D5 -> 5443571.6 | F7: =F5-E5 -> 1096152.5 | G7: =G5-F5 -> -5385947.9 | H7: =H5-G5 -> 2964006.6 | I7: =I5-H5 -> 4012848.8 | J7: =J5-I5 -> 578886.23 | K7: =K5-J5 -> -47753840 | ... R7: =R5-Q5 -> 4303204.9
A10: GOL | B10: RPK mil | C10: 29266253 | D10: 30922480 | E10: 33661475 | F10: 33833189 | G10: 31999872 | H10: 33219792 | I10: 34258111 | J10: 36429290 | K10: 18838943 | L10: 22114929 | M10: =0.345377057469976*M5 -> 33238114 | N10: =M10+N11 -> 34072190 | O10: =N10+O11 -> 36447134 | P10: =O10+P11 -> 37957366 | Q10: =P10+Q11 -> 39131772 | R10: =Q10+R11 -> 40349455
B11: gorwth | D11: =D10-C10 -> 1656227 | E11: =E10-D10 -> 2738995 | F11: =F10-E10 -> 171714 | G11: =G10-F10 -> -1833317 | H11: =H10-G10 -> 1219920 | I11: =I10-H10 -> 1038319 | J11: =J10-I10 -> 2171179 | K11: =K10-J10 -> -17590347 | ... M11: =M10-L10 -> 11123185 | N11: =N14*N7 -> 834076.12 | O11: =O14*O7 -> 2374944.6 | P11: =P14*P7 -> 1510231.9 | Q11: =Q14*Q7 -> 1174405.1 | R11: =R14*R7 -> 1217683.3
B12: growth share | D12: =D11/D7 -> 1.7110572 | E12: =E11/E7 -> 0.50316138 | F12: =F11/F7 -> 0.15665156 | G12: =G11/G7 -> 0.34038892 | H12: =H11/H7 -> 0.41157803 | I12: =I11/I7 -> 0.2587486 | J12: =J11/J7 -> 3.7506144 | K12: =K11/K7 -> 0.3683546 | L12: =L11/L7 -> 0.18531817 | M12: =M11/$M$7 -> 0.3724611
B13: relative growth share | D13: =D12/(D12+D18+D30) -> 0.39005666 | E13: =E12/(E12+E18+E30) -> 0.36955147 | F13: =F12/(F12+F18+F30) -> -0.71098101 | G13: =G12/(G12+G18+G30) -> 0.28508009 | H13: =H12/(H12+H18+H30) -> 0.80898322 | I13: =I12/(I12+I18+I30) -> 0.33198767 | J13: =J12/(J12+J18+J30) -> 0.22052615 | K13: =K12/(K12+K18+K30) -> 0.39955071 | ... M13: =M12/(M12+M18+M30) -> 0.36851417
B14: avg relative growth share | M14: =SUMPRODUCT(D13:M13,$D$54:$M$54) -> 0.29814058 | N14: =$M14*(1-N$44-$N$36) -> 0.29489689 | O14: =$M14*(1-O$44-$N$36) -> 0.28893408 | P14: =$M14*(1-P$44-$N$36) -> 0.28297127 | Q14: =$M14*(1-Q$44-$N$36) -> 0.28297127 | R14: =$M14*(1-R$44-$N$36) -> 0.28297127
A16: AZUL | B16: RPK mil | C16: 8684707 | D16: 11420585 | E16: 15438446 | F16: 15992755 | G16: 15089537 | H16: 16364798 | I16: 17808150 | J16: 22588609 | K16: 13814405 | L16: 23303714 | M16: =0.31009361875521*M5 -> 29842535 | N16: =M16+N17 -> 30615691 | O16: =N16+O17 -> 32817172 | P16: =O16+P17 -> 34217098 | Q16: =P16+Q17 -> 35305725 | R16: =Q16+R17 -> 36434470
B17: growth | D17: =D16-C16 -> 2735878 | E17: =E16-D16 -> 4017861 | F17: =F16-E16 -> 554309 | G17: =G16-F16 -> -903218 | H17: =H16-G16 -> 1275261 | I17: =I16-H16 -> 1443352 | J17: =J16-I16 -> 4780459 | K17: =K16-J16 -> -8774204 | ... M17: =M16-L16 -> 6538821.2 | N17: =N20*N7 -> 773155.92 | O17: =O20*O7 -> 2201480.7 | P17: =P20*P7 -> 1399925.9 | Q17: =Q20*Q7 -> 1088627.6 | R17: =R20*R7 -> 1128744.8
B18: growth share | D18: =D17/D7 -> 2.8264506 | E18: =E17/E7 -> 0.7380928 | F18: =F17/F7 -> 0.50568604 | G18: =G17/G7 -> 0.16769899 | H18: =H17/H7 -> 0.43024904 | I18: =I17/I7 -> 0.35968263 | J18: =J17/J7 -> 8.2580286 | K18: =K17/K7 -> 0.18373819 | L18: =L17/L7 -> 0.53679759 | M18: =M17/$M$7 -> 0.21895317
B19: relative growht share | D19: =D18/(D12+D18+D30) -> 0.64432438 | E19: =E18/(E12+E18+E30) -> 0.54209899 | F19: =F18/(F12+F18+F30) -> -2.2951138 | G19: =G18/(G12+G18+G30) -> 0.14045005 | H19: =H18/(H12+H18+H30) -> 0.8456823 | I19: =I18/(I12+I18+I30) -> 0.46149119 | J19: =J18/(J12+J18+J30) -> 0.48555013 | K19: =K18/(K12+K18+K30) -> 0.19929905 | ... M19: =M18/(M12+M18+M30) -> 0.21663295
B20: avg relative growth share | M20: =SUMPRODUCT(D19:M19,$D$54:$M$54) -> 0.27636465 | N20: =$M20*(1-N$44-$N$36) -> 0.27335788 | O20: =$M20*(1-O$44-$N$36) -> 0.26783058 | P20: =$M20*(1-P$44-$N$36) -> 0.26230329 | Q20: =$M20*(1-Q$44-$N$36) -> 0.26230329 | R20: =$M20*(1-R$44-$N$36) -> 0.26230329
A22: GOL+AZUL | B22: RPK mil | C22: =C10+C16 -> 37950960 | D22: =D10+D16 -> 42343065 | E22: =E10+E16 -> 49099921 | F22: =F10+F16 -> 49825944 | G22: =G10+G16 -> 47089409 | H22: =H10+H16 -> 49584590 | I22: =I10+I16 -> 52066261 | J22: =J10+J16 -> 59017899 | ... L22: =L10+L16 -> 45418643 | M22: =M59*M5 -> 63080649 | N22: =M22+N23 -> 65135796 | O22: =N22+O23 -> 70987721 | P22: =O22+P23 -> 74709042 | Q22: =P22+Q23 -> 77602862 | R22: =Q22+R23 -> 80603323
B23: growth | D23: =D22-C22 -> 4392105 | E23: =E22-D22 -> 6756856 | F23: =F22-E22 -> 726023 | G23: =G22-F22 -> -2736535 | H23: =H22-G22 -> 2495181 | I23: =I22-H22 -> 2481671 | J23: =J22-I22 -> 6951638 | K23: =K22-J22 -> -26364551 | ... M23: =M22-L22 -> 17662006 | N23: =N7*N26 -> 2055147.3 | O23: =O7*O26 -> 5851924.6 | P23: =P7*P26 -> 3721321.4 | Q23: =Q7*Q26 -> 2893819.8 | R23: =R7*R26 -> 3000460.4
B24: growth share | D24: =D23/D7 -> 4.5375078 | E24: =E23/E7 -> 1.2412542 | F24: =F23/F7 -> 0.6623376 | G24: =G23/G7 -> 0.50808791 | H24: =H23/H7 -> 0.84182707 | I24: =I23/I7 -> 0.61843122 | J24: =J23/J7 -> 12.008643 | K24: =K23/K7 -> 0.55209279 | ... M24: =M23/M7 -> 0.59141427
B25: avg relative growth share | M25: =SUMPRODUCT(D$54:M$54,D24:M24) -> 2.081362
B26: normalized avg growth share | M26: =M25/(M25+M31) -> 0.7339598 | N26: =$M$26-$M$26*N49 -> 0.7266202 | O26: =$M$26*(1-O49) -> 0.711941 | P26: =$M$26*(1-P49) -> 0.69726181 | Q26: =$M$26*(1-Q49) -> 0.69726181 | R26: =$M$26*(1-R49) -> 0.69726181
A28: LATAM | B28: RPK mil | C28: 35083621 | D28: 34937635 | E28: 35592453 | F28: 34624913 | G28: 30930564 | H28: 29943350 | I28: 30589262 | J28: 33483073 | K28: 15822306 | L28: 20247851 | M28: =M60*M5 -> 32769717 | N28: =M28+N29 -> 33514652 | O28: =N28+O29 -> 35635813 | P28: =O28+P29 -> 36984690 | Q28: =P28+Q29 -> 38033619 | R28: =Q28+R29 -> 39121204
B29: growth | D29: =D28-C28 -> -145986 | E29: =E28-D28 -> 654818 | F29: =F28-E28 -> -967540 | G29: =G28-F28 -> -3694349 | H29: =H28-G28 -> -987214 | I29: =I28-H28 -> 645912 | J29: =J28-I28 -> 2893811 | K29: =K28-J28 -> -17660767 | ... M29: =M28-L28 -> 12521866 | N29: =N7*N32 -> 744934.28 | O29: =O7*O32 -> 2121161.4 | P29: =P7*P32 -> 1348876.5 | Q29: =Q7*Q32 -> 1048929.9 | R29: =R7*R32 -> 1087584.2
B30: growth share | D30: =D29/D7 -> -0.15081894 | E30: =E29/E7 -> 0.12029198 | F30: =F29/F7 -> -0.88266918 | G30: =G29/G7 -> 0.68592364 | H30: =H29/H7 -> -0.33306741 | I30: =I29/I7 -> 0.16096096 | J30: =J29/J7 -> 4.9989287 | K30: =K29/K7 -> 0.36982925 | ... M30: =M29/M7 -> 0.41929611
B31: avg relative growth share | M31: =SUMPRODUCT($D$54:$M$54,D30:M30) -> 0.75443636
B32: normalized avg growth share | M32: =M31/(M31+M25) -> 0.2660402 | N32: =$M$32*(1-N49) -> 0.2633798 | O32: =$M$32*(1-O49) -> 0.258059 | P32: =$M$32*(1-P49) -> 0.25273819 | Q32: =$M$32*(1-Q49) -> 0.25273819 | R32: =$M$32*(1-R49) -> 0.25273819
A34: PASSAREDO | B34: RPK mil | C34: 467684 | D34: 420876 | E34: 520810 | F34: 749536 | G34: 566167 | H34: 351156 | I34: 283988 | J34: 275303 | K34: 150414 | L34: 202754 | M34: 229026.67 | N34: =M34+N35 -> 231514.9 | O34: =N34+O35 -> 238746.11 | P34: =O34+P35 -> 243441.34 | Q34: =P34+Q35 -> 247092.51 | R34: =Q34+R35 -> 250878.22
B35: growth | D35: =D34-C34 -> -46808 | E35: =E34-D34 -> 99934 | F35: =F34-E34 -> 228726 | G35: =G34-F34 -> -183369 | H35: =H34-G34 -> -215011 | I35: =I34-H34 -> -67168 | J35: =J34-I34 -> -8685 | K35: =K34-J34 -> -124889 | ... M35: =M34-L34 -> 26272.667 | N35: =N36*N7 -> 2488.2352 | O35: =O36*O7 -> 7231.2045 | P35: =P36*P7 -> 4695.234 | Q35: =Q36*Q7 -> 3651.1656 | R35: =R36*R7 -> 3785.7154
B36: growth share | D36: =D35/D7 -> -0.048357602 | E36: =E35/E7 -> 0.018358168 | F36: =F35/F7 -> 0.20866258 | G36: =G35/G7 -> 0.034045818 | H36: =H35/H7 -> -0.072540661 | I36: =I35/I7 -> -0.016738233 | J36: =J35/J7 -> -0.015002948 | K36: =K35/K7 -> 0.0026152661 | L36: =L35/L7 -> 0.0029608042 | M36: =M35/$M$7 -> 0.00087974322 | N36: =$M$36 -> 0.00087974322 | O36: =$M$36 -> 0.00087974322 | P36: =$M$36 -> 0.00087974322 | Q36: =$M$36 -> 0.00087974322 | R36: =$M$36 -> 0.00087974322
A38: AVAINCA | B38: RPK mil | C38: 4670242 | D38: 6318866 | E38: 7826986 | F38: 8926701 | G38: 10205055 | H38: 11878795 | I38: 12822257 | J38: 3553676
B39: grwoth | D39: =D38-C38 -> 1648624 | E39: =E38-D38 -> 1508120 | F39: =F38-E38 -> 1099715 | G39: =G38-F38 -> 1278354 | H39: =H38-G38 -> 1673740 | I39: =I38-H38 -> 943462 | J39: =J38-I38 -> -9268581 | K39: =K38-J38 -> -3553676
B40: grwoth share | D40: =D39/D7 -> 1.7032025 | E40: =E39/E7 -> 0.27704605 | F40: =F39/F7 -> 1.00325 | G40: =G39/G7 -> -0.23734986 | H40: =H39/H7 -> 0.56468835 | I40: =I39/I7 -> 0.23511028 | J40: =J39/J7 -> -16.011058 | K40: =K39/K7 -> 0.074416549
A42: OTHERS | B42: RPK mil | C42: =C5-C10-C16-C28-C34-C38 -> 8599392.8 | D42: =D5-D10-D16-D28-D34-D38 -> 3719413.1 | E42: =E5-E10-E16-E28-E34-E38 -> 143256.75 | F42: =F5-F10-F16-F28-F34-F38 -> 152485.22 | G42: =G5-G10-G16-G28-G34-G38 -> 102436.32 | H42: =H5-H10-H16-H28-H34-H38 -> 99746.947 | I42: =I5-I10-I16-I28-I34-I38 -> 108718.76 | J42: =J5-J10-J16-J28-J34-J38 -> 119421.99 | ... L42: =L5-L10-L16-L28-L34-L38 -> 503914.1 | M42: 136158.83 | N42: =M42+N43 -> 164442.48 | O42: =N42+O43 -> 411032.77 | P42: =O42+P43 -> 677885.29 | Q42: =P42+Q43 -> 885398.43 | R42: =Q42+R43 -> 1100558.7
B43: growth | D43: =D42-C42 -> -4879979.6 | E43: =E42-D42 -> -3576156.4 | F43: =F42-E42 -> 9228.474 | G43: =G42-F42 -> -50048.898 | H43: =H42-G42 -> -2689.377 | I43: =I42-H42 -> 8971.812 | J43: =J42-I42 -> 10703.227 | K43: =K42-J42 -> -49957.422 | ... M43: =M42-L42 -> -367755.27 | N43: =N44*N7 -> 28283.653 | O43: =O44*O7 -> 246590.29 | P43: =P44*P7 -> 266852.52 | Q43: =Q44*Q7 -> 207513.14 | R43: =R44*R7 -> 215160.25
B44: growth share | D44: =D43/D7 -> -5.0415337 | E44: =E43/E7 -> -0.65695037 | F44: =F43/F7 -> 0.0084189693 | G44: =G43/G7 -> 0.0092924958 | H44: =H43/H7 -> -0.00090734514 | I44: =I43/I7 -> 0.0022357712 | J44: =J43/J7 -> 0.018489345 | K44: =K43/K7 -> 0.0010461446 | L44: =L43/L7 -> 0.024576233 | M44: =M43/$M$7 -> -0.012314327 | N44: 0.01 | O44: 0.03 | P44: 0.05 | Q44: 0.05 | R44: 0.05
A46: OTHERS+AVIANCA+PASSAREDO | B46: RPK mil | C46: =C34+C38+C42 -> 13737319 | D46: =D34+D38+D42 -> 10459155 | E46: =E34+E38+E42 -> 8491052.7 | F46: =F34+F38+F42 -> 9828722.2 | G46: =G34+G38+G42 -> 10873658 | H46: =H34+H38+H42 -> 12329698 | I46: =I34+I38+I42 -> 13214964 | J46: =J34+J38+J42 -> 3948401 | ... L46: =L34+L38+L42 -> 706668.1 | M46: =M61*M5 -> 386812.96 | N46: =M46+N47 -> 415096.61 | O46: =N46+O47 -> 661686.9 | P46: =O46+P47 -> 928539.42 | Q46: =P46+Q47 -> 1136052.6 | R46: =Q46+R47 -> 1351212.8
B47: growth | D47: =D46-C46 -> -3278163.6 | E47: =E46-D46 -> -1968102.4 | F47: =F46-E46 -> 1337669.5 | G47: =G46-F46 -> 1044936.1 | H47: =H46-G46 -> 1456039.6 | I47: =I46-H46 -> 885265.81 | J47: =J46-I46 -> -9266562.8 | K47: =K46-J46 -> -3728522.4 | ... M47: =M46-L46 -> -319855.14 | N47: =N49*N7 -> 28283.653 | O47: =O49*O7 -> 246590.29 | P47: =P49*P7 -> 266852.52 | Q47: =Q49*Q7 -> 207513.14 | R47: =R49*R7 -> 215160.25
B48: growth share | D48: =D47/D7 -> -3.3866888 | E48: =E47/E7 -> -0.36154616 | F48: =F47/F7 -> 1.2203316 | G48: =G47/G7 -> -0.19401155 | H48: =H47/H7 -> 0.49124034 | I48: =I47/I7 -> 0.22060782 | J48: =J47/J7 -> -16.007572 | K48: =K47/K7 -> 0.07807796 | ... M48: =M47/M7 -> -0.010710386
B49: normalized avg relative growth share | M49: 0 | N49: 0.01 | O49: 0.03 | P49: 0.05 | Q49: 0.05 | R49: 0.05 | T49: arbitrary competition
A52: SMOOTHED AVERAGE | B52: Coeff smoothed avg | C52: costants | D52: 10 | E52: 9 | F52: 8 | G52: 7 | H52: 6 | I52: 5 | J52: 4 | K52: 3 | L52: 2 | M52: 1
B53: Gross weight | C53: 0.8 | D53: =$C$53^D52 -> 0.10737418 | E53: =$C$53^E52 -> 0.13421773 | F53: =$C$53^F52 -> 0.16777216 | G53: =$C$53^G52 -> 0.2097152 | H53: =$C$53^H52 -> 0.262144 | I53: =$C$53^I52 -> 0.32768 | J53: =$C$53^J52 -> 0.4096 | K53: =$C$53^K52 -> 0.512 | ... M53: =$C$53^M52 -> 0.8
B54: Nrmalized weight | C54: =SUM(D53:M53) -> 3.5705033 | D54: =D53/$C$54 -> 0.030072562 | E54: =E53/$C$54 -> 0.037590703 | F54: =F53/$C$54 -> 0.046988379 | G54: =G53/$C$54 -> 0.058735473 | H54: =H53/$C$54 -> 0.073419342 | I54: =I53/$C$54 -> 0.091774177 | J54: =J53/$C$54 -> 0.11471772 | K54: =K53/$C$54 -> 0.14339715 | ... M54: =M53/$C$54 -> 0.22405805
B57: RPK Brazil mil | C57: historical | D57: historical | E57: historical | F57: historical | G57: historical | H57: historical | I57: historical | J57: historical | K57: historical | L57: historical | M57: expected | N57: forecast | O57: forecast | P57: forecast | Q57: forecast | R57: forecast | T57: OUTPUT
A58: MKT SHARE | B58: AnNo | C58: 2012 | D58: 2013 | E58: 2014 | F58: 2015 | G58: 2016 | H58: 2017 | I58: 2018 | J58: 2019 | K58: 2020 | L58: 2021 | M58: 2022 | N58: 2023 | O58: 2024 | P58: 2025 | Q58: 2026 | R58: 2027
B59: GOL+AZUL | C59: =C22/C5 -> 0.43736463 | D59: =D22/D5 -> 0.48259784 | E59: =E22/E5 -> 0.52691689 | F59: =F22/F5 -> 0.52849137 | G59: =G22/G5 -> 0.52972759 | H59: =H22/H5 -> 0.53979823 | I59: =I22/I5 -> 0.54308957 | J59: =J22/J5 -> 0.61190547 | ... L59: =L22/L5 -> 0.68429229 | M59: 0.65547068 | N59: =N22/N5 -> 0.65750203 | O59: =O22/O5 -> 0.66167288 | P59: =P22/P5 -> 0.6633594 | Q59: =Q22/Q5 -> 0.66456434 | R59: =R22/R5 -> 0.66572645
B60: LATAM | C60: =C28/C5 -> 0.40432007 | D60: =D28/D5 -> 0.39819572 | E60: =E28/E5 -> 0.38196119 | F60: =F28/F5 -> 0.36725782 | G60: =G28/G5 -> 0.34795028 | H60: =H28/H5 -> 0.32597561 | I60: =I28/I5 -> 0.3190686 | J60: =J28/J5 -> 0.34715698 | ... L60: =L28/L5 -> 0.30506082 | M60: 0.34050995 | N60: =N28/N5 -> 0.33830785 | O60: =O28/O5 -> 0.33215957 | P60: =P28/P5 -> 0.32839588 | Q60: =Q28/Q5 -> 0.32570689 | R60: =R28/R5 -> 0.32311348
B61: OTHERS | C61: =C46/C5 -> 0.15831529 | D61: =D46/D5 -> 0.11920643 | E61: =E46/E5 -> 0.09112192 | F61: =F46/F5 -> 0.10425081 | G61: =G46/G5 -> 0.12232213 | H61: =H46/H5 -> 0.13422616 | I61: =I46/I5 -> 0.13784183 | J61: =J46/J5 -> 0.04093755 | ... L61: =L46/L5 -> 0.010646895 | M61: 0.0040193713 | N61: =N46/N5 -> 0.0041901209 | O61: =O46/O5 -> 0.0061675494 | P61: =P46/P5 -> 0.0082447229 | Q61: =Q46/Q5 -> 0.0097287652 | R61: =R46/R5 -> 0.011160062
B62: TOTALE | C62: =SUM(C59:C61) -> 1 | D62: =SUM(D59:D61) -> 1 | E62: =SUM(E59:E61) -> 1 | F62: =SUM(F59:F61) -> 1 | G62: =SUM(G59:G61) -> 1 | H62: =SUM(H59:H61) -> 1 | I62: =SUM(I59:I61) -> 1 | J62: =SUM(J59:J61) -> 1 | ... R62: =SUM(R59:R61) -> 1
A64: RPK LATAM | B64: RPK LATAM mil
B65: LATAM | C65: =C60*C5 -> 35083621 | D65: =D60*D5 -> 34937635 | E65: =E60*E5 -> 35592453 | F65: =F60*F5 -> 34624913 | G65: =G60*G5 -> 30930564 | H65: =H60*H5 -> 29943350 | I65: =I60*I5 -> 30589262 | J65: =J60*J5 -> 33483073 | ... R65: =R60*R5 -> 39121204
I67: Average | J67: =J59/2 -> 0.30595274 | K67: =K59/2 -> 0.33528074 | L67: =L59/2 -> 0.34214614 | M67: =M59/2 -> 0.32773534 | N67: =N59/2 -> 0.32875101 | O67: =O59/2 -> 0.33083644 | P67: =P59/2 -> 0.3316797 | Q67: =Q59/2 -> 0.33228217 | R67: =R59/2 -> 0.33286323

Sheet SSC_regression
A5: Mln of 2017 USD | J5: Model: non-lagged with intercept -> Model2)
A6: observation_date | B6: SSC GDP | C6: DJFUELUSGULF | D6: #Pass | E6: log(GDP) | F6: log(JF_t-1) | G6: log(#Pass) | J6: OUTPUT RIEPILOGO
A7: 36526 | B7: 830452.54 | C7: 0.849952 | D7: 16657396 | E7: =LN(B7) -> 13.629726 | F7: =LOG(C7) -> -0.0706056 | G7: =LN(D7) -> 16.628365
A8: 36892 | B8: 848889.14 | C8: 0.724988 | D8: 18453926 | E8: =LN(B8) -> 13.651684 | F8: =LOG(C8) -> -0.13966918 | G8: =LN(D8) -> 16.730788 | J8: Statistica della regressione
A9: 37257 | B9: 875906.35 | C9: 0.687064 | D9: 17681498 | E9: =LN(B9) -> 13.683014 | F9: =LOG(C9) -> -0.16300281 | G9: =LN(D9) -> 16.688029 | J9: R multiplo | K9: 0.99198364
A10: 37622 | B10: 908985.14 | C10: 0.8236 | D10: 18136950 | E10: =LN(B10) -> 13.720084 | F10: =LOG(C10) -> -0.084283662 | G10: =LN(D10) -> 16.713462 | J10: R al quadrato | K10: 0.98403155
A11: 37987 | B11: 964222.45 | C11: 1.1511365 | D11: 19346278 | E11: =LN(B11) -> 13.779077 | F11: =LOG(C11) -> 0.061126842 | G11: =LN(D11) -> 16.778011 | J11: R al quadrato corretto | K11: 0.98215291
A12: 38353 | B12: 1017197.2 | C12: 1.7155976 | D12: 22266671 | E12: =LN(B12) -> 13.832562 | F12: =LOG(C12) -> 0.23441543 | G12: =LN(D12) -> 16.918602 | J12: Errore standard | K12: 0.075972289
A13: 38718 | B13: 1083034.4 | C13: 1.9230201 | D13: 22961308 | E13: =LN(B13) -> 13.895277 | F13: =LOG(C13) -> 0.28398382 | G13: =LN(D13) -> 16.949321 | J13: Osservazioni | K13: 20
A14: 39083 | B14: 1148228.3 | C14: 2.1309127 | D14: 26725504 | E14: =LN(B14) -> 13.953731 | F14: =LOG(C14) -> 0.32856566 | G14: =LN(D14) -> 17.101129
A15: 39448 | B15: 1204593.8 | C15: 2.9644466 | D15: 29471876 | E15: =LN(B15) -> 14.001653 | F15: =LOG(C15) -> 0.47194364 | G15: =LN(D15) -> 17.198947 | J15: ANALISI VARIANZA
A16: 39814 | B16: 1208571.9 | C16: 1.6642897 | D16: 28952367 | E16: =LN(B16) -> 14.00495 | F16: =LOG(C16) -> 0.22122892 | G16: =LN(D16) -> 17.181163 | K16: gdl | L16: SQ | M16: MQ | N16: F | O16: Significatività F
A17: 40179 | B17: 1275685.7 | C17: 2.1498805 | D17: 38125791 | E17: =LN(B17) -> 14.058994 | F17: =LOG(C17) -> 0.33241432 | G17: =LN(D17) -> 17.456402 | J17: Regressione | K17: 2 | L17: 6.0465213 | M17: 3.0232607 | N17: 523.7996 | O17: 5.3423661e-16
A18: 40544 | B18: 1361150.8 | C18: 2.9985119 | D18: 43042133 | E18: =LN(B18) -> 14.123841 | F18: =LOG(C18) -> 0.47690578 | G18: =LN(D18) -> 17.57769 | J18: Residuo | K18: 17 | L18: 0.098120409 | M18: 0.0057717888
A19: 40909 | B19: 1428924.1 | C19: 3.0561905 | D19: 49738577 | E19: =LN(B19) -> 14.172432 | F19: =LOG(C19) -> 0.48518042 | G19: =LN(D19) -> 17.722291 | J19: Totale | K19: 19 | L19: 6.1446417
A20: 41275 | B20: 1500099.2 | C20: 2.9204921 | D20: 58148980 | E20: =LN(B20) -> 14.221042 | F20: =LOG(C20) -> 0.46545603 | G20: =LN(D20) -> 17.878519
A21: 41640 | B21: 1548460.9 | C21: 2.6927024 | D21: 60982817 | E21: =LN(B21) -> 14.252772 | F21: =LOG(C21) -> 0.43018835 | G21: =LN(D21) -> 17.926103 | K21: Coefficienti | L21: Errore standard | M21: Stat t | N21: Valore di significatività | O21: Inferiore 95% | P21: Superiore 95% | Q21: Inferiore 95.0% | R21: Superiore 95.0%
A22: 42005 | B22: 1587221 | C22: 1.5217937 | D22: 65471963 | E22: =LN(B22) -> 14.277495 | F22: =LOG(C22) -> 0.18235577 | G22: =LN(D22) -> 17.997133 | J22: Intercetta | K22: -16.709699 | L22: 1.2686597 | M22: -13.171144 | N22: 2.3907429e-10 | O22: -19.386337 | P22: -14.033061 | Q22: -19.386337 | R22: -14.033061
A23: 42370 | B23: 1619112.7 | C23: 1.2517063 | D23: 68806576 | E23: =LN(B23) -> 14.297389 | F23: =LOG(C23) -> 0.097502455 | G23: =LN(D23) -> 18.04681 | J23: Variabile X 1 | K23: 2.4366987 | L23: 0.091517309 | M23: 26.62555 | N23: 2.6680468e-15 | O23: 2.2436141 | P23: 2.6297834 | Q23: 2.2436141 | R23: 2.6297834
A24: 42736 | B24: 1646550 | C24: 1.55794 | D24: 71385257 | E24: =LN(B24) -> 14.314193 | F24: =LOG(C24) -> 0.19255073 | G24: =LN(D24) -> 18.083602 | J24: Variabile X 2 | K24: -0.35241045 | L24: 0.10890401 | M24: -3.2359731 | N24: 0.0048564608 | O24: -0.58217782 | P24: -0.12264307 | Q24: -0.58217782 | R24: -0.12264307
A25: 43101 | B25: 1697168.4 | C25: 2.0268514 | D25: 76345010 | E25: =LN(B25) -> 14.344472 | F25: =LOG(C25) -> 0.30682191 | G25: =LN(D25) -> 18.150773
A26: 43466 | B26: 1732672.5 | C26: 1.8787108 | D26: 81878152 | E26: =LN(B26) -> 14.365176 | F26: =LOG(C26) -> 0.27385994 | G26: =LN(D26) -> 18.220743

Sheet SSC estimate
B3: data | D3: 2000 | E3: 2001 | F3: 2002 | G3: 2003 | H3: 2004 | I3: 2005 | J3: 2006 | K3: 2007 | L3: 2008 | M3: 2009 | N3: 2010 | O3: 2011 | P3: 2012 | Q3: 2013 | R3: 2014 | S3: 2015 | T3: 2016 | U3: 2017 | V3: 2018 | W3: 2019
B4: #Passengers | D4: 16657396 | E4: 18453926 | F4: 17681498 | G4: 18136950 | H4: 19346278 | I4: 22266671 | J4: 22961308 | K4: 26725504 | L4: 29471876 | M4: 28952367 | N4: 38125791 | O4: 43042133 | P4: 49738577 | Q4: 58148980 | R4: 60982817 | S4: 65471963 | T4: 68806576 | U4: 71385257 | V4: 76345010 | W4: 81878152
B5: GDP real | D5: =SUM(D1:D4) -> 16657396 | E5: =SUM(E1:E4) -> 18453926 | F5: =SUM(F1:F4) -> 17681498 | G5: =SUM(G1:G4) -> 18136950 | H5: =SUM(H1:H4) -> 19346278 | I5: =SUM(I1:I4) -> 22266671 | J5: =SUM(J1:J4) -> 22961308 | K5: =SUM(K1:K4) -> 26725504 | ... W5: =SUM(W1:W4) -> 81878152
B6: jet fuel cost | D6: 0.849952 | E6: 0.724988 | F6: 0.687064 | G6: 0.8236 | H6: 1.1511365 | I6: 1.7155976 | J6: 1.9230201 | K6: 2.1309127 | L6: 2.9644466 | M6: 1.6642897 | N6: 2.1498805 | O6: 2.9985119 | P6: 3.0561905 | Q6: 2.9204921 | R6: 2.6927024 | S6: 1.5217937 | T6: 1.2517063 | U6: 1.55794 | V6: 2.0268514 | W6: 1.8787108
B9: year | C9: source | D9: 2020 | E9: 2021 | F9: 2022 | G9: 2023 | H9: 2024 | I9: 2025 | J9: 2026 | K9: 2027 | O9: Passport | P9: 2019 | Q9: 2020 | R9: 2021
B10: GDP real | D10: 1598026.5 | E10: 1771457.3 | F10: =E10*(1+F11) -> 1789171.9 | G10: =F10*(1+G11) -> 1807063.6 | H10: =G10*(1+H11) -> 1825134.2 | I10: =H10*(1+I11) -> 1843385.6 | J10: =I10*(1+J11) -> 1861819.4 | K10: =J10*(1+K11) -> 1880437.6 | O10: real gdp colombia | P10: 695584.44 | Q10: =P10*(1+Q11) -> 646559.65 | R10: =Q10*(1+R11) -> 715592.82
B11: real GDP growth SSC | F11: 0.01 | G11: 0.01 | H11: 0.01 | I11: 0.01 | J11: 0.01 | K11: 0.01 | O11: colombia g | Q11: =-7.048/(100) -> -0.07048 | R11: =10.677/(100) -> 0.10677
B12: jet fuel cost | C12: latam bp | F12: 3.43 | G12: 3.1 | H12: 2.38 | I12: 2.38 | J12: 2.38 | K12: 2.38 | O12: real gdp chile | P12: 443616.22 | Q12: =P12*(1+Q13) -> 417096.84 | R12: =Q12*(1+R13) -> 465763.7
O13: chile g | Q13: =-5.978/(100) -> -0.05978 | R13: =11.668/(100) -> 0.11668
O14: real gdp perù | P14: 399324.97 | Q14: =P14*(1+Q15) -> 355343.32 | R14: =Q14*(1+R15) -> 403492.34
B15: Year | D15: 2020 | E15: 2021 | F15: 2022 | G15: 2023 | H15: 2024 | I15: 2025 | J15: 2026 | K15: 2027 | O15: perù g | Q15: =-11.014/(100) -> -0.11014 | R15: =13.55/(100) -> 0.1355
B16: ln(GDP) | D16: =LN(D10) -> 14.28428 | E16: =LN(E10) -> 14.387313 | F16: =LN(F10) -> 14.397263 | G16: =LN(G10) -> 14.407214 | H16: =LN(H10) -> 14.417164 | I16: =LN(I10) -> 14.427114 | J16: =LN(J10) -> 14.437065 | K16: =LN(K10) -> 14.447015 | O16: rela gdp ecuador | P16: 194146.83 | Q16: =P16*(1+Q17) -> 179026.67 | R16: =Q16*(1+R17) -> 186608.45
B17: ln(JF) | F17: =LN(F12) -> 1.2325603 | G17: =LN(G12) -> 1.1314021 | H17: =LN(H12) -> 0.86710049 | I17: =LN(I12) -> 0.86710049 | J17: =LN(J12) -> 0.86710049 | K17: =LN(K12) -> 0.86710049 | O17: ecuador g | Q17: =-7.788/(100) -> -0.07788 | R17: =4.235/(100) -> 0.04235
B18: ln(#P) forecasted | D18: =LN(P26) -> 17.116708 | F18: =$P$21+$P$22*F16+$P$23*F17 -> 17.937727 | G18: =$P$21+$P$22*G16+$P$23*G17 -> 17.997622 | H18: =$P$21+$P$22*H16+$P$23*H17 -> 18.115011 | I18: =$P$21+$P$22*I16+$P$23*I17 -> 18.139257 | J18: =$P$21+$P$22*J16+$P$23*J17 -> 18.163503 | K18: =$P$21+$P$22*K16+$P$23*K17 -> 18.187749 | O18: TOTAL | P18: =SUM(P10,P12,P14,P16) -> 1732672.5 | Q18: =SUM(Q10,Q12,Q14,Q16) -> 1598026.5 | R18: =SUM(R10,R12,R14,R16) -> 1771457.3
B19: #P forecasted | D19: =EXP(D18) -> 27145135 | F19: =EXP(F18) -> 61695850 | G19: =EXP(G18) -> 65504040 | H19: =EXP(H18) -> 73662984 | I19: =EXP(I18) -> 75470842 | J19: =EXP(J18) -> 77323069 | K19: =EXP(K18) -> 79220753
O20: Estimation | P20: Coefficienti
O21: Intercetta | P21: =SSC_regression!K22 -> -16.709699
D22: %CAGR | E22: =(K19/F19)^(1/5)-1 -> 0.051275645 | O22: Variabile X 1 | P22: =SSC_regression!K23 -> 2.4366987
D23: %CAGR | E23: =(K19/F19)^(1/5)-1 -> 0.051275645 | O23: Variabile X 2 | P23: =SSC_regression!K24 -> -0.35241045
O25: Year | P25: #P_statista
O26: 2020 | P26: 27145135

Sheet SSC_Mkt_Sh
G3: historical | H3: historical | I3: historical | J3: historical | K3: historical | L3: historical | M3: historical | N3: expected | O3: forecast | P3: forecast | Q3: forecast | R3: forecast | S3: forecast
A4: CHILE | B4: 2010 | C4: 2011 | D4: 2012 | E4: 2013 | F4: 2014 | G4: 2015 | H4: 2016 | I4: 2017 | J4: 2018 | K4: 2019 | L4: 2020 | M4: 2021 | N4: 2022 | O4: 2023 | P4: 2024 | Q4: 2025 | R4: 2026 | S4: 2027
A5: LATAM | B5: 4629210 | C5: 5369559 | D5: 6345222 | E5: 7014908 | F5: 7302247 | G5: 7324006 | H5: 7980119 | I5: 7876321 | J5: 8206661 | K5: 8779272 | L5: 3687207 | M5: 5395804
A6: SKY+JETSMART+AEROVIAS+ONE | B6: 1151861 | C6: 1362328 | D6: 1687513 | E6: 2169635 | F6: 2414076 | G6: 2572820 | H6: 2855260 | I6: 3576877 | J6: 5237582 | K6: 6206233 | L6: 2693501 | M6: 3718439
A7: OTHERS | B7: 193659 | C7: 293101 | D7: 302106 | E7: 288659 | F7: 97267 | G7: 1288 | H7: 579 | I7: 144430 | J7: 16527 | K7: 0 | L7: 0 | M7: 0
A8: TOTAL | B8: 5974730 | C8: 7024988 | D8: 8334841 | E8: 9473202 | F8: 9813590 | G8: 9898114 | H8: 10835958 | I8: 11597628 | J8: 13460770 | K8: 14985505 | L8: 6380708 | M8: 9114243
A10: PERU'
A11: LATAM | D11: 4488512 | E11: 5256240 | F11: 5655413 | G11: 6213918 | H11: 6627050 | I11: 6746867 | J11: 7393426 | K11: 8604304 | L11: 3075744 | M11: 5493661
A12: SKY+STAR+VIVA | D12: 785763 | E12: 627172 | F12: 624680 | G12: 598928 | H12: 486526 | I12: 681329 | J12: 1118829 | K12: 3181721 | L12: 1591883 | M12: 2379912
A13: OTHERS | D13: 1947129 | E13: 2406656 | F13: 2670072 | G13: 3192398 | H13: 3680455 | I13: 4280102 | J13: 4198410 | K13: 2042163 | L13: 208925 | M13: 261713
A14: TOTALE | D14: 7221404 | E14: 8290068 | F14: 8950165 | G14: 10005244 | H14: 10794031 | I14: 11708298 | J14: 12710665 | K14: 13828188 | L14: 4876552 | M14: 8135286
A16: COLOMBIA
A17: AVIANCA | F17: 13839652 | G17: 15430530 | H17: 15946804 | I17: 14922584 | J17: 15289316 | K17: 15413797 | L17: 4378240 | M17: 9112191
A18: LATAM | F18: 4407208 | G18: 4637632 | H18: 4873385 | I18: 4867605 | J18: 5080897 | K18: 5933921 | L18: 2165847 | M18: 5894500
A19: VIVA+SATENA+EASYFLY+WINGO | F19: 4491866 | G19: 4974972 | H19: 5327362 | I19: 5598615 | J19: 6052642 | K19: 7465865 | L19: 3149887 | M19: 8297719
A20: OTHERS | F20: 863282 | G20: 813300 | H20: 764354 | I20: 713293 | J20: 727581 | K20: 1195526 | L20: 530531 | M20: 977170
A21: TOTALE | F21: 23602008 | G21: 25856434 | H21: 26911905 | I21: 26102097 | J21: 27150436 | K21: 30009109 | L21: 10224505 | M21: 24281580
F23: historical | G23: historical | H23: historical | I23: historical | J23: historical | K23: historical | L23: historical | M23: historical | N23: expected | O23: forecast | P23: forecast | Q23: forecast | R23: forecast | S23: forecast
A24: Number of Passengers | F24: 2014 | G24: 2015 | H24: 2016 | I24: 2017 | J24: 2018 | K24: 2019 | L24: 2020 | M24: 2021 | N24: 2022 | O24: 2023 | P24: 2024 | Q24: 2025 | R24: 2026 | S24: 2027
A25: TOTAL SCC MARKET | F25: 42365763 | G25: 45759792 | H25: 48541894 | I25: 49408023 | J25: 53321871 | K25: 58822802 | L25: 21481765 | M25: 41531109 | N25: ='SSC estimate'!F19 -> 61695850 | O25: ='SSC estimate'!G19 -> 65504040 | P25: ='SSC estimate'!H19 -> 73662984 | Q25: ='SSC estimate'!I19 -> 75470842 | R25: ='SSC estimate'!J19 -> 77323069 | S25: ='SSC estimate'!K19 -> 79220753 | U25: input
A26: rate g | G26: =G25/F25-1 -> 0.080112543 | H26: =H25/G25-1 -> 0.06079796 | I26: =I25/H25-1 -> 0.017842917 | J26: =J25/I25-1 -> 0.079214827 | K26: =K25/J25-1 -> 0.10316463 | L26: =L25/K25-1 -> -0.63480548 | M26: =M25/L25-1 -> 0.93331921 | N26: =N25/M25-1 -> 0.48553341 | ... S26: =S25/R25-1 -> 0.024542282
A27: gorwth | G27: =G25-F25 -> 3394029 | H27: =H25-G25 -> 2782102 | I27: =I25-H25 -> 866129 | J27: =J25-I25 -> 3913848 | K27: =K25-J25 -> 5500931 | L27: =L25-K25 -> -37341037 | M27: =M25-L25 -> 20049344 | N27: =N25-M25 -> 20164741 | ... S27: =S25-R25 -> 1897684.5
A29: LATAM | F29: 17364868 | G29: 18175556 | H29: 19480554 | I29: 19490793 | J29: 20680984 | K29: 23317497 | L29: 8928798 | M29: 16783965 | N29: =M29+N30 -> 23844996 | O29: =N29+O30 -> 25178500 | P29: =O29+P30 -> 28035495 | Q29: =P29+Q30 -> 28668547 | R29: =Q29+R30 -> 29317136 | S29: =R29+S30 -> 29981643
A30: growth | G30: =G29-F29 -> 810688 | H30: =H29-G29 -> 1304998 | I30: =I29-H29 -> 10239 | J30: =J29-I29 -> 1190191 | K30: =K29-J29 -> 2636513 | L30: =L29-K29 -> -14388699 | M30: =M29-L29 -> 7855167 | N30: =N$27*N32 -> 7061031.5 | O30: =O$27*O32 -> 1333503.2 | P30: =P$27*P32 -> 2856995.1 | Q30: =Q$27*Q32 -> 633052.52 | R30: =R$27*R32 -> 648589.08 | S30: =S$27*S32 -> 664506.93
A31: growth contribution | G31: =G30/G$27 -> 0.23885712 | H31: =H30/H$27 -> 0.46906907 | I31: =I30/I$27 -> 0.011821565 | J31: =J30/J$27 -> 0.3040974 | K31: =K30/K$27 -> 0.47928487 | L31: =L30/L$27 -> 0.38533207 | M31: =M30/M$27 -> 0.39179172
A32: avg growth contribution | M32: =SUMPRODUCT(G31:M31,$G$51:$M$51) -> 0.35016723 | N32: =$M$32 -> 0.35016723 | O32: =$M$32 -> 0.35016723 | P32: =$M$32 -> 0.35016723 | Q32: =$M$32 -> 0.35016723 | R32: =$M$32 -> 0.35016723 | S32: =$M$32 -> 0.35016723
A34: LOW COST CARRIERS | F34: 7530622 | G34: 8146720 | H34: 8669148 | I34: 9856821 | J34: 12409053 | K34: 16853819 | L34: 7435271 | M34: 14396070 | N34: =M34+N35 -> 24963408 | O34: =N34+O35 -> 26959091 | P34: =O34+P35 -> 31234788 | Q34: =P34+Q35 -> 32182197 | R34: =Q34+R35 -> 33152857 | S34: =R34+S35 -> 34147339
A35: growth | G35: =G34-F34 -> 616098 | H35: =H34-G34 -> 522428 | I35: =I34-H34 -> 1187673 | J35: =J34-I34 -> 2552232 | K35: =K34-J34 -> 4444766 | L35: =L34-K34 -> -9418548 | M35: =M34-L34 -> 6960799 | N35: =N$27*N37 -> 10567338 | O35: =O$27*O37 -> 1995682.9 | P35: =P$27*P37 -> 4275697.3 | Q35: =Q$27*Q37 -> 947408.34 | R35: =R$27*R37 -> 970659.9 | S35: =S$27*S37 -> 994482.11
A36: growth contribution | G36: =G35/G$27 -> 0.18152408 | H36: =H35/H$27 -> 0.18778176 | I36: =I35/I$27 -> 1.3712426 | J36: =J35/J$27 -> 0.65210299 | K36: =K35/K$27 -> 0.8080025 | L36: =L35/L$27 -> 0.25223049 | M36: =M35/M$27 -> 0.34718338
A37: avg growth contribution | M37: =SUMPRODUCT(G36:M36,$G$51:$M$51) -> 0.52405028 | N37: =$M$37 -> 0.52405028 | O37: =$M$37 -> 0.52405028 | P37: =$M$37 -> 0.52405028 | Q37: =$M$37 -> 0.52405028 | R37: =$M$37 -> 0.52405028 | S37: =$M$37 -> 0.52405028
A39: AVIANCA COLOMBIA | F39: 13839652 | G39: 15430530 | H39: 15946804 | I39: 14922584 | J39: 15289316 | K39: 15413797 | L39: 4378240 | M39: 9112191 | N39: =M39+N40 -> 10307959 | O39: =N39+O40 -> 10533785 | P39: =O39+P40 -> 11017610 | Q39: =P39+Q40 -> 11124816 | R39: =Q39+R40 -> 11234653 | S39: =R39+S40 -> 11347185
A40: growth | G40: =G39-F39 -> 1590878 | H40: =H39-G39 -> 516274 | I40: =I39-H39 -> -1024220 | J40: =J39-I39 -> 366732 | K40: =K39-J39 -> 124481 | L40: =L39-K39 -> -11035557 | M40: =M39-L39 -> 4733951 | N40: =N$27*N42 -> 1195768.2 | O40: =O$27*O42 -> 225825.48 | P40: =P$27*P42 -> 483825.06 | Q40: =Q$27*Q42 -> 107205.88 | R40: =R$27*R42 -> 109836.96 | S40: =S$27*S42 -> 112532.61
A41: growth contribution | G41: =G40/G$27 -> 0.46872846 | H41: =H40/H$27 -> 0.18556976 | I41: =I40/I$27 -> -1.1825259 | J41: =J40/J$27 -> 0.093701135 | K41: =K40/K$27 -> 0.022629079 | L41: =L40/L$27 -> 0.29553429 | M41: =M40/M$27 -> 0.23611501
A42: avg growth contribution | M42: =SUMPRODUCT(G41:M41,$G$51:$M$51) -> 0.059299955 | N42: =$M$42 -> 0.059299955 | O42: =$M$42 -> 0.059299955 | P42: =$M$42 -> 0.059299955 | Q42: =$M$42 -> 0.059299955 | R42: =$M$42 -> 0.059299955 | S42: =$M$42 -> 0.059299955
A44: OTHERS | F44: 3630621 | G44: 4006986 | H44: 4445388 | I44: 5137825 | J44: 4942518 | K44: 3237689 | L44: 739456 | M44: 1238883 | N44: =M44+N45 -> 2579486.1 | O44: =N44+O45 -> 2832664.2 | P44: =O44+P45 -> 3375091.6 | Q44: =P44+Q45 -> 3495282.5 | R44: =Q44+R45 -> 3618423.3 | S44: =R44+S45 -> 3744586.1
A45: growth | G45: =G44-F44 -> 376365 | H45: =H44-G44 -> 438402 | I45: =I44-H44 -> 692437 | J45: =J44-I44 -> -195307 | K45: =K44-J44 -> -1704829 | L45: =L44-K44 -> -2498233 | M45: =M44-L44 -> 499427 | N45: =N$27*N47 -> 1340603.1 | O45: =O$27*O47 -> 253178.11 | P45: =P$27*P47 -> 542427.34 | Q45: =Q$27*Q47 -> 120190.97 | R45: =R$27*R47 -> 123140.73 | S45: =S$27*S47 -> 126162.88
A46: growth contribution | G46: =G45/G$27 -> 0.11089033 | H46: =H45/H$27 -> 0.15757941 | I46: =I45/I$27 -> 0.79946174 | J46: =J45/J$27 -> -0.049901529 | K46: =K45/K$27 -> -0.30991645 | L46: =L45/L$27 -> 0.06690315 | M46: =M45/M$27 -> 0.024909892
A47: avg growth contribution | M47: =SUMPRODUCT(G46:M46,$G$51:$M$51) -> 0.066482536 | N47: =$M$47 -> 0.066482536 | O47: =$M$47 -> 0.066482536 | P47: =$M$47 -> 0.066482536 | Q47: =$M$47 -> 0.066482536 | R47: =$M$47 -> 0.066482536 | S47: =$M$47 -> 0.066482536
A49: SMOOTHED AVERAGE | F49: constant | G49: 7 | H49: 6 | I49: 5 | J49: 4 | K49: 3 | L49: 2 | M49: 1
D50: weight | F50: 0.8 | G50: =$F$50^G49 -> 0.2097152 | H50: =$F$50^H49 -> 0.262144 | I50: =$F$50^I49 -> 0.32768 | J50: =$F$50^J49 -> 0.4096 | K50: =$F$50^K49 -> 0.512 | L50: =$F$50^L49 -> 0.64 | M50: =$F$50^M49 -> 0.8
D51: normalized weight | F51: =SUM(G50:M50) -> 3.1611392 | G51: =G50/$F$51 -> 0.066341653 | H51: =H50/$F$51 -> 0.082927066 | I51: =I50/$F$51 -> 0.10365883 | J51: =J50/$F$51 -> 0.12957354 | K51: =K50/$F$51 -> 0.16196693 | L51: =L50/$F$51 -> 0.20245866 | M51: =M50/$F$51 -> 0.25307332
A53: MARKET SHARES | F53: 2014 | G53: 2015 | H53: 2016 | I53: 2017 | J53: 2018 | K53: 2019 | L53: 2020 | M53: 2021 | N53: 2022 | O53: 2023 | P53: 2024 | Q53: 2025 | R53: 2026 | S53: 2027
A54: LATAM | F54: =F29/F25 -> 0.40987974 | G54: =G29/G25 -> 0.3971949 | H54: =H29/H25 -> 0.40131425 | I54: =I29/I25 -> 0.3944864 | J54: =J29/J25 -> 0.38785181 | K54: =K29/K25 -> 0.39640235 | L54: =L29/L25 -> 0.41564546 | M54: =M29/M25 -> 0.40412995 | ... S54: =S29/S25 -> 0.37845693
A55: LOW COST CARRIERS | F55: =F34/F25 -> 0.17775254 | G55: =G34/G25 -> 0.17803228 | H55: =H34/H25 -> 0.17859105 | I55: =I34/I25 -> 0.19949839 | J55: =J34/J25 -> 0.23271976 | K55: =K34/K25 -> 0.28651847 | L55: =L34/L25 -> 0.34612012 | M55: =M34/M25 -> 0.34663341 | ... S55: =S34/S25 -> 0.43104032 | U55: output
A56: AVIANCA | F56: =F39/F25 -> 0.32667067 | G56: =G39/G25 -> 0.33720717 | H56: =H39/H25 -> 0.32851631 | I56: =I39/I25 -> 0.30202755 | J56: =J39/J25 -> 0.2867363 | K56: =K39/K25 -> 0.26203779 | L56: =L39/L25 -> 0.20381193 | M56: =M39/M25 -> 0.2194064 | ... S56: =S39/S25 -> 0.14323501
A57: OTHERS | F57: =F44/F25 -> 0.085697052 | G57: =G44/G25 -> 0.087565652 | H57: =H44/H25 -> 0.09157838 | I57: =I44/I25 -> 0.10398767 | J57: =J44/J25 -> 0.092692134 | K57: =K44/K25 -> 0.055041394 | L57: =L44/L25 -> 0.034422497 | M57: =M44/M25 -> 0.029830241 | ... S57: =S44/S25 -> 0.047267742
J59: Average | K59: =AVERAGE(K55:K56) -> 0.27427813 | L59: =AVERAGE(L55:L56) -> 0.27496602 | M59: =AVERAGE(M55:M56) -> 0.2830199 | N59: =AVERAGE(N55:N56) -> 0.28584878 | O59: =AVERAGE(O55:O56) -> 0.28618751 | P59: =AVERAGE(P55:P56) -> 0.28679532 | Q59: =AVERAGE(Q55:Q56) -> 0.28691221 | R59: =AVERAGE(R55:R56) -> 0.2870263 | S59: =AVERAGE(S55:S56) -> 0.28713766

Sheet Int_Mkt_Sh
A1: Market shares with Arba | R1: Historical | S1: #PASSENGERS international | W1: 4/3*(Q1-Q322)
A2: Latin America | B2: 2018 | C2: 2019 | D2: 2020 | E2: 2021 | F2: 2022 | G2: 2023 | H2: 2024 | I2: 2025 | J2: 2026 | K2: 2027 | M2: Global Allainces | R2: Latin America | S2: 2018 | T2: 2019 | U2: 2020 | V2: 2021 | W2: 2022 | X2: 2023 | Y2: =X2+1 -> 2024 | Z2: =Y2+1 -> 2025 | AA2: =Z2+1 -> 2026 | AB2: =AA2+1 -> 2027
A3: LATAM | B3: 0.29948473 | C3: 0.29264907 | D3: 0.27591979 | E3: 0.1800499 | F3: 0.18764017 | G3: =G5*$F$3/$F$5 -> 0.25163509 | H3: =H5*$F$3/$F$5 -> 0.27906149 | I3: =I5*$F$3/$F$5 -> 0.27906149 | J3: =J5*$F$3/$F$5 -> 0.27906149 | K3: =K5*$F$3/$F$5 -> 0.27906149 | M3: Latin America | O3: US | R3: LATAM | S3: 18590118 | T3: 18481071 | U3: 4695683 | V3: 3327268 | W3: =V3*4/3 -> 4436357.3
A4: DELTA Airlines | B4: 0.018596466 | C4: 0.015807106 | D4: 0.01840937 | E4: 0.025165237 | F4: 0.017607531 | G4: =G5*$F$4/$F$5 -> 0.023612603 | H4: =H5*$F$4/$F$5 -> 0.026186206 | I4: =I5*$F$4/$F$5 -> 0.026186206 | J4: =J5*$F$4/$F$5 -> 0.026186206 | K4: =K5*$F$4/$F$5 -> 0.026186206 | M4: LATAM | O4: Delta | R4: DELTA Airlines | S4: 1154351 | T4: 998234 | U4: 313296 | V4: 465046 | W4: =V4*4/3 -> 620061.33
A5: Join venture | B5: =SUM(B3:B4) -> 0.31808119 | C5: =SUM(C3:C4) -> 0.30845618 | D5: =SUM(D3:D4) -> 0.29432916 | E5: =SUM(E3:E4) -> 0.20521514 | F5: =SUM(F3:F4) -> 0.2052477 | G5: =F5+G6 -> 0.2752477 | H5: =G5+H6 -> 0.3052477 | I5: =H5+I6 -> 0.3052477 | J5: =I5+J6 -> 0.3052477 | K5: =J5+K6 -> 0.3052477 | R5: Avianca | S5: 7885816 | T5: 7944587 | U5: 1796995 | V5: 2199551 | W5: =V5*4/3 -> 2932734.7
A6: growth | G6: 0.07 | H6: 0.03 | I6: 0 | J6: 0 | K6: 0 | M6: Gol | N6: JetSmart | O6: American Airlines | R6: Viva | S6: 343866 | T6: 505179 | U6: 198983 | V6: 511668 | W6: =V6*4/3 -> 682224
R7: Gol | S7: 2091365 | T7: 2318077 | U7: 549363 | V7: 41236 | W7: =V7*4/3 -> 54981.333
A8: Abra group | B8: 0.16627092 | C8: 0.17050956 | D8: 0.14956503 | E8: 0.1489448 | F8: 0.28272309 | G8: =F8+G9 -> 0.25272309 | H8: =G8+H9 -> 0.24272309 | I8: =H8+I9 -> 0.25272309 | J8: =I8+J9 -> 0.28272309 | K8: =J8+K9 -> 0.29272309 | M8: Avianca | N8: Copa | O8: United | R8: American Airlines | S8: 2812605 | T8: 2745377 | U8: 853532 | V8: 2226748 | W8: =V8*4/3 -> 2968997.3
A9: growth | G9: -0.03 | H9: -0.01 | I9: 0.01 | J9: 0.03 | K9: 0.01 | R9: United Airlines | S9: 1355338 | T9: 1398277 | U9: 437856 | V9: 605322 | W9: =V9*4/3 -> 807096
R10: Copa Holdings | S10: 2373107 | T10: 2311423 | U10: 732204 | V10: 2309922 | W10: =V10*4/3 -> 3079896
A11: Copa Holdings | B11: 0.038230489 | C11: 0.036601547 | D11: 0.043024534 | E11: 0.12499782 | F11: 0.10086714 | G11: =F11+G12 -> 0.090867135 | H11: =G11+H12 -> 0.085867135 | I11: =H11+I12 -> 0.085867135 | J11: =I11+J12 -> 0.085867135 | K11: =J11+K12 -> 0.085867135 | R11: Jet Smart | S11: 241943 | T11: 572397 | U11: 260111 | V11: 203644 | W11: =V11*4/3 -> 271525.33
A12: growth | G12: -0.01 | H12: -0.005 | I12: 0 | J12: 0 | K12: 0 | R12: Sky Airlines | S12: 1031342 | T12: 1286078 | U12: 476257 | V12: 371324 | W12: =V12*4/3 -> 495098.67
R13: OTHERS | S13: 24193825 | T13: 24590264 | U13: 6704010 | V13: 6217970 | W13: =V13*4/3 -> 8290626.7
A14: Jet Smart | B14: 0.0038976748 | C14: 0.0090639471 | D14: 0.015284203 | E14: 0.011019876 | F14: 0.020714661 | G14: =$F$14 -> 0.020714661 | H14: =$F$14 -> 0.020714661 | I14: =$F$14 -> 0.020714661 | J14: =$F$14 -> 0.020714661 | K14: =$F$14 -> 0.020714661 | N14: Int rev | O14: 219365.59 | P14: =O14*10^4 -> 2.1936559e+09 | R14: TOTAL | S14: 62073676 | T14: 63150964 | U14: 17018290 | V14: 18479699 | W14: =V14*4/3 -> 24639599 | X14: =T14*0.75 -> 47363223 | Y14: =T14 -> 63150964 | Z14: =Y14*(1+$Y$16) -> 67800750 | AA14: =Z14*(1+$Y$16) -> 72792899 | AB14: =$T$14*(1.027)^(AB2-$T$2) -> 78152618
A15: Sky Airlines | B15: 0.016614805 | C15: 0.020365136 | D15: 0.027985009 | E15: 0.020093617 | F15: 0.034865124 | G15: =$F$15 -> 0.034865124 | H15: =$F$15 -> 0.034865124 | I15: =$F$15 -> 0.034865124 | J15: =$F$15 -> 0.034865124 | K15: =$F$15 -> 0.034865124 | O15: =W19 -> 4623378.4 | P15: =O15 -> 4623378.4 | R15: growth | W15: =W14/V14-1 -> 0.33333333 | X15: =X14/W14-1 -> 0.92224003 | Y15: =Y14/X14-1 -> 0.33333333 | Z15: =Z14/Y14-1 -> 0.073629698 | AA15: =AA14/Z14-1 -> 0.073629698 | AB15: =AB14/AA14-1 -> 0.073629698
W16: 1 | Y16: =(AB14/Y14)^(1/3)-1 -> 0.073629698
A17: American Airlines | B17: 0.045310753 | C17: 0.04347324 | D17: 0.050153805 | E17: 0.12049698 | F17: 0.072666224 | G17: =F17+G18 -> 0.062666224 | H17: =G17+H18 -> 0.057666224 | I17: =H17+I18 -> 0.052666224 | J17: =I17+J18 -> 0.052666224 | K17: =J17+K18 -> 0.055166224 | P17: =P14/P15 -> 474.47035 | W17: 0.18863486
A18: growth | G18: -0.01 | H18: -0.005 | I18: -0.005 | J18: 0 | K18: 0.0025 | R18: LATAM | S18: 0.29948473 | T18: 0.29264907 | U18: 0.27591979 | V18: 0.1800499 | W18: =F3 -> 0.18764017 | X18: =G3 -> 0.25163509 | Y18: =H3 -> 0.27906149 | Z18: =I3 -> 0.27906149 | AA18: =J3 -> 0.27906149 | AB18: =K3 -> 0.27906149
R19: Number Passengers | S19: =S14*S18 -> 18590118 | T19: =T14*T18 -> 18481071 | U19: =U14*U18 -> 4695683 | V19: =V14*V18 -> 3327268 | W19: =W14*W18 -> 4623378.4 | X19: =X14*X18 -> 11918249 | Y19: =Y14*Y18 -> 17623002 | Z19: =Z14*Z18 -> 18920579 | ... AB19: =AB14*AB18 -> 21809386
A20: United Airlines | B20: 0.021834344 | C20: 0.022141816 | D20: 0.025728554 | E20: 0.032756053 | F20: 0.015392781 | G20: =F20+G21 -> 0.012892781 | H20: =G20+H21 -> 0.012892781 | I20: =H20+I21 -> 0.012892781 | J20: =I20+J21 -> 0.010392781 | K20: =J20+K21 -> 0.012892781
A21: growth | G21: -0.0025 | H21: 0 | I21: 0 | J21: -0.0025 | K21: 0.0025
A23: OTHERS | B23: 0.38975982 | C23: 0.38938858 | D23: 0.39392971 | E23: 0.33647572 | F23: 0.26752329 | G23: =F23+G24 -> 0.25002329 | H23: =G23+H24 -> 0.24002329 | I23: =H23+I24 -> 0.23502329 | J23: =I23+J24 -> 0.20752329 | K23: =J23+K24 -> 0.19252329
G24: =-SUM(G21,G18,G12,G9,G6) -> -0.0175 | H24: =-SUM(H21,H18,H12,H9,H6) -> -0.01 | I24: =-SUM(I21,I18,I12,I9,I6) -> -0.005 | J24: =-SUM(J21,J18,J12,J9,J6) -> -0.0275 | K24: =-SUM(K21,K18,K12,K9,K6) -> -0.015
A26: TOTAL | B26: =SUM(B5,B8,B11,B14,B15,B17,B20,B23) -> 1 | C26: =SUM(C5,C8,C11,C14,C15,C17,C20,C23) -> 1 | D26: =SUM(D5,D8,D11,D14,D15,D17,D20,D23) -> 1 | E26: =SUM(E5,E8,E11,E14,E15,E17,E20,E23) -> 1 | F26: =SUM(F5,F8,F11,F14,F15,F17,F20,F23) -> 1 | G26: =SUM(G5,G8,G11,G14,G15,G17,G20,G23) -> 1 | H26: =SUM(H5,H8,H11,H14,H15,H17,H20,H23) -> 1 | I26: =SUM(I5,I8,I11,I14,I15,I17,I20,I23) -> 1 | ... K26: =SUM(K5,K8,K11,K14,K15,K17,K20,K23) -> 1
A29: Average | C29: =AVERAGE(C8,C11,C14:C15,C17,C20) -> 0.050359208 | D29: =AVERAGE(D8,D11,D14:D15,D17,D20) -> 0.051956855 | E29: =AVERAGE(E8,E11,E14:E15,E17,E20) -> 0.076384857 | F29: =AVERAGE(F8,F11,F14:F15,F17,F20) -> 0.087871502 | G29: =AVERAGE(G8,G11,G14:G15,G17,G20) -> 0.079121502 | H29: =AVERAGE(H8,H11,H14:H15,H17,H20) -> 0.075788169 | I29: =AVERAGE(I8,I11,I14:I15,I17,I20) -> 0.076621502 | J29: =AVERAGE(J8,J11,J14:J15,J17,J20) -> 0.081204835 | K29: =AVERAGE(K8,K11,K14:K15,K17,K20) -> 0.083704835

Sheet A1-jet Fuel
A1: Workbook Contents
A2: U.S. Gulf Coast Kerosene-Type Jet Fuel Spot Price FOB (Dollars per Gallon)
A4: Click worksheet name or tab at bottom for data
A5: Worksheet Name | B5: Description | C5: # Of Series | D5: Frequency | E5: Latest Data for
A6: Data 1 | B6: U.S. Gulf Coast Kerosene-Type Jet Fuel Spot Price FOB (Dollars per Gallon) | C6: 1 | D6: Monthly | E6: 10/2022
A8: Release Date: | B8: 11/9/2022
A9: Next Release Date: | B9: 11/16/2022
A10: Excel File Name: | B10: eer_epjk_pf4_rgc_dpgm.xls
A11: Available from Web Page: | B11: https://www.eia.gov/dnav/pet/hist/LeafHandler.ashx?n=PET&s=EER_EPJK_PF4_RGC_DPG&f=M
A12: Source:
A13: For Help, Contact: | B13: infoctr@eia.doe.gov
B14: (202) 586-8800 | E14: 11/9/2022 9:48:10 AM
A16: Data 1: U.S. Gulf Coast Kerosene-Type Jet Fuel Spot Price FOB (Dollars per Gallon)
A17: Sourcekey | B17: EER_EPJK_PF4_RGC_DPG
A18: Date | B18: U.S. Gulf Coast Kerosene-Type Jet Fuel Spot Price FOB (Dollars per Gallon) | C18: Date | D18: Quarterly Mean
A19: 32978 | B19: 0.54 | C19: q4-1999 | D19: =C135 -> 0.65233333
A20: 33008 | B20: 0.515 | C20: q1-2000 | D20: 0.77733333
A21: 33039 | B21: 0.494 | C21: q2-2000 | D21: 0.75533333
A22: 33069 | B22: 0.535 | C22: q3-2000 | D22: 0.90433333
A23: 33100 | B23: 0.791 | C23: q4-2000 | D23: 0.95766667
A24: 33131 | B24: 1.012 | C24: q1-2001 | D24: 0.811
A25: 33161 | B25: 1.196 | C25: q2-2001 | D25: 0.786
A26: 33192 | B26: 0.971 | C26: q3-2001 | D26: 0.73766667
A27: 33222 | B27: 0.803 | C27: q4-2001 | D27: 0.56
A28: 33253 | B28: 0.741 | C28: q1-2002 | D28: 0.57133333
A29: 33284 | B29: 0.637 | C29: q2-2002 | D29: 0.66266667
A30: 33312 | B30: 0.558 | C30: q3-2002 | D30: 0.73766667
A31: 33343 | B31: 0.552 | C31: q4-2002 | D31: 0.76966667
... A110: 35749 | B110: 0.549 | C110: q3-2022 | D110: 3.3596667
A111: 35779 | B111: 0.496
A112: 35810 | B112: 0.476
A113: 35841 | B113: 0.449
A114: 35869 | B114: 0.413
A115: 35900 | B115: 0.426
A116: 35930 | B116: 0.416
A117: 35961 | B117: 0.389
A118: 35991 | B118: 0.386
A119: 36022 | B119: 0.372
A120: 36053 | B120: 0.42
A121: 36083 | B121: 0.42
A122: 36114 | B122: 0.371
... A134: 36479 | B134: 0.661
A135: 36509 | B135: 0.701 | C135: =AVERAGE(B133:B135) -> 0.65233333
A136: 36540 | B136: 0.781
A137: 36571 | B137: 0.78
A138: 36600 | B138: 0.771 | C138: =AVERAGE(B136:B138) -> 0.77733333
A139: 36631 | B139: 0.719
A140: 36661 | B140: 0.762
A141: 36692 | B141: 0.785 | C141: =AVERAGE(B139:B141) -> 0.75533333
A142: 36722 | B142: 0.796
A143: 36753 | B143: 0.9
A144: 36784 | B144: 1.017 | C144: =AVERAGE(B142:B144) -> 0.90433333
A145: 36814 | B145: 0.982
A146: 36845 | B146: 1.028
A147: 36875 | B147: 0.863 | C147: =AVERAGE(B145:B147) -> 0.95766667
A148: 36906 | B148: 0.87
A149: 36937 | B149: 0.815
A150: 36965 | B150: 0.748 | C150: =AVERAGE(B148:B150) -> 0.811
A151: 36996 | B151: 0.77
A152: 37026 | B152: 0.821
A153: 37057 | B153: 0.767 | C153: =AVERAGE(B151:B153) -> 0.786
A154: 37087 | B154: 0.711
A155: 37118 | B155: 0.764
A156: 37149 | B156: 0.738 | C156: =AVERAGE(B154:B156) -> 0.73766667
A157: 37179 | B157: 0.622
A158: 37210 | B158: 0.543
A159: 37240 | B159: 0.515 | C159: =AVERAGE(B157:B159) -> 0.56
A160: 37271 | B160: 0.533
A161: 37302 | B161: 0.551
A162: 37330 | B162: 0.63 | C162: =AVERAGE(B160:B162) -> 0.57133333
A163: 37361 | B163: 0.669
A164: 37391 | B164: 0.666
A165: 37422 | B165: 0.653 | C165: =AVERAGE(B163:B165) -> 0.66266667
A166: 37452 | B166: 0.691
A167: 37483 | B167: 0.722
A168: 37514 | B168: 0.8 | C168: =AVERAGE(B166:B168) -> 0.73766667
A169: 37544 | B169: 0.79
A170: 37575 | B170: 0.708
A171: 37605 | B171: 0.811 | C171: =AVERAGE(B169:B171) -> 0.76966667
A172: 37636 | B172: 0.887
A173: 37667 | B173: 1.055
A174: 37695 | B174: 0.893 | C174: =AVERAGE(B172:B174) -> 0.945
A175: 37726 | B175: 0.743
A176: 37756 | B176: 0.714
A177: 37787 | B177: 0.748 | C177: =AVERAGE(B175:B177) -> 0.735
A178: 37817 | B178: 0.78
A179: 37848 | B179: 0.823
A180: 37879 | B180: 0.738 | C180: =AVERAGE(B178:B180) -> 0.78033333
A181: 37909 | B181: 0.82
A182: 37940 | B182: 0.831
A183: 37970 | B183: 0.876 | C183: =AVERAGE(B181:B183) -> 0.84233333
A184: 38001 | B184: 0.998
A185: 38032 | B185: 0.933
A186: 38061 | B186: 0.947 | C186: =AVERAGE(B184:B186) -> 0.95933333
A187: 38092 | B187: 0.973
A188: 38122 | B188: 1.092
A189: 38153 | B189: 1.032 | C189: =AVERAGE(B187:B189) -> 1.0323333
A190: 38183 | B190: 1.145
A191: 38214 | B191: 1.227
A192: 38245 | B192: 1.362 | C192: =AVERAGE(B190:B192) -> 1.2446667
...

Sheet Futures_provvisorio
A1: $/BRL | B1: Ultimo | C1: Variazione | D1: Massimo | E1: Minimo
A2: Cash | B2: 0.18745 | C2: -1e-05 | D2: 0.18746 | E2: 0.18745
A3: Dec 22 | B3: 0.1867 | C3: -0.00045 | D3: 0.18865 | E3: 0.18615
A4: Jan 23 | B4: 0.18525 | C4: -0.0008 | D4: 0.18725 | E4: 0.18525
A5: Feb 23 | B5: 0.185 | C5: -5e-05 | D5: 0.185 | E5: 0.18485
A6: Mar 23 | B6: 0.1839 | C6: -0.00015 | D6: 0.1839 | E6: 0.1839
A7: Apr 23 | B7: 0.18295 | C7: -0.0001 | D7: 0.18295 | E7: 0.18295
A8: May 23 | B8: 0.18205 | C8: -0.00015 | D8: 0.18205 | E8: 0.18205
A9: Jun 23 | B9: 0.181 | C9: -0.0001 | D9: 0.181 | E9: 0.181
A10: Jul 23 | B10: 0.17995 | C10: -0.00015 | D10: 0.17995 | E10: 0.17995
A11: Aug 23 | B11: 0.1789 | C11: -0.0001 | D11: 0.1789 | E11: 0.1789
A12: Sep 23 | B12: 0.17785 | C12: -0.00015 | D12: 0.17785 | E12: 0.17785
A13: Oct 23 | B13: 0.1769 | C13: -0.0002 | D13: 0.1769 | E13: 0.1769
... A19: Apr 24 | B19: 0.1713 | C19: -0.00025 | D19: 0.1713 | E19: 0.1713
A20: May 24 | B20: 0.1703 | C20: -0.0003 | D20: 0.1703 | E20: 0.1703 | H20: =
A21: Jun 24 | B21: 0.1694 | C21: -0.00025 | D21: 0.1694 | E21: 0.1694
A22: Jul 24 | B22: 0.1686 | C22: -0.00025 | D22: 0.1686 | E22: 0.1686
A23: Aug 24 | B23: 0.16765 | C23: -0.00025 | D23: 0.16765 | E23: 0.16765
A24: Sep 24 | B24: 0.16675 | C24: -0.0003 | D24: 0.16675 | E24: 0.16675
A25: Oct 24 | B25: 0.1659 | C25: -0.0003 | D25: 0.1659 | E25: 0.1659
A26: Nov 24 | B26: 0.165 | C26: -0.0003 | D26: 0.165 | E26: 0.165
A27: Dec 24 | B27: 0.1642 | C27: -0.0003 | D27: 0.1642 | E27: 0.1642
A28: Jan 25 | B28: 0.16335 | C28: -0.0003 | D28: 0.16335 | E28: 0.16335
A29: Feb 25 | B29: 0.1625 | C29: -0.0003 | D29: 0.1625 | E29: 0.1625
A30: Mar 25 | B30: 0.16175 | C30: -0.0003 | D30: 0.16175 | E30: 0.16175
A31: Apr 25 | B31: 0.1609 | C31: -0.00035 | D31: 0.1609 | E31: 0.1609
A32: May 25 | B32: 0.1601 | C32: -0.00035 | D32: 0.1601 | E32: 0.1601
... A62: Nov 27 | B62: 0.1393 | C62: -0.0004 | D62: 0.1393 | E62: 0.1393

Sheet Drivers Cargo
A1: Forecast Drivers
A8: Income statement items | C8: Computation strategy | E8: 2019 | F8: 2020 | G8: 2021 | H8: 2022E | I8: 2023F | J8: 2024F | K8: 2025F | L8: 2026F | M8: 2027F
A9: Cargo Revenues | B9: Cargo ATK and RTK | C9: ATK | E9: =+Cargo!D13 -> 6356.6697 | F9: =+Cargo!E13 -> 4708.2548 | G9: =+Cargo!F13 -> 4788.0802 | H9: =+Cargo!G13 -> 6583.6103 | I9: =+Cargo!H13 -> 7930.2579 | J9: =+Cargo!I13 -> 8379.1404 | K9: =+Cargo!J13 -> 8659.8416 | L9: =+Cargo!K13 -> 8502.449 | M9: =+Cargo!L13 -> 8787.2811
C10: Growth Rates | F10: =F9/E9-1 -> -0.25932053 | G10: =G9/F9-1 -> 0.016954369 | H10: =H9/G9-1 -> 0.375 | I10: =I9/H9-1 -> 0.20454545 | J10: =J9/I9-1 -> 0.056603774 | K10: =K9/J9-1 -> 0.0335 | L10: =L9/K9-1 -> -0.018175 | M10: =M9/L9-1 -> 0.0335
C11: Load factor 2012-2015 | D11: =+AVERAGE(Cargo!$D$28:$S$28) -> 0.59150095
C12: Load factor 2012-2019 | D12: =+AVERAGE(Cargo!$D$28:$AI$28) -> 0.5647873
C13: Load factor % | E13: =+Cargo!D16 -> 0.5546902 | F13: =+Cargo!E16 -> 0.65369859 | G13: =+Cargo!F16 -> 0.63383686 | H13: =+$D$11 -> 0.59150095 | I13: =+$D$11 -> 0.59150095 | J13: 0.5647873 | K13: =+$D$12 -> 0.5647873 | L13: =+$D$12 -> 0.5647873 | M13: =+$D$12 -> 0.5647873
C14: RTK | E14: =+E9*E13 -> 3525.9824 | F14: =+F9*F13 -> 3077.7795 | G14: =+G9*G13 -> 3034.8618 | H14: =+H9*H13 -> 3894.2118 | I14: =+I9*I13 -> 4690.7551 | J14: =+J9*J13 -> 4732.4321 | K14: =+K9*K13 -> 4890.9685 | L14: =+L9*L13 -> 4802.0752 | M14: =+M9*M13 -> 4962.9447
C15: Growth Rates | F15: =F14/E14-1 -> -0.12711433 | G15: =G14/F14-1 -> -0.013944381 | H15: =H14/G14-1 -> 0.28315952 | I15: =I14/H14-1 -> 0.20454545 | J15: =J14/I14-1 -> 0.0088849202 | K15: =K14/J14-1 -> 0.0335 | L15: =L14/K14-1 -> -0.018175 | M15: =M14/L14-1 -> 0.0335
C17: RTK CAGR 2020-2027, 7 years | D17: =+POWER(M14/F14,1/7)-1 -> 0.070639183
C18: Recovery Rate market to pre pandemic Levels (2019) vs 2022 | D18: =H9/E9 -> 1.0357012
B21: Yield per RPk and Revenues | C21: Yield Per RPK 2012-2015 (US$ cents) | D21: =+AVERAGE(Cargo!$D$43:$S$43) -> 42.39396
C22: RATK (USD Cents) | E22: 16.745152 | F22: 25.697271 | G22: 32.2 | H22: =+Cargo!C87 -> 28.137406 | I22: =+Cargo!D87 -> 25.948911 | J22: =+Cargo!E87 -> 21.409471 | K22: =+Cargo!F87 -> 21.409471 | L22: =+Cargo!G87 -> 20.161771 | M22: =+Cargo!H87 -> 20.161771
C23: Yield Per RPK (USD Cents) | E23: 30.188296 | F23: 39.310581 | G23: 50.797522 | H23: =+H22*H9/H14 -> 47.569503 | I23: =+I22*I9/I14 -> 43.869602 | J23: =+J22*J9/J14 -> 37.907139 | K23: =+K22*K9/K14 -> 37.907139 | L23: =+L22*L9/L14 -> 35.697989 | M23: =+M22*M9/M14 -> 35.697989
C24: Revenues mln USD | E24: =+E9*E22/100 -> 1064.434 | F24: =+F9*F22/100 -> 1209.893 | G24: =+G9*G22/100 -> 1541.7618 | H24: =+H9*H22/100 -> 1852.4572 | I24: =+I9*I22/100 -> 2057.8156 | J24: =+J9*J22/100 -> 1793.9296 | K24: =+K9*K22/100 -> 1854.0263 | L24: =+L9*L22/100 -> 1714.2443 | M24: =+M9*M22/100 -> 1771.6714
C25: Growth Rates | F25: =F24/E24-1 -> 0.13665385 | G25: =G24/F24-1 -> 0.27429602 | H25: =H24/G24-1 -> 0.20151968 | I25: =I24/H24-1 -> 0.11085729 | J25: =J24/I24-1 -> -0.12823596 | K25: =K24/J24-1 -> 0.0335 | L25: =L24/K24-1 -> -0.075393752 | M25: =M24/L24-1 -> 0.0335
C26: CAGR 2022-2027, 5 years | D26: =(M24/G24)^(1/6)-1 -> 0.023436689
C27: CAGR 2021-2027 | D27: =(M24/F24)^(1/7)-1 -> 0.055996107
C30: Recovery Rate market to pre pandemic Levels (2019) vs 2022 | D30: =+H24/E24 -> 1.7403213

Sheet Cargo_Graph
B3: Correlation between "Revenues per ATK" and "ATK from dedicated cargo planes %"
B5: The graphs show that the air transport using cargo dedicated airplanes is more lucrative, intuitevely because the service provided is better. However, reasonably, this involves higher cost.
B23: Correlation between "Total ATK" and "ATK from dedicated cargo planes %"
B25: The graph shows that more cargo dedicated airplanes LATAM has, more its cargo business expands. LATAM's strategy up until 2018 was to lower the number of cargo planes, which resulted in a decrease in its business volume. Beginning in 2019, the firm reevaluated this division and adopted a new strategy.
B44: Relation between cargo business and Latin America export
B46: The recent devaluation of Latin American currencies as a result of the dollar's increasing strength led to a sharp increase in exports, which also benefited LATAM.
K49: Select Country | M49: Chile | N49: =+M49&" Export" -> Chile Export

Sheet Cargo
B2: NOTE 1.1 | C2: (Report 2021) LATAM announced a three-year growth plan for the cargo fleet that includes the conversion by Boeing of up to eight Boeing 767-300ER, following which the group would increase its combined cargo capacity by nearly 80%.
B4: NOTE 1.2 | C4: (Report 2022 Q3) Four freighters have already been converted, with the remaining six conversions to take place in 2023 and 2024. Additionally, the company has signed contracts for the sale of two freighters in 2024, and thus expects to reach a total freighter fleet of up to 20 freighters in 2024.
B6: NOTE 1.2 | C6: Boeing estimates that the air cargo traffic growth 2020-2039 from Latin America to Europe is 4.1% per year, to North America is 2.6%. Since the relative volumes are similar, the average growth of Latin America market will be 3.35%.
A9: ATK Forecast | C9: Unit | D9: 2019 | E9: 2020 | F9: 2021 | G9: 2022 | H9: 2023 | I9: 2024 | J9: 2025 | K9: 2026 | L9: 2027
B12: Cargo Boeing 767-300F | D12: 11 | E12: 12 | F12: 12 | G12: 16 | H12: 19 | I12: =22-2 -> 20 | J12: 20 | K12: 19 | L12: 19
B13: ATKs | C13: millions | D13: 6356.6697 | E13: 4708.2548 | F13: 4788.0802 | G13: =+$F$13*(1+G14) -> 6583.6103 | H13: =+$F$13*(1+H14) -> 7930.2579 | I13: =+$F$13*(1+I14) -> 8379.1404 | J13: =+I13*(1+$J15) -> 8659.8416 | K13: =+J13*(1+$J15)*(K12/20) -> 8502.449 | L13: =+K13*(1+$J15) -> 8787.2811
B14: Growth (Base year = 2021) | G14: =0.75*(4/8) -> 0.375 | H14: =0.75*(7/8) -> 0.65625 | I14: =0.75*(8/8) -> 0.75
B15: Growth | E15: =+E13/D13-1 -> -0.25932053 | F15: =+F13/E13-1 -> 0.016954369 | G15: =+G13/F13-1 -> 0.375 | H15: =+H13/G13-1 -> 0.20454545 | I15: =+I13/H13-1 -> 0.056603774 | J15: 0.0335 | K15: 0.0335 | L15: 0.0335
B16: Load factor | D16: 0.5546902 | E16: 0.65369859 | F16: 0.63383686 | G16: =+AVERAGE($D$28:$S$28) -> 0.59150095 | H16: =+AVERAGE($D$28:$S$28) -> 0.59150095 | I16: =+AVERAGE(H16,J16) -> 0.57814412 | J16: =+AVERAGE($D$28:$AI$28) -> 0.5647873 | K16: =+AVERAGE($D$28:$AI$28) -> 0.5647873 | L16: =+AVERAGE($D$28:$AI$28) -> 0.5647873
B17: RPK | C17: millions | D17: =+D13*D16 -> 3525.9824 | E17: =+E13*E16 -> 3077.7795 | F17: =+F13*F16 -> 3034.8618 | G17: =+G13*G16 -> 3894.2118 | H17: =+H13*H16 -> 4690.7551 | I17: =+I13*I16 -> 4844.3508 | J17: =+J13*J16 -> 4890.9685 | K17: =+K13*K16 -> 4802.0752 | L17: =+L13*L16 -> 4962.9447
B18: Growth | E18: =+E17/D17-1 -> -0.12711433 | F18: =+F17/E17-1 -> -0.013944381 | G18: =+G17/F17-1 -> 0.28315952 | H18: =+H17/G17-1 -> 0.20454545 | I18: =+I17/H17-1 -> 0.032744347 | J18: =+J17/I17-1 -> 0.0096231155 | K18: =+K17/J17-1 -> -0.018175 | L18: =+L17/K17-1 -> 0.0335
B22: NOTE 2. | C22: (Report 2017) The mix of cargo transported in cargo planes and the bellies of the passenger fleet was 29% and 71%, respectively.
C23: This analysis aims to reproduce the information reported above from 2012 to 2022, using information on its fleet.
A25: Cargo | C25: Unit | D25: 1Q12 | E25: 2Q12 | F25: 3Q12 | G25: 4Q12 | H25: 1Q13 | I25: 2Q13 | J25: 3Q13 | K25: 4Q13 | L25: 1Q14 | M25: 2Q14 | N25: 3Q14 | O25: 4Q14 | P25: 1Q15 | Q25: 2Q15 | R25: 3Q15 | S25: 4Q15 | T25: 1Q16 | U25: 2Q16 | V25: 3Q16 | W25: 4Q16 | X25: 1Q17 | Y25: 2Q17 | Z25: 3Q17 | AA25: 4Q17 | AB25: 1Q18 | AC25: 2Q18 | AD25: 3Q18 | AE25: 4Q18 | AF25: 1Q19 | AG25: 2Q19 | AH25: 3Q19 | AI25: 4Q19 | AJ25: 1Q20 | AK25: 2Q20 | AL25: 3Q20 | AM25: 4Q20 | AN25: 1Q21 | AO25: 2Q21 | AP25: 3Q21 | AQ25: 4Q21 | AR25: 1Q22 | AS25: 2Q22
B27: ATKs | C27: millions | D27: 1885.0286 | E27: 1847.7965 | F27: 1862.7511 | G27: 2050.3688 | H27: 1957.0936 | I27: 1906.9763 | J27: 1864.1815 | K27: 1923.6294 | L27: 1827.5361 | M27: 1763.0739 | N27: 1774.0056 | O27: 1855.097 | P27: 1767.4547 | Q27: 1739.8601 | R27: 1765.234 | S27: 1810.2102 | T27: 1707.0333 | U27: 1633.1691 | V27: 1661.1818 | W27: 1702.748 | X27: 1532.5904 | Y27: 1482.7806 | Z27: 1573.3238 | AA27: 1641.609 | AB27: 1609.8892 | AC27: 1593.6706 | AD27: 1634.9936 | AE27: 1659.0932 | AF27: 1603.6407 | AG27: 1521.3048 | AH27: 1591.7918 | AI27: 1639.9323 | AJ27: 1586.7718 | AK27: 918.77166 | AL27: 957.92254 | AM27: 1244.7888 | AN27: 1119.2926 | AO27: 1095.8456 | AP27: 1178.4403 | AQ27: 1394.5017 | AR27: 1429.8556 | AS27: 1459.2791
B28: Load Factor (based on ATKs) | C28: % | D28: 0.57753949 | E28: 0.5934421 | F28: 0.58855907 | G28: 0.63214425 | H28: 0.58275501 | I28: 0.58607203 | J28: 0.57306383 | K28: 0.60446853 | L28: 0.56124785 | M28: 0.58663711 | N28: 0.56825887 | O28: 0.61876036 | P28: 0.58665311 | Q28: 0.5954521 | R28: 0.5859522 | S28: 0.62300932 | T28: 0.54851403 | U28: 0.52801945 | V28: 0.51433726 | W28: 0.55293064 | X28: 0.51230606 | Y28: 0.48798337 | Z28: 0.49633256 | AA28: 0.56984228 | AB28: 0.5288005 | AC28: 0.5386816 | AD28: 0.54214753 | AE28: 0.58428981 | AF28: 0.54778302 | AG28: 0.54904841 | AH28: 0.53504727 | AI28: 0.5731145 | AJ28: 0.56045422 | AK28: 0.55839162 | AL28: 0.53598866 | AM28: 0.56377262 | AN28: 0.52455144 | AO28: 0.77953875 | AP28: 0.7276005 | AQ28: 0.66857371 | AR28: 0.65349747 | AS28: 0.68016858 | AT28: 0.61563102 | AU28: 0.59703241 | AV28: 0.58436372 | AW28: 0.58052925
B30: ASKs | C30: millions | D30: 16183.02 | E30: 15586.19 | F30: 16298.299 | G30: 17560.278 | H30: 18038.577 | I30: 16152.189 | J30: 16552.831 | K30: 16418.734 | L30: 16666.934 | M30: 15927.898 | N30: 16502.394 | O30: 16432.868 | P30: 17089.335 | Q30: 16390.962 | R30: 17912.668 | S30: 18357.512 | T30: 18566.076 | U30: 17550.212 | V30: 18799.254 | W30: 18626.359 | X30: 19402.58 | Y30: 18094.492 | Z30: 19537.377 | AA30: 19331.648 | AB30: 20063.942 | AC30: 19054.268 | AD30: 21183.51 | AE30: 20757.982 | AF30: 21694.873 | AG30: 19683 | AH30: 20321 | AI30: 19633.694 | AJ30: 17985.836 | AK30: 928.45213 | AL30: 1392.6153 | AM30: 3576.4183 | AN30: 4089.7377 | AO30: 2796.4821 | AP30: 5462.6192 | AQ30: 8112.207 | AR30: 10455.611 | AS30: 10681.478
B31: Average seats (estimate) | D31: =+HLOOKUP(2000+RIGHT(D25,2),Fleet!$C$1:$N$12,11,TRUE) -> 234.35821 | E31: =+HLOOKUP(2000+RIGHT(E25,2),Fleet!$C$1:$N$12,11,TRUE) -> 234.35821 | F31: =+HLOOKUP(2000+RIGHT(F25,2),Fleet!$C$1:$N$12,11,TRUE) -> 234.35821 | G31: =+HLOOKUP(2000+RIGHT(G25,2),Fleet!$C$1:$N$12,11,TRUE) -> 234.35821 | H31: =+HLOOKUP(2000+RIGHT(H25,2),Fleet!$C$1:$N$12,11,TRUE) -> 241.42029 | I31: =+HLOOKUP(2000+RIGHT(I25,2),Fleet!$C$1:$N$12,11,TRUE) -> 241.42029 | J31: =+HLOOKUP(2000+RIGHT(J25,2),Fleet!$C$1:$N$12,11,TRUE) -> 241.42029 | K31: =+HLOOKUP(2000+RIGHT(K25,2),Fleet!$C$1:$N$12,11,TRUE) -> 241.42029 | ... AS31: =+HLOOKUP(2000+RIGHT(AS25,2),Fleet!$C$1:$N$12,11,TRUE) -> 287.22642
B33: Km. traveled (estimate) | C33: millions | D33: =+D30/D31 -> 69.052498 | E33: =+E30/E31 -> 66.505842 | F33: =+F30/F31 -> 69.54439 | G33: =+G30/G31 -> 74.929222 | H33: =+H30/H31 -> 74.718561 | I33: =+I30/I31 -> 66.904852 | J33: =+J30/J31 -> 68.564375 | K33: =+K30/K31 -> 68.008924 | ... AS33: =+AS30/AS31 -> 37.188357
B34: Avg. tons capacity of bellies | D34: =+HLOOKUP(2000+RIGHT(D25,2),Fleet!$C$1:$N$14,14,TRUE) -> 13.76676 | E34: =+HLOOKUP(2000+RIGHT(E25,2),Fleet!$C$1:$N$14,14,TRUE) -> 13.76676 | F34: =+HLOOKUP(2000+RIGHT(F25,2),Fleet!$C$1:$N$14,14,TRUE) -> 13.76676 | G34: =+HLOOKUP(2000+RIGHT(G25,2),Fleet!$C$1:$N$14,14,TRUE) -> 13.76676 | H34: =+HLOOKUP(2000+RIGHT(H25,2),Fleet!$C$1:$N$14,14,TRUE) -> 14.176096 | I34: =+HLOOKUP(2000+RIGHT(I25,2),Fleet!$C$1:$N$14,14,TRUE) -> 14.176096 | J34: =+HLOOKUP(2000+RIGHT(J25,2),Fleet!$C$1:$N$14,14,TRUE) -> 14.176096 | K34: =+HLOOKUP(2000+RIGHT(K25,2),Fleet!$C$1:$N$14,14,TRUE) -> 14.176096 | ... AS34: =+HLOOKUP(2000+RIGHT(AS25,2),Fleet!$C$1:$N$14,14,TRUE) -> 16.067322
B36: ATK from bellies of the passenger fleet | C36: millions | D36: =+D33*D34 -> 950.62921 | E36: =+E33*E34 -> 915.56999 | F36: =+F33*F34 -> 957.40096 | G36: =+G33*G34 -> 1031.5327 | H36: =+H33*H34 -> 1059.2175 | I36: =+I33*I34 -> 948.44957 | J36: =+J33*J34 -> 971.97512 | K36: =+K33*K34 -> 964.10101 | ... AS36: =+AS33*AS34 -> 597.51729
B37: ATK from dedicated cargo planes | C37: millions | D37: =+D27-D36 -> 934.39935 | E37: =+E27-E36 -> 932.22652 | F37: =+F27-F36 -> 905.35018 | G37: =+G27-G36 -> 1018.8362 | H37: =+H27-H36 -> 897.87615 | I37: =+I27-I36 -> 958.52678 | J37: =+J27-J36 -> 892.20634 | K37: =+K27-K36 -> 959.52837 | ... AS37: =+AS27-AS36 -> 861.76183
B39: ATK from bellies of the passenger fleet | C39: % | D39: =+D36/D27 -> 0.50430494 | E39: =+E36/E27 -> 0.49549287 | F39: =+F36/F27 -> 0.51397148 | G39: =+G36/G27 -> 0.50309614 | H39: =+H36/H27 -> 0.54121962 | I39: =+I36/I27 -> 0.4973578 | J39: =+J36/J27 -> 0.52139512 | K39: =+K36/K27 -> 0.50118854 | ... AS39: =+AS36/AS27 -> 0.40946059
B40: ATK from dedicated cargo planes | C40: % | D40: =1-D39 -> 0.49569506 | E40: =1-E39 -> 0.50450713 | F40: =1-F39 -> 0.48602852 | G40: =1-G39 -> 0.49690386 | H40: =1-H39 -> 0.45878038 | I40: =1-I39 -> 0.5026422 | J40: =1-J39 -> 0.47860488 | K40: =1-K39 -> 0.49881146 | ... AS40: =1-AS39 -> 0.59053941
B42: Revenues per ATK | C42: US$ cents | D42: 25.230705 | E42: 25.881854 | F42: 24.0512 | G42: 26.233621 | H42: 23.524424 | I42: 25.513007 | J42: 23.4077 | K42: 24.937028 | L42: 23.020558 | M42: 24.101883 | N42: 23.138934 | O42: 24.648252 | P42: 19.820706 | Q42: 19.222523 | R42: 17.549005 | S42: 18.499675 | T42: 16.166468 | U42: 15.920581 | V42: 15.920581 | W42: 18.150307 | X42: 16.556674 | Y42: 17.299323 | Z42: 17.297965 | AA42: 20.529858 | AB42: 18.375178 | AC42: 18.805831 | AD42: 17.057131 | AE42: 18.809191 | AF42: 16.431112 | AG42: 17.699346 | AH42: 15.811804 | AI42: 17.073021 | AJ42: 15.905816 | AK42: 34.690556 | AL42: 29.642898 | AM42: 28.504514 | AN42: 30.842814 | AO42: 33.778686 | AP42: 30.670794 | AQ42: 33.331906 | AR42: 30.121786 | AS42: 31.716264
B43: Yield based on RTKs | C43: US$ cents | D43: 42.135922 | E43: 47.297497 | F43: 46.25011 | G43: 44.12562 | H43: 43.295561 | I43: 44.161559 | J43: 41.969496 | K43: 43.399483 | L43: 41.914502 | M43: 43.490271 | N43: 41.191965 | O43: 40.301593 | P43: 39.240493 | Q43: 40.47661 | R43: 39.489458 | S43: 39.563216 | T43: 36.135276 | U43: 36.404952 | V43: 34.119665 | W43: 33.457496 | X43: 31.55627 | Y43: 32.625252 | Z43: 32.640443 | AA43: 31.851476 | AB43: 31.309869 | AC43: 32.114189 | AD43: 31.90638 | AE43: 35.136429 | AF43: 33.544629 | AG43: 34.25168 | AH43: 31.879671 | AI43: 32.819255 | AJ43: 29.317492 | AK43: 31.697012 | AL43: 29.500258 | AM43: 30.283524 | AN43: 30.3227 | AO43: 44.501388 | AP43: 40.740624 | AQ43: 42.634812 | AR43: 47.196532 | AS43: 49.662227 | AT43: 49.820092 | AU43: 55.829308 | AV43: 51.546298 | AW43: 54.63336
B47: NOTE 3. | C47: (LATAM Integrated Report) A large amount of our cargo revenue originates from a few product kinds, which may be affected by production, trade, or demand. The group's cargo demand is centered in a few product categories, such as fish from Chile, asparagus from Peru, and fresh flowers from Ecuador and Colombia.
A50: Export of Latin America | C50: Unit | D50: 2015Q1 | E50: 2015Q2 | F50: 2015Q3 | G50: 2015Q4 | H50: 2016Q1 | I50: 2016Q2 | J50: 2016Q3 | K50: 2016Q4 | L50: 2017Q1 | M50: 2017Q2 | N50: 2017Q3 | O50: 2017Q4 | P50: 2018Q1 | Q50: 2018Q2 | R50: 2018Q3 | S50: 2018Q4 | T50: 2019Q1 | U50: 2019Q2 | V50: 2019Q3 | W50: 2019Q4 | X50: 2020Q1 | Y50: 2020Q2 | Z50: 2020Q3 | AA50: 2020Q4 | AB50: 2021Q1 | AC50: 2021Q2 | AD50: 2021Q3 | AE50: 2021Q4 | AF50: 2022Q1 | AG50: 2022Q2
B52: Argentina | C52: millions | D52: 12061.478 | E52: 16411.409 | F52: 15872.122 | G52: 12464.044 | H52: 12454.085 | I52: 15437.821 | J52: 15828.638 | K52: 14239.39 | L52: 12764.826 | M52: 15524.041 | N52: 15851.884 | O52: 14521.123 | P52: 14535.245 | Q52: 15518.452 | R52: 15665.261 | S52: 16082.044 | T52: 14170.703 | U52: 16630.151 | V52: 17178.576 | W52: 17182.632 | X52: 13360.223 | Y52: 14235.15 | Z52: 14620.267 | AA52: 12729.978 | AB52: 15415.907 | AC52: 19980.47 | AD52: 22935.812 | AE52: 19654.524 | AF52: 19370.064 | AG52: 25040.716
B53: Brazil | C53: millions | D53: 42509.4 | E53: 51312.2 | F53: 49824.7 | G53: 46267.7 | H53: 40284.1 | I53: 49364.7 | J53: 48892.6 | K53: 45725.5 | L53: 50485 | M53: 57307.9 | N53: 56977.5 | O53: 53230.1 | P53: 54777.3 | Q53: 59205.2 | R53: 63303.5 | S53: 62233.6 | T53: 51231.7 | U53: 58348.6 | V53: 60253.2 | W53: 55966.1 | X53: 48569.5 | Y53: 52837.5 | Z53: 55372.1 | AA53: 53927.9 | AB53: 56160 | AC53: 81852.5 | AD53: 77753.4 | AE53: 68245.9 | AF53: 73392.4 | AG53: 92415.4
B54: Colombia | C54: millions | D54: 10053.224 | E54: 10372.044 | F54: 9513.2203 | G54: 8633.6253 | H54: 7192.4508 | I54: 8776.9628 | J54: 8765.7009 | K54: 9328.119 | L54: 9187.2188 | M54: 9472.8325 | N54: 10177.635 | O54: 10947.926 | P54: 9968.0723 | Q54: 11149.534 | R54: 11061.467 | S54: 10813.976 | T54: 9933.3521 | U54: 11017.864 | V54: 9897.1879 | W54: 9807.1971 | X54: 9065.8729 | Y54: 6849.7781 | Z54: 7912.9262 | AA54: 8480.39 | AB54: 9278.5692 | AC54: 9542.74 | AD54: 11075.9 | AE54: 12838.365 | AF54: 13763.622 | AG54: 16489.112
B55: Chile | C55: millions | D55: 17139.2 | E55: 16110.2 | F55: 14246.2 | G55: 14624.7 | H55: 15083.1 | I55: 14818.1 | J55: 14528.4 | K55: 16339.9 | L55: 15704.4 | M55: 16393.4 | N55: 17573.6 | O55: 19232.8 | P55: 19406.9 | Q55: 18949.6 | R55: 17621.6 | S55: 18860 | T55: 18259.2 | U55: 17022 | V55: 16697 | W55: 16814.2 | X55: 17215.2 | Y55: 17643.3 | Z55: 17835.5 | AA55: 21391.8 | AB55: 22145 | AC55: 23788.6 | AD55: 23462.7 | AE55: 25280.3 | AF55: 24585.7 | AG55: 25294.3
B56: Ecuador | C56: millions | D56: 5062 | E56: 5115.1 | F56: 4612.7 | G56: 4253 | H56: 3783.4 | I56: 4457.3 | J56: 4396.6 | K56: 4776.2 | L56: 4831.6 | M56: 4776.6 | N56: 4731.7 | O56: 5209.2 | P56: 5320 | Q56: 5656.8 | R56: 5706.7 | S56: 5473.7 | T56: 5362.7 | U56: 5877.4 | V56: 5801.2 | W56: 5732.5 | X56: 5537.3 | Y56: 4224.6 | Z56: 5202.6 | AA56: 5626.8 | AB56: 5954.2 | AC56: 6855.8 | AD56: 6989.7 | AE56: 7436.2 | AF56: 8231.1 | AG56: 9007.8
B57: Peru | C57: millions | D57: 8147.8201 | E57: 8282.9262 | F57: 8639.1257 | G57: 9344.4825 | H57: 7753.8066 | I57: 8366.3999 | J57: 9875.0571 | K57: 11086.474 | L57: 10173.397 | M57: 10556.236 | N57: 11908.293 | O57: 12783.668 | P57: 11951.1 | Q57: 12592.77 | R57: 12042.242 | S57: 12480.358 | T57: 11212.789 | U57: 11575.369 | V57: 12137.211 | W57: 13055.086 | X57: 10280.414 | Y57: 6770.855 | Z57: 11707.19 | AA57: 14146.846 | AB57: 13648.263 | AC57: 14564.562 | AD57: 16565.253 | AE57: 18372.759 | AF57: 17047.662 | AG57: 16185.547
B59: Total Export | C59: millions | D59: =+SUM(D52:D57) -> 94973.122 | E59: =+SUM(E52:E57) -> 107603.88 | F59: =+SUM(F52:F57) -> 102708.07 | G59: =+SUM(G52:G57) -> 95587.552 | H59: =+SUM(H52:H57) -> 86550.943 | I59: =+SUM(I52:I57) -> 101221.28 | J59: =+SUM(J52:J57) -> 102287 | K59: =+SUM(K52:K57) -> 101495.58 | ... AG59: =+SUM(AG52:AG57) -> 184432.88
B61: Total Revenues | C61: millions | D61: 350.322 | E61: 334.445 | F61: 309.781 | G61: 334.883 | H61: 275.967 | I61: 260.01 | J61: 264.46978 | K61: 309.054 | L61: 253.746 | M61: 256.511 | N61: 272.153 | O61: 337.02 | P61: 295.82 | Q61: 299.703 | R61: 278.883 | S61: 312.062 | T61: 263.496 | U61: 269.261 | V61: 251.691 | W61: 279.986 | X61: 252.389 | Y61: 318.727 | Z61: 283.956 | AA61: 354.821 | AB61: 345.22135 | AC61: 370.16223 | AD61: 361.437 | AE61: 464.814 | AF61: 430.69805 | AG61: 462.82881
B63: =+Cargo_Graph!M49 -> Chile | D63: {=+INDEX($D$52:$AG$57,MATCH($B$63,$B$52:$B$57,0),)} -> 17139.2 | E63: 16110.2 | F63: 14246.2 | G63: 14624.7 | H63: 15083.1 | I63: 14818.1 | J63: 14528.4 | K63: 16339.9 | L63: 15704.4 | M63: 16393.4 | N63: 17573.6 | O63: 19232.8 | P63: 19406.9 | Q63: 18949.6 | R63: 17621.6 | S63: 18860 | T63: 18259.2 | U63: 17022 | V63: 16697 | W63: 16814.2 | X63: 17215.2 | Y63: 17643.3 | Z63: 17835.5 | AA63: 21391.8 | AB63: 22145 | AC63: 23788.6 | AD63: 23462.7 | AE63: 25280.3 | AF63: 24585.7 | AG63: 25294.3
B64: Result: | C64: This research confirms that the current increase in cargo revenues is sustainable, given the dollar's strength appears to represent a long-term trend.
B67: NOTE 4. | C67: LATAM Yield per RTK depends on the following two variables.
B70: Yield of ATK | D70: 1Q13 | E70: 2Q13 | F70: 3Q13 | G70: 4Q13 | H70: 1Q14 | I70: 2Q14 | J70: 3Q14 | K70: 4Q14 | L70: 1Q15 | M70: 2Q15 | N70: 3Q15 | O70: 4Q15 | P70: 1Q16 | Q70: 2Q16 | R70: 3Q16 | S70: 4Q16 | T70: 1Q17 | U70: 2Q17 | V70: 3Q17 | W70: 4Q17 | X70: 1Q18 | Y70: 2Q18 | Z70: 3Q18 | AA70: 4Q18 | AB70: 1Q19 | AC70: 2Q19 | AD70: 3Q19 | AE70: 4Q19 | AF70: 1Q20 | AG70: 2Q20 | AH70: 3Q20 | AI70: 4Q20 | AJ70: 1Q21 | AK70: 2Q21 | AL70: 3Q21 | AM70: 4Q21 | AN70: 1Q22 | AO70: 2Q22
B72: Cargo ATK % | D72: 0.45878038 | E72: 0.5026422 | F72: 0.47860488 | G72: 0.49881146 | H72: 0.46014635 | I72: 0.46522111 | J72: 0.44934669 | K72: 0.47563582 | L72: 0.43317334 | M72: 0.44771466 | N72: 0.40511725 | O72: 0.40549131 | P72: 0.37950866 | Q72: 0.38693176 | R72: 0.35437394 | S72: 0.3759273 | T72: 0.27396488 | U72: 0.3001681 | V72: 0.2878485 | W72: 0.32465858 | X72: 0.29136367 | Y72: 0.32017549 | Z72: 0.26330962 | AA72: 0.28859405 | AB72: 0.24980828 | AC72: 0.28254066 | AD72: 0.29208512 | AE72: 0.33610665 | AF72: 0.38592376 | AG72: 0.94525329 | AH72: 0.92123979 | AI72: 0.84434654 | AJ72: 0.79152868 | AK72: 0.8544014 | AL72: 0.73552304 | AM72: 0.66809448 | AN72: 0.59095005 | AO72: 0.59053941
B73: A1 Jt Fuel | D73: 3.0926667 | E73: 2.7673333 | F73: 2.9436667 | G73: 2.89 | H73: 2.9253333 | I73: 2.8796667 | J73: 2.795 | K73: 2.186 | L73: 1.6303333 | M73: 1.761 | N73: 1.4443333 | O73: 1.2663333 | P73: 0.99066667 | Q73: 1.276 | R73: 1.2953333 | S73: 1.4346667 | T73: 1.502 | U73: 1.4056667 | V73: 1.5926667 | W73: 1.7453333 | X73: 1.8863333 | Y73: 2.0866667 | Z73: 2.135 | AA73: 1.9633333 | AB73: 1.8666667 | AC73: 1.922 | AD73: 1.8623333 | AE73: 1.8593333 | AF73: 1.4106667 | AG73: 3.52 | AH73: 1.0673333 | AI73: 1.168 | AJ73: 1.5606667 | AK73: 1.7593333 | AL73: 1.9023333 | AM73: 2.1946667 | AN73: 2.8743333 | AO73: 3.9786667
B75: RATK | C75: US$ cents | D75: 23.524424 | E75: 25.513007 | F75: 23.4077 | G75: 24.937028 | H75: 23.020558 | I75: 24.101883 | J75: 23.138934 | K75: 24.648252 | L75: 19.820706 | M75: 19.222523 | N75: 17.549005 | O75: 18.499675 | P75: 16.166468 | Q75: 15.920581 | R75: 15.920581 | S75: 18.150307 | T75: 16.556674 | U75: 17.299323 | V75: 17.297965 | W75: 20.529858 | X75: 18.375178 | Y75: 18.805831 | Z75: 17.057131 | AA75: 18.809191 | AB75: 16.431112 | AC75: 17.699346 | AD75: 15.811804 | AE75: 17.073021 | AF75: 15.905816 | AG75: 34.690556 | AH75: 29.642898 | AI75: 28.504514 | AJ75: 30.842814 | AK75: 33.778686 | AL75: 30.670794 | AM75: 33.331906 | AN75: 30.121786 | AO75: 31.716264
B77: Regression output
B79: Coefficients | E79: Adj. R Square | G79: 0.73385042
B80: Intercept | C80: 4.6054574
B81: Cargo ATK % | C81: 25.900427
B82: A1 Jt Fuel | C82: 2.7074969
C84: 2022 | D84: 2023 | E84: 2024 | F84: 2025 | G84: 2026 | H84: 2027
B85: Cargo ATK % | C85: 0.55 | D85: 0.5 | E85: 0.4 | F85: 0.4 | G85: =+H85 -> 0.35182704 | H85: =+Fleet!$C$30 -> 0.35182704
B86: A1 Jt Fuel | C86: 3.43 | D86: 3.1 | E86: 2.38 | F86: 2.38 | G86: 2.38 | H86: 2.38
B87: RATK | C87: =+$C$80+SUMPRODUCT(C85:C86,$C$81:$C$82) -> 28.137406 | D87: =+$C$80+SUMPRODUCT(D85:D86,$C$81:$C$82) -> 25.948911 | E87: =+$C$80+SUMPRODUCT(E85:E86,$C$81:$C$82) -> 21.409471 | F87: =+$C$80+SUMPRODUCT(F85:F86,$C$81:$C$82) -> 21.409471 | G87: =+$C$80+SUMPRODUCT(G85:G86,$C$81:$C$82) -> 20.161771 | H87: =+$C$80+SUMPRODUCT(H85:H86,$C$81:$C$82) -> 20.161771

Sheet Fleet
C1: 2012 | D1: 2013 | E1: 2014 | F1: 2015 | G1: 2016 | H1: 2017 | I1: 2018 | J1: 2019 | K1: 2020 | L1: 2021 | M1: 2022 | N1: f2023 | P1: Seats | Q1: Maximum payload | R1: Net maximum payload
B2: Long-range fleet | Q2: tonnes | R2: (Max - passenger weight)
B3: Boeing 737-300 | C3: 8 | D3: 5 | E3: 0 | F3: 0 | G3: 0 | H3: 0 | I3: 0 | J3: 0 | K3: 0 | L3: 0 | M3: 0 | N3: 0 | P3: 148 | Q3: 19 | R3: =+Q3-P3*$R$11 -> 6.5806392
B4: Boeing 767-300 | C4: 41 | D4: 43 | E4: 38 | F4: 38 | G4: 37 | H4: 36 | I4: 35 | J4: 31 | K4: 17 | L4: 22 | M4: 13 | N4: 10 | P4: 221 | Q4: 33 | R4: =+Q4-P4*$R$11 -> 14.454873
B5: Boeing 777-300ER | C5: 8 | D5: 10 | E5: 10 | F5: 10 | G5: 10 | H5: 10 | I5: 10 | J5: 10 | K5: 10 | L5: 10 | M5: 10 | N5: 10 | P5: 362 | Q5: 46 | R5: =+Q5-P5*$R$11 -> 15.622915
B6: Boeing 787-8 | C6: 3 | D6: 5 | E6: 10 | F6: 10 | G6: 10 | H6: 10 | I6: 10 | J6: 10 | K6: 10 | L6: 10 | M6: 10 | N6: 10 | P6: 247 | Q6: 36 | R6: =+Q6-P6*$R$11 -> 15.273094
B7: Boeing 787-9 | C7: 0 | D7: 0 | E7: 0 | F7: 7 | G7: 12 | H7: 14 | I7: 14 | J7: 16 | K7: 12 | L7: 17 | M7: 20 | N7: 21 | P7: 313 | Q7: 44 | R7: =+Q7-P7*$R$11 -> 17.73473
B8: Airbus A350-900 | C8: 0 | D8: 0 | E8: 0 | F8: 1 | G8: 7 | H8: 5 | I8: 7 | J8: 13 | K8: 10 | L8: 0 | M8: 0 | N8: 0 | P8: 348 | Q8: 45 | R8: =+Q8-P8*$R$11 -> 15.797719
B9: Airbus A340-300/500 | C9: 7 | D9: 6 | E9: 3 | F9: 0 | G9: 0 | H9: 0 | I9: 0 | J9: 0 | K9: 0 | L9: 0 | M9: 0 | N9: 0 | P9: 260 | Q9: 37 | R9: =+Q9-P9*$R$11 -> 15.182204
B11: Average seats | C11: {=+SUMPRODUCT(C3:C9/SUM(C3:C9),$P$3:$P$9)} -> 234.35821 | D11: {=+SUMPRODUCT(D3:D9/SUM(D3:D9),$P$3:$P$9)} -> 241.42029 | E11: {=+SUMPRODUCT(E3:E9/SUM(E3:E9),$P$3:$P$9)} -> 250.29508 | F11: {=+SUMPRODUCT(F3:F9/SUM(F3:F9),$P$3:$P$9)} -> 257.98485 | G11: {=+SUMPRODUCT(G3:G9/SUM(G3:G9),$P$3:$P$9)} -> 269.19737 | H11: {=+SUMPRODUCT(H3:H9/SUM(H3:H9),$P$3:$P$9)} -> 268.90667 | I11: {=+SUMPRODUCT(I3:I9/SUM(I3:I9),$P$3:$P$9)} -> 271.61842 | J11: {=+SUMPRODUCT(J3:J9/SUM(J3:J9),$P$3:$P$9)} -> 280.9125 | ... N11: {=+SUMPRODUCT(N3:N9/SUM(N3:N9),$P$3:$P$9)} -> 291.62745 | P11: Average international passengers' weight (tons) | R11: 0.0839146
B12: Total seats | C12: =+SUMPRODUCT(C3:C9,$P$3:$P$9) -> 15702 | D12: =+SUMPRODUCT(D3:D9,$P$3:$P$9) -> 16658 | E12: =+SUMPRODUCT(E3:E9,$P$3:$P$9) -> 15268 | F12: =+SUMPRODUCT(F3:F9,$P$3:$P$9) -> 17027 | G12: =+SUMPRODUCT(G3:G9,$P$3:$P$9) -> 20459 | H12: =+SUMPRODUCT(H3:H9,$P$3:$P$9) -> 20168 | I12: =+SUMPRODUCT(I3:I9,$P$3:$P$9) -> 20643 | J12: =+SUMPRODUCT(J3:J9,$P$3:$P$9) -> 22473 | ... N12: =+SUMPRODUCT(N3:N9,$P$3:$P$9) -> 14873
B14: Average availabe payload for cargo (tons) | C14: {=+SUMPRODUCT(C3:C9/SUM(C3:C9),$R$3:$R$9)} -> 13.76676 | D14: {=+SUMPRODUCT(D3:D9/SUM(D3:D9),$R$3:$R$9)} -> 14.176096 | E14: {=+SUMPRODUCT(E3:E9/SUM(E3:E9),$R$3:$R$9)} -> 14.81626 | F14: {=+SUMPRODUCT(F3:F9/SUM(F3:F9),$R$3:$R$9)} -> 15.124032 | G14: {=+SUMPRODUCT(G3:G9/SUM(G3:G9),$R$3:$R$9)} -> 15.357779 | H14: {=+SUMPRODUCT(H3:H9/SUM(H3:H9),$R$3:$R$9)} -> 15.421471 | I14: {=+SUMPRODUCT(I3:I9/SUM(I3:I9),$R$3:$R$9)} -> 15.444091 | J14: {=+SUMPRODUCT(J3:J9/SUM(J3:J9),$R$3:$R$9)} -> 15.57734 | ... N14: {=+SUMPRODUCT(N3:N9/SUM(N3:N9),$R$3:$R$9)} -> 16.194866
A15: (1) | B15: Total availabe payload for cargo (tons) | C15: =+SUMPRODUCT(C3:C9,$R$3:$R$9) -> 922.37295 | D15: =+SUMPRODUCT(D3:D9,$R$3:$R$9) -> 978.15059 | E15: =+SUMPRODUCT(E3:E9,$R$3:$R$9) -> 903.79189 | F15: =+SUMPRODUCT(F3:F9,$R$3:$R$9) -> 998.18611 | G15: =+SUMPRODUCT(G3:G9,$R$3:$R$9) -> 1167.1912 | H15: =+SUMPRODUCT(H3:H9,$R$3:$R$9) -> 1156.6103 | I15: =+SUMPRODUCT(I3:I9,$R$3:$R$9) -> 1173.7509 | J15: =+SUMPRODUCT(J3:J9,$R$3:$R$9) -> 1246.1872 | ... N15: =+SUMPRODUCT(N3:N9,$R$3:$R$9) -> 825.93815
B18: Cargo Fleet | P18: Net maximum payload
B19: Cargo Boeing 767-300F | C19: 16 | D19: 15 | E19: 15 | F19: 10 | G19: 9 | H19: 10 | I19: 11 | J19: 11 | K19: 12 | L19: 13 | M19: 16 | N19: 20 | P19: 28
A21: (2) | B21: Available payload | C21: =+C19*$P$19 -> 448 | D21: =+D19*$P$19 -> 420 | E21: =+E19*$P$19 -> 420 | F21: =+F19*$P$19 -> 280 | G21: =+G19*$P$19 -> 252 | H21: =+H19*$P$19 -> 280 | I21: =+I19*$P$19 -> 308 | J21: =+J19*$P$19 -> 308 | ... N21: =+N19*$P$19 -> 560
B23: (2) / [(1) + (2)] | C23: =+C21/(C21+C15) -> 0.3269183 | D23: =+D21/(D21+D15) -> 0.30039683 | E23: =+E21/(E21+E15) -> 0.31727041 | F23: =+F21/(F21+F15) -> 0.21906043 | G23: =+G21/(G21+G15) -> 0.17756593 | H23: =+H21/(H21+H15) -> 0.19490323 | I23: =+I21/(I21+I15) -> 0.2078622 | J23: =+J21/(J21+J15) -> 0.19817433 | ... N23: =+N21/(N21+N15) -> 0.40405843
C26: 2027 | D26: * Considering the fleet given in the business plan
A27: (1) | B27: Total availabe payload for cargo (tons) | C27: =+M15*(61/53) -> 980.10662
A28: (2) | B28: Available payload | C28: =+N21*(19/20) -> 532
B30: (2) / [(1) + (2)] | C30: =+C28/SUM(C27:C28) -> 0.35182704
C35: 2012 | D35: 2013 | E35: 2014 | F35: 2015 | G35: 2016 | H35: 2017 | I35: 2018 | J35: 2019 | K35: 2020 | L35: 2021
B36: Amounts raised from sale of property, plant and equipment | C36: 73429 | D36: 225196 | E36: 524370 | F36: 57117.138 | G36: 76084 | H36: 51316 | I36: 223753 | J36: 50322 | K36: 75566 | L36: 105000
B37: Purchases of property, plant and equipment | C37: -2389364 | D37: -1381786 | E37: -474656 | F37: -1569749.4 | G37: -694370 | H37: -403666 | I37: -660707 | J37: -1276621 | K37: -324264 | L37: -587245 | M37: =+H37+H36 -> -352350 | N37: =+I37+I36 -> -436954 | O37: =+J37+J36 -> -1226299 | P37: =+K37+K36 -> -248698 | Q37: =+L37+L36 -> -482245
B38: Amounts raised from sale of intangible assets | E38: 564266 | F38: 91 | G38: 1 | H38: 0 | I38: 0
B39: Purchases of intangible assets | C39: -59166 | D39: -43484 | E39: -1440445 | F39: -52449 | G39: -88587 | H39: -87318 | I39: -96206 | J39: -140173 | K39: -75433 | L39: -88518
B40: Payment from other long-term assets | C40: 38035 | D40: 22144 | E40: -55759
B41: Other cash inflows (outflows) | C41: 27143 | D41: 75448 | E41: -17399 | F41: 10576.157 | G41: 843 | H41: -9223 | I41: -2476 | J41: -2249 | K41: -2192 | L41: 18475
B42: AVERAGE | C42: =+SUM(C36:C41) -> -2309923 | D42: =+SUM(D36:D41) -> -1102482 | E42: =+SUM(E36:E41) -> -899623 | F42: =+SUM(F36:F41) -> -1554414.1 | G42: =+SUM(G36:G41) -> -706029 | H42: =+SUM(H36:H41) -> -448891 | I42: =+SUM(I36:I41) -> -535636 | J42: =+SUM(J36:J41) -> -1368721 | ... L42: =+SUM(L36:L41) -> -552288 | M42: =+AVERAGE(C42:L42) -> -980433.01
B44: Flotta aerea operativa per programma e modello - Di proprietà | C44: 209 | D44: 248 | E44: 208 | F44: 210 | G44: 221 | H44: 214 | I44: 219 | J44: 225 | K44: 198 | L44: 185
B45: Aircraft Operating Fleet - Operating Lease | C45: 123 | D45: 128 | E45: 97 | F45: 92 | G45: 111 | H45: 93 | I45: 91 | J45: 106 | K45: 98 | L45: 117
B46: Total | C46: =SUM(C44:C45) -> 332 | D46: =SUM(D44:D45) -> 376 | E46: =SUM(E44:E45) -> 305 | F46: =SUM(F44:F45) -> 302 | G46: =SUM(G44:G45) -> 332 | H46: =SUM(H44:H45) -> 307 | I46: =SUM(I44:I45) -> 310 | J46: =SUM(J44:J45) -> 331 | ... L46: =SUM(L44:L45) -> 302
B47: =+"Differential "&B44 -> Differential Flotta aerea operativa per programma e modello - Di proprietà | D47: =+D44-C44 -> 39 | E47: =+E44-D44 -> -40 | F47: =+F44-E44 -> 2 | G47: =+G44-F44 -> 11 | H47: =+H44-G44 -> -7 | I47: =+I44-H44 -> 5 | J47: =+J44-I44 -> 6 | K47: =+K44-J44 -> -27 | L47: =+L44-K44 -> -13
B48: =+"Differential "&B45 -> Differential Aircraft Operating Fleet - Operating Lease | D48: =+D45-C45 -> 5 | E48: =+E45-D45 -> -31 | F48: =+F45-E45 -> -5 | G48: =+G45-F45 -> 19 | H48: =+H45-G45 -> -18 | I48: =+I45-H45 -> -2 | J48: =+J45-I45 -> 15 | K48: =+K45-J45 -> -8 | L48: =+L45-K45 -> 19
B49: =+"Differential "&B46 -> Differential Total | D49: =+D46-C46 -> 44 | E49: =+E46-D46 -> -71 | F49: =+F46-E46 -> -3 | G49: =+G46-F46 -> 30 | H49: =+H46-G46 -> -25 | I49: =+I46-H46 -> 3 | J49: =+J46-I46 -> 21 | K49: =+K46-J46 -> -35 | L49: =+L46-K46 -> 6
C52: Proprietà | D52: Leasing | E52: Total | G52: Proprietà | H52: Leasing | I52: Total
B53: Amounts raised from sale of property, plant and equipment | C53: =+CORREL(C36:L36,$C$44:$L$44) -> 0.10299838 | D53: =+CORREL(C36:L36,$C$45:$L$45) -> -0.10076564 | E53: =+CORREL(C36:L36,$C$46:$L$46) -> 0.014874437 | G53: =+CORREL(D36:L36,$D$47:$L$47) -> -0.34801872 | H53: =+CORREL(D36:L36,$D$48:$L$48) -> -0.57749768 | I53: =+CORREL(D36:L36,$D$49:$L$49) -> -0.50193476
B54: Purchases of property, plant and equipment | C54: =+CORREL(C37:L37,$C$44:$L$44) -> -0.28908764 | D54: =+CORREL(C37:L37,$C$45:$L$45) -> -0.50641089 | E54: =+CORREL(C37:L37,$C$46:$L$46) -> -0.48418167 | G54: =+CORREL(D37:L37,$D$47:$L$47) -> -0.67252176 | H54: =+CORREL(D37:L37,$D$48:$L$48) -> -0.33972617 | I54: =+CORREL(D37:L37,$D$49:$L$49) -> -0.59624681
B55: Purchases of intangible assets | C55: =+CORREL(C39:L39,$C$44:$L$44) -> 0.12554517 | D55: =+CORREL(C39:L39,$C$45:$L$45) -> 0.24052362 | E55: =+CORREL(C39:L39,$C$46:$L$46) -> 0.22181836 | G55: =+CORREL(D39:L39,$D$47:$L$47) -> 0.62321596 | H55: =+CORREL(D39:L39,$D$48:$L$48) -> 0.64763916 | I55: =+CORREL(D39:L39,$D$49:$L$49) -> 0.71276175
B56: Other cash inflows (outflows) | C56: =+CORREL(C41:L41,$C$44:$L$44) -> 0.49856726 | D56: =+CORREL(C41:L41,$C$45:$L$45) -> 0.79028455 | E56: =+CORREL(C41:L41,$C$46:$L$46) -> 0.78845543 | G56: =+CORREL(D41:L41,$D$47:$L$47) -> 0.74294401 | H56: =+CORREL(D41:L41,$D$48:$L$48) -> 0.38278561 | I56: =+CORREL(D41:L41,$D$49:$L$49) -> 0.66228573

Sheet Cap_Inc
A2: CAPITAL AND DEBT ISSUANCES AND USES | H2: FINANCIAL LIABILITIES
A3: Capital/Debt Increase | C3: Amount USD Th | D3: Description | H3: 3Q 2022 | L3: Changes during 4Q 2022 | O3: 44926
B4: New share issed | C4: 800000
B5: Convertible Bond Class B | C5: 1373000 | H5: Operating and financial leases | I5: 4406845 | L5: Decrease in Operating lease | M5: =I5-P5 -> 429845 | O5: Operating and Financial Leases | P5: 3977000
B6: Convertible Bonds Class C | C6: 3269000
B7: Capital Increase New resources | C7: =SUM(C4:C6) -> 5442000 | D7: equity
B9: Convertible Bond Class A | C9: 1257000 | H9: bank loans | I9: 581731 | L9: Debt brazil reapyment | M9: 298000 | O9: PDP Financing (Bank loan) | P9: 98000
B10: Convertible Bond Class C | C10: 3594000 | L10: Other Bank loans repayment | M10: =I9-P9-M9 -> 185731
B11: Capital Increase substitution in payment | C11: =SUM(C9:C10) -> 4851000 | D11: operating liabilties | L11: Totla bank loan repayment | M11: =SUM(M9:M10) -> 483731
B12: Total Capital Increase | C12: =C7+C11 -> 10293000
H13: guaranteed obligations | I13: 4095256 | L13: Reapyment of DIP | M13: 2929000 | O13: other guaranteed existing | P13: =I13-M16 -> 95256
L14: Repayment fo RCF | M14: 600000
L15: Subsidiary claims | M15: 471000
B16: New Revolving Credit Facility | C16: 500000 | D16: not used | L16: Total guaranteed reapyments | M16: =SUM(M13:M15) -> 4000000
B17: Term B Loan | C17: 2250000
B18: Debt Issuance New Resources | C18: =SUM(C16:C17) -> 2750000 | D18: financial liabilties | L18: Term B Loan Issaunce | M18: 2250000 | O18: Term B Loan | P18: 2250000
L19: PV of New Corporate Bond | M19: 42000 | O19: Present Value of the new Coprate Bond | P19: 42000
B20: Corporate Bond | C20: 131000
B21: Debt issuance substitution in payment | C21: =C20 -> 131000 | D21: operating liabilties | L21: Total guarnateed issuances | M21: =SUM(M18:M20) -> 2292000 | O21: Total guaranteed obligations | P21: =SUM(P13:P20) -> 2387256
B22: Debt Issuance Total | C22: =C21+C18 -> 2881000
H24: Othr obligations with public | I24: 2335563 | L24: USD Bond Repayment | M24: 1519000 | O24: Othe obligations with public | P24: 0
L25: Other bonds repayment | M25: =816563 -> 816563
A26: New Resources
B27: New share issed | C27: 800000 | D27: equity | H27: Other loans | I27: 81259 | O27: Other loans | P27: 81259
B28: Convertible Bond Class B | C28: 1373000 | D28: equity | O28: Total other loans | P28: =SUM(P27) -> 81259
B29: Convertible Bonds Class C | C29: 3269000 | D29: equity
B30: Term B Loan | C30: 2250000 | D30: fin. Liabilties | L30: Substituion in payment for fin.liab | M30: =M10+M25+M5 -> 1432139 | O30: Total Financial Debt | P30: =SUM(P5,P9,P21,P24,P28) -> 6543515
A32: Cash already available
B33: Cash | C33: 989000 | H33: OPERATING LIABILITIES
B34: Total soruces | C34: =SUM(C27:C33) -> 8681000 | H34: 3Q 2022 | L34: Changes during 4Q 2022 | O34: 44926
V35: Liabilties accrued
A36: Uses | H36: Operating liabilites (current & non-current) | I36: 10193628 | L36: Subpayment for op. liab. | M36: =C11-M30 -> 3418861 | O36: Operating liabilites (current & non-current) | P36: =I36-M39 -> 5631767 | V36: 538784
B37: Rpeayment of DIP | C37: 2929000 | D37: otehr guranteed obligations | L37: PV Debt Issuance in sub. Payments | M37: 42000
B38: Adimin/professonal/bakcstop/Financing/other fees | C38: 1101000 | D38: Operating liabilties | H38: 2021 Op. Liab (current&non) | I38: =9977.185*1000 -> 9977185 | L38: Admin/pro/fin and other fees | M38: =C38 -> 1101000
B39: RCF Repayment | C39: 600000 | D39: other guranteed obligations | L39: Total decrease in operating liabilties | M39: =SUM(M36:M38) -> 4561861
B40: USD Bond Repayment | C40: 1519000 | D40: Other obligations with public
B41: Debt Brazil Repayment | C41: 298000 | D41: Bank loans | H41: EQUITY
B42: Subsidiary Claims | C42: 471000 | D42: other guranteed obligations | H42: 3Q 2022 | L42: Changes during 4Q 2022 | O42: 44926
B43: Cash in balnce | C43: =C34-SUM(C37:C42) -> 1763000
B44: Total uses | C44: =SUM(C37:C43) -> 8681000 | H44: Total shaeholders' Equity | I44: -8263375 | L44: Total Capital Increase | M44: =C12 -> 10293000 | O44: Total shaeholders' Equity | P44: =I44+M44 -> 2029625
H46: CASH BALANCE
B47: DTE expenses adn fees | C47: 118000 | H47: 3Q 2022 | L47: Changes during 4Q 2022 | O47: 44926
B48: Fees & oters | C48: 743000
B49: Administrative claims | C49: 240000 | H49: Cash and Cash Equivalents | I49: 897183 | L49: Increase in cash | M49: =M44-M5-M11-M16+M21-M24-M39 -> 1590563 | O49: cahs balance | P49: =I49+M49 -> 2487746
B50: Admin/professional/finaincg other ffes | C50: =(SUM(C47:C49)) -> 1101000

Sheet Sch_Deb
A1: Data are presetned in US$ Thousands
C2: Notes | E2: 2018 | G2: 2019 | I2: 2020 | K2: 2021 | M2: 3Q 2022 | P2: 2022 | Q2: 2023 | R2: 2024 | S2: 2025 | T2: 2026 | U2: 2027
A3: CASH FLOW STATEMENT
B4: Operating Cash flow
B5: Unlevered Free Cash flow from operations | C5: Note A | P5: 50000 | Q5: 50000 | R5: 50000 | S5: 50000 | T5: 50000 | U5: 50000 | W5: input DCF
B6: Interest expenses cash outflow | D6: 0.27 | P6: =-P43 -> -769659.25 | Q6: =-Q43 -> #REF! | R6: =-R43 -> #REF! | S6: =-S43 -> #REF! | T6: =-T43 -> #REF! | U6: =-U43 -> #REF!
B7: Tax Shield on Interest expesnes | P7: =-$D$6*P6 -> 207808 | Q7: =-$D$6*Q6 -> #REF! | R7: =-$D$6*R6 -> #REF! | S7: =-$D$6*S6 -> #REF! | T7: =-$D$6*T6 -> #REF! | U7: =-$D$6*U6 -> #REF!
B8: Levered free cahs flow | E8: 864268 | G8: 2445447 | I8: -3903883 | K8: -386655 | P8: =SUM(P5:P7) -> -511851.25 | Q8: =SUM(Q5:Q7) -> #REF! | R8: =SUM(R5:R7) -> #REF! | S8: =SUM(S5:S7) -> #REF! | T8: =SUM(T5:T7) -> #REF! | U8: =SUM(U5:U7) -> #REF!
B9: Cash flow from debt financing | G9: =G30-E30 -> -264826 | I9: =I30-G30 -> 707031 | K9: =K30-I30 -> -457378 | P9: =P32 -> -3696928 | Q9: =Q32 -> #REF! | R9: =R32 -> #REF! | S9: =S32 -> #REF! | T9: =T32 -> #REF! | U9: =U32 -> #REF!
B10: Cash flow from equity financing | C10: Note F | E10: -54580.443 | G10: -57129 | I10: 0 | K10: 0 | P10: =D46-Cap_Inc!M39 -> 5731408.5 | Q10: =(Q46-P46)-Q68 -> 0 | R10: =(R46-Q46)-R68 -> 0 | S10: =(S46-R46)-S68 -> 0 | T10: =(T46-S46)-T68 -> 0 | U10: =(U46-T46)-U68 -> 0
B11: Free cahs flow from the Firm | G11: =SUM(G8:G10) -> 2123492 | I11: =SUM(I8:I10) -> -3196852 | K11: =SUM(K8:K10) -> -844033 | N11: =IF(O19-P75>0,O19-P75,0) -> 1042016 | P11: =SUM(P8:P10) -> 1522629.3 | Q11: =SUM(Q8:Q10) -> #REF! | R11: =SUM(R8:R10) -> #REF! | S11: =SUM(S8:S10) -> #REF! | T11: =SUM(T8:T10) -> #REF! | U11: =SUM(U8:U10) -> #REF!
A14: FINANCIAL LIBAILITIES
B15: Loans to exporters | C15: Note 2 | E15: 400721 | G15: 341475 | I15: 151701 | K15: 159161 | M15: 161447 | P15: =M15 -> 161447 | Q15: =P15*(1+Q16) -> #REF! | R15: =Q15*(1+R16) -> #REF! | S15: =R15*(1+S16) -> #REF! | T15: =S15*(1+T16) -> #REF! | U15: =T15*(1+U16) -> #REF!
B16: growth (revenues/recivables) | Q16: =H93 -> #REF! | R16: =I93 -> #REF! | S16: =J93 -> #REF! | T16: =K93 -> #REF! | U16: =L93 -> #REF!
B17: Bank loans | C17: Note 3,4 | E17: 222741 | G17: 217255 | I17: 525273 | K17: 521838 | M17: 581731 | O17: =Cap_Inc!P9 -> 98000 | P17: =$O$17 -> 98000 | Q17: =$O$17 -> 98000 | R17: =$O$17 -> 98000 | S17: =$O$17 -> 98000 | T17: =$O$17 -> 98000 | U17: =$O$17 -> 98000
B18: growth (FCF needs) | Q18: 0 | R18: 0 | S18: 0 | T18: 0 | U18: 0
B19: Guaranteed obligations and other | C19: Note 1,5 | E19: 3207473 | G19: 2737759 | I19: 3257972 | K19: 3235957 | M19: 4095256 | O19: =Cap_Inc!$P$21 -> 2387256 | P19: =Cap_Inc!$P$21 -> 2387256 | Q19: =Cap_Inc!$P$21 -> 2387256 | R19: =Cap_Inc!$P$21 -> 2387256 | S19: =Cap_Inc!$P$21 -> 2387256 | T19: =Cap_Inc!$P$21 -> 2387256 | U19: =Cap_Inc!$P$21 -> 2387256
B20: growth | Q20: =Q19/P19-1 -> 0 | R20: =R19/Q19-1 -> 0 | S20: =S19/R19-1 -> 0 | T20: =T19/S19-1 -> 0 | U20: =U19/T19-1 -> 0
B21: Subtotal bank loans | E21: 3830935 | G21: 3296489 | I21: 3934946 | K21: 3916956 | M21: 4838434 | P21: =SUM(P15:P19) -> 2646703 | Q21: =SUM(Q15:Q19) -> #REF! | R21: =SUM(R15:R19) -> #REF! | S21: =SUM(S15:S19) -> #REF! | T21: =SUM(T15:T19) -> #REF! | U21: =SUM(U15:U19) -> #REF!
B22: aggregated growth | Q22: =Q21/P21-1 -> #REF! | R22: =R21/Q21-1 -> #REF! | S22: =S21/R21-1 -> #REF! | T22: =T21/S21-1 -> #REF! | U22: =U21/T21-1 -> #REF!
B24: Obligation with the public | C24: Note 6 | E24: 1553079 | G24: 2064934 | I24: 2183407 | K24: 2253198 | M24: 2335563 | P24: =Cap_Inc!P24 -> 0 | Q24: =P24 -> 0 | R24: =Q24 -> 0 | S24: =R24 -> 0 | T24: =S24 -> 0 | U24: =T24 -> 0
B25: Financial leases + Lease Liabilties | C25: Note 7 | E25: 4746481 | G25: 4639422 | I25: 4735507 | K25: 4149820 | M25: 4406845 | P25: 3977000 | Q25: =H107+P25 -> 4796000 | R25: =I107+Q25 -> 4696000 | S25: =J107+R25 -> 4779000 | T25: =K107+S25 -> 4856000 | U25: =L107+T25 -> 5163000
B26: growth | Q26: =Q25/P25-1 -> 0.20593412 | R26: 0.05 | S26: 0.03 | T26: 0.03 | U26: 0.03
B27: Other loans | C27: Note 9 | E27: 252858 | G27: 101261 | I27: 0 | K27: 76508 | M27: 81259 | P27: =Cap_Inc!P28 -> 81259 | Q27: =$P$27 -> 81259 | R27: =$P$27 -> 81259 | S27: =$P$27 -> 81259 | T27: =$P$27 -> 81259 | U27: =$P$27 -> 81259
B28: Hedge and other derviaves | C28: Note 8 | E28: 33973 | G28: 50394 | I28: 5671 | K28: 5671 | M28: 263 | P28: =M28 -> 263 | Q28: =P28*(1+Q29) -> #REF! | R28: =Q28*(1+R29) -> #REF! | S28: =R28*(1+S29) -> #REF! | T28: =S28*(1+T29) -> #REF! | U28: =T28*(1+U29) -> #REF!
B29: growth (revenues) | Q29: =H93 -> #REF! | R29: =I93 -> #REF! | S29: =J93 -> #REF! | T29: =K93 -> #REF! | U29: =L93 -> #REF!
B30: Total Financial liabilties | E30: 10417326 | G30: 10152500 | I30: 10859531 | K30: 10402153 | M30: 11662364 | P30: =SUM(P21,P24,P25,P28,P27) -> 6705225 | Q30: =SUM(Q21,Q24,Q25,Q28,Q27) -> #REF! | R30: =SUM(R21,R24,R25,R28,R27) -> #REF! | S30: =SUM(S21,S24,S25,S28,S27) -> #REF! | T30: =SUM(T21,T24,T25,T28,T27) -> #REF! | U30: =SUM(U21,U24,U25,U28,U27) -> #REF!
P31: =P21+P27+P28 -> 2728225 | Q31: =Q21+Q27+Q28 -> #REF! | R31: =R21+R27+R28 -> #REF! | S31: =S21+S27+S28 -> #REF! | T31: =T21+T27+T28 -> #REF! | U31: =U21+U27+U28 -> #REF!
B32: Cash flow form debt finaincing | P32: =P30-K30 -> -3696928 | Q32: =Q30-P30 -> #REF! | R32: =R30-Q30 -> #REF! | S32: =S30-R30 -> #REF! | T32: =T30-S30 -> #REF! | U32: =U30-T30 -> #REF!
B34: FORWARD LOOKING COST OF DEBT
B35: Risk Free | P35: 0.0405 | Q35: 0.0405 | R35: 0.0405 | S35: 0.0405 | T35: 0.0405 | U35: 0.0405
B36: Defualt credit spread | P36: 0.074285 | Q36: 0.074285 | R36: 0.074285 | S36: 0.074285 | T36: 0.074285 | U36: 0.074285
B37: Pre-tax cost of debt | P37: 0.114785 | Q37: 0.114785 | R37: 0.114785 | S37: 0.114785 | T37: 0.114785 | U37: 0.114785
A39: FINANCIAL EXPENSES
B40: Bank loan interest | G40: 325650 | I40: 314468 | K40: 580193 | P40: =P37*P21 -> 303801.8 | Q40: =Q37*Q21 -> #REF! | R40: =R37*R21 -> #REF! | S40: =S37*S21 -> #REF! | T40: =T37*T21 -> #REF! | U40: =U37*U21 -> #REF!
B41: Financial Lease + Lease Liabilties | G41: 243794 | I41: 216163 | K41: 167826 | P41: =P25*P37 -> 456499.95 | Q41: =Q25*Q37 -> 550508.86 | R41: =R25*R37 -> 539030.36 | S41: =S25*S37 -> 548557.52 | T41: =T25*T37 -> 557395.96 | U41: =U25*U37 -> 592634.95
B42: Other financial debt | G42: 20490 | I42: 56348 | K42: 57525 | P42: {=SUM(P24+P27:P28)*P37} -> 9357.5028 | Q42: {=SUM(Q24+Q27:Q28)*Q37} -> #REF! | R42: {=SUM(R24+R27:R28)*R37} -> #REF! | S42: {=SUM(S24+S27:S28)*S37} -> #REF! | T42: {=SUM(T24+T27:T28)*T37} -> #REF! | U42: {=SUM(U24+U27:U28)*U37} -> #REF!
B43: Total | G43: 589934 | I43: 586979 | K43: 805544 | P43: =P30*P37 -> 769659.25 | Q43: =Q30*Q37 -> #REF! | R43: =R30*R37 -> #REF! | S43: =S30*S37 -> #REF! | T43: =T30*T37 -> #REF! | U43: =U30*U37 -> #REF!
D44: 0.1692076
A45: EQUITY
B46: Parent Share capital | C46: Note G | D46: 10293270 | E46: 3146265 | G46: 3146265 | I46: 3146265 | K46: 3146265 | M46: =K46+D46 -> 13439535 | P46: =K46+D46+K47+K49-P49 -> 3604476.5 | Q46: =P46 -> 3604476.5 | R46: =Q46 -> 3604476.5 | S46: =R46 -> 3604476.5 | T46: =S46 -> 3604476.5 | U46: =T46 -> 3604476.5
B47: Parent Retained earnings/(losses) | C47: Note H | E47: 218971 | G47: 352272 | I47: -4193615 | K47: -8841106 | M47: =K47 -> -8841106 | P47: =0+P67 -> 47684.656 | Q47: =P47+Q67 -> 95369.313 | R47: =Q47+R67 -> 143053.97 | S47: =R47+S67 -> 190738.63 | T47: =S47+T67 -> 238423.28 | U47: =T47+U67 -> 286107.94
B48: Parent Treasury Shares | E48: -178 | G48: -178 | I48: -178 | K48: -178 | L48: =1-L51 -> 0.95369313 | M48: =K48 -> -178 | P48: =K48 -> -178 | Q48: =P48 -> -178 | R48: =Q48 -> -178 | S48: =R48 -> -178 | T48: =S48 -> -178 | U48: =T48 -> -178
B49: Parent Other reserves | C49: Note I | E49: -4365 | G49: -367577 | I49: -1388185 | K49: -1361529 | M49: =K49 -> -1361529 | P49: =G49 -> -367577 | Q49: =$P$49 -> -367577 | R49: =$P$49 -> -367577 | S49: =$P$49 -> -367577 | T49: =$P$49 -> -367577 | U49: =$P$49 -> -367577
B50: Total Parent Equity | E50: =SUM(E46:E49) -> 3360693 | G50: =SUM(G46:G49) -> 3130782 | I50: =SUM(I46:I49) -> -2435713 | K50: =SUM(K46:K49) -> -7056548 | M50: =SUM(M46:M49) -> 3236721.5 | P50: =SUM(P46:P49) -> 3284406.2 | Q50: =SUM(Q46:Q49) -> 3332090.8 | R50: =SUM(R46:R49) -> 3379775.5 | S50: =SUM(S46:S49) -> 3427460.1 | T50: =SUM(T46:T49) -> 3475144.8 | U50: =SUM(U46:U49) -> 3522829.5
B51: Non-controlling interests Share Capital | C51: 0.1692076 | K51: 622342.81 | L51: =M51/M46 -> 0.046306872 | M51: =K51 -> 622342.81 | N51: =M51 -> 622342.81 | P51: =$M$51 -> 622342.81 | Q51: =$M$51 -> 622342.81 | R51: =$M$51 -> 622342.81 | S51: =$M$51 -> 622342.81 | T51: =$M$51 -> 622342.81 | U51: =$M$51 -> 622342.81
B52: Non ctronlling retained earnings+others | K52: =K53-K51 -> -632698.81 | M52: =K52 -> -632698.81 | N52: =N53-N51 -> -635719.81 | P52: =M52+P66*$L$51 -> -630383.47 | Q52: =P52+Q66*$L$51 -> -628068.12 | R52: =Q52+R66*$L$51 -> -625752.78 | S52: =R52+S66*$L$51 -> -623437.43 | T52: =S52+T66*$L$51 -> -621122.09 | U52: =T52+U66*$L$51 -> -618806.75
B53: Total Non controlling itnerests | E53: 79908 | G53: -1605 | I53: -6672 | K53: -10356 | M53: =K53 -> -10356 | N53: -13377 | P53: =SUM(P51:P52) -> -8040.6564 | Q53: =SUM(Q51:Q52) -> -5725.3128 | R53: =SUM(R51:R52) -> -3409.9692 | S53: =SUM(S51:S52) -> -1094.6255 | T53: =SUM(T51:T52) -> 1220.7181 | U53: =SUM(U51:U52) -> 3536.0617
B54: Total equity | E54: =SUM(E50,E53) -> 3440601 | G54: =SUM(G50,G53) -> 3129177 | I54: =SUM(I50,I53) -> -2442385 | K54: =SUM(K50,K53) -> -7066904 | P54: =SUM(P50,P53) -> 3276365.5 | Q54: =SUM(Q50,Q53) -> 3326365.5 | R54: =SUM(R50,R53) -> 3376365.5 | S54: =SUM(S50,S53) -> 3426365.5 | T54: =SUM(T50,T53) -> 3476365.5 | U54: =SUM(U50,U53) -> 3526365.5
B56: Share capital total
B57: Retianed earnings total
N59: 589994732307
B60: N° of shares (Units) | C60: Note J | D60: 605801285307 | E60: 606407693 | G60: 606407693 | I60: 606407693 | K60: 606407693 | P60: =K60+D60 -> 606407693000 | Q60: =P60 -> 606407693000 | R60: =Q60 -> 606407693000 | S60: =R60 -> 606407693000 | T60: =S60 -> 606407693000 | U60: =T60 -> 606407693000
B61: Book value of shares (US$ Units) | E61: =E46*1000/E60 -> 5.1883659 | G61: =G46*1000/G60 -> 5.1883659 | I61: =I46*1000/I60 -> 5.1883659 | K61: =K46*1000/K60 -> 5.1883659 | P61: =P46*1000/P60 -> 0.0059439822 | Q61: =Q46*1000/Q60 -> 0.0059439822 | R61: =R46*1000/R60 -> 0.0059439822 | S61: =S46*1000/S60 -> 0.0059439822 | T61: =T46*1000/T60 -> 0.0059439822 | U61: =U46*1000/U60 -> 0.0059439822
B62: Market Value of shares (US$ unites Latam forecast) | G62: =G63*1000/G60 -> 3.7433236 | I62: NA | K62: =K63*1000/K60 -> 0.070865593 | P62: =P63*1000/P60 -> 0.001391857 | Q62: =Q63*1000/Q60 -> #REF! | R62: =R63*1000/R60 -> #REF! | S62: =S63*1000/S60 -> #REF! | T62: =T63*1000/T60 -> #REF! | U62: =U63*1000/U60 -> #REF!
B63: Market Cap (latam forecast) | G63: =G82 -> 2269980.2 | I63: NA | K63: =K82 -> 42973.441 | P63: =P82 -> 844032.8 | Q63: =Q82 -> #REF! | R63: =R82 -> #REF! | S63: =S82 -> #REF! | T63: =T82 -> #REF! | U63: =U82 -> #REF!
B65: INCOME STATEMENT
B66: Net Income | E66: 341800 | G66: 195700 | I66: -4555500 | K66: -4653142 | P66: 50000 | Q66: 50000 | R66: 50000 | S66: 50000 | T66: 50000 | U66: 50000 | W66: Input: net Income
B67: reatined Earnings (Loss) | E67: =E66-E68 -> 287219.56 | G67: =G66-G68 -> 138571 | I67: =I66-I68 -> -4555500 | K67: =K66-K68 -> -4653142 | P67: =P66*$L$48-P68 -> 47684.656 | Q67: =Q66*$L$48-Q68 -> 47684.656 | R67: =R66*$L$48-R68 -> 47684.656 | S67: =S66*$L$48-S68 -> 47684.656 | T67: =T66*$L$48-T68 -> 47684.656 | U67: =U66*$L$48-U68 -> 47684.656
B68: Dividends | E68: 54580.443 | G68: 57129 | P68: =P66*$L$48*P69 -> 0 | Q68: =Q66*$L$48*Q69 -> 0 | R68: =R66*$L$48*R69 -> 0 | S68: =S66*$L$48*S69 -> 0 | T68: =T66*$L$48*T69 -> 0 | U68: =U66*$L$48*U69 -> 0
B69: Payout ratio | E69: =E68/E66 -> 0.15968532 | G69: =G68/G66 -> 0.29192131
B71: CASH BALANCE | C71: Note K
B72: Cash and Cash equivalents beofre debt rpayment (debt financing) | E72: 1081642 | G72: 1072579 | I72: 1695841 | K72: 1046835 | P72: =K72+P11 -> 2569464.3 | Q72: =P76+Q11 -> #REF! | R72: =Q76+R11 -> #REF! | S72: =R76+S11 -> #REF! | T72: =S76+T11 -> #REF! | U72: =T76+U11 -> #REF!
B73: Average excess cash | C73: Note L | K73: =AVERAGE(E72:K72) -> 1224224.2 | P73: =$K$73 -> 1224224.2 | Q73: =P73*(1+Q74) -> 1483540.7 | R73: =Q73*(1+R74) -> 1531346 | S73: =R73*(1+S74) -> 1572452.9 | T73: =S73*(1+T74) -> 1586134.8 | U73: =T73*(1+U74) -> 1628389.4
B74: growth revenues | Q74: 0.21182103 | R74: 0.03222383 | S74: 0.026843612 | T74: 0.0087009826 | U74: 0.026639983
B75: Cash available for debt repayment (need from debt financing) | P75: =P72-P73 -> 1345240 | Q75: =Q72-Q73 -> #REF! | R75: =R72-R73 -> #REF! | S75: =S72-S73 -> #REF! | T75: =T72-T73 -> #REF! | U75: =U72-U73 -> #REF!
B76: Cash after debt repayment (financing) | P76: =P72-(O19-P19) -> 2569464.3 | Q76: =Q72-(P19-Q19) -> #REF! | R76: =R72-(Q19-R19) -> #REF! | S76: =S72-(R19-S19) -> #REF! | T76: =T72-(S19-T19) -> #REF! | U76: =U72-(T19-U19) -> #REF!
B78: CAPITAL STRUCTURE
B79: Book Value of Equity | E79: =SUM(E46:E47,E48:E49,E53) -> 3440601 | G79: =SUM(G46:G47,G48:G49,G53) -> 3129177 | I79: =SUM(I46:I47,I48:I49,I53) -> -2442385 | K79: =SUM(K46:K47,K48:K49,K53) -> -7066904 | P79: =P54 -> 3276365.5 | Q79: =Q54 -> 3326365.5 | R79: =R54 -> 3376365.5 | S79: =S54 -> 3426365.5 | T79: =T54 -> 3476365.5 | U79: =U54 -> 3526365.5
B80: Net Debt | E80: =E30-E72 -> 9335684 | G80: =G30-G72 -> 9079921 | I80: =I30-I72 -> 9163690 | K80: =K30-K72 -> 9355318 | P80: =P30-P76 -> 4135760.7 | Q80: =Q30-Q76 -> #REF! | R80: =R30-R76 -> #REF! | S80: =S30-S76 -> #REF! | T80: =T30-T76 -> #REF! | U80: =U30-U76 -> #REF!
B81: NetDebt/Book | E81: =E80/E79 -> 2.7133876 | G81: =G80/G79 -> 2.9016962 | I81: =I80/I79 -> -3.7519433 | K81: =K80/K79 -> -1.3238213
B82: Makret Value of Equity (latam forecast) | G82: =G80/G83 -> 2269980.2 | I82: NA | K82: =K80/K83 -> 42973.441 | P82: =P80/P83 -> 844032.8 | Q82: =Q80/Q83 -> #REF! | R82: =R80/R83 -> #REF! | S82: =S80/S83 -> #REF! | T82: =T80/T83 -> #REF! | U82: =U80/U83 -> #REF!
B83: NetDebt/market (Latam forecast) | G83: 4 | I83: NA | K83: 217.7 | P83: 4.9 | Q83: 3.2 | R83: 2.6 | S83: 2.2 | T83: 1.9 | U83: 1.7
N85: ebitdar | P85: ='Pro_Forma IS'!H25 -> 884792.78 | Q85: ='Pro_Forma IS'!I25 -> 1727801.3 | R85: ='Pro_Forma IS'!J25 -> 2696874.3 | S85: ='Pro_Forma IS'!K25 -> 2792090.8 | T85: ='Pro_Forma IS'!L25 -> 2675617.7 | U85: ='Pro_Forma IS'!M25 -> 3060091.2
B86: NOTES | N86: NetDebt/Ebitdar | P86: =P80/P85 -> 4.6742705 | Q86: =Q80/Q85 -> #REF! | R86: =R80/R85 -> #REF! | S86: =S80/S85 -> #REF! | T86: =T80/T85 -> #REF! | U86: =U80/U85 -> #REF!
B88: Note 1: to understand financial liabilities, equity and cash dynamics, look at the sheet Cap_Inc where it's described the effect of the captial icnrease on the capital strcutre.
B90: Note 2: by exiting from Chapter 11 and recoverying its ordinary volume of operations, Latam will proabably increase their use of export fiancing, starting from 2022 and then gowing with the amount of revenues and recivables.
C91: 2018 | D91: 2019 | E91: 2020 | F91: 2021 | G91: 2022 | H91: 2023 | I91: 2024 | J91: 2025 | K91: 2026 | L91: 2027
B92: Revenues | D92: =#REF! -> #REF! | E92: =#REF! -> #REF! | F92: =#REF! -> #REF! | G92: =#REF! -> #REF! | H92: =#REF! -> #REF! | I92: =#REF! -> #REF! | J92: =#REF! -> #REF! | K92: =#REF! -> #REF! | L92: =#REF! -> #REF!
B93: growth | E93: =E92/D92-1 -> #REF! | F93: =F92/E92-1 -> #REF! | G93: =G92/F92-1 -> #REF! | H93: =H92/G92-1 -> #REF! | I93: =I92/H92-1 -> #REF! | J93: =J92/I92-1 -> #REF! | K93: =K92/J92-1 -> #REF! | L93: =L92/K92-1 -> #REF!
B95: Note 3: the majority of the extraordinary amount of bank loans settled up to cover cash needs during pandemic crisis expired in 2020 and 2021, thus we cna assume non-current bank loans remain nearly constant to the level fo 3Q 2022.
B96: Note 4: if free cahs flow form operations, especially in the frist years, are nto eough to cover Capital expenditre adn Workign capital increases, as Latam wil have to establish its capcity by purchasing new planes, we will assume Bank loans will be the main instrument to cover these cash needs.
B98: Note5: Majority of other guaranteed liabilties are expiring within 2022, therefore we assume the level at 31th december 2022 to be equal to the non-current portion fo 3Q 22 and then decreasing over time as obligations expire
B100: Note 6: Obligations with the public are two bonds: one of USD 500m that expires between 2 and 4 years, the other expires over 5 years fro USD 340m. As publci financing is channel used by Latam, we can assume it will issue new debt once it's expired. We expect coprate bond rates to reach acceptable amounts fro Latam within expiring bond dates, as Latam will have probably reached a less risky capital structure.
B102: Note 7: Financial leases and lease liabilties are linked to the purchase of the right-of-use assets, mainly aircraft, their growth is linked to the changes in fleet. They decreased in 2021 due to the rejection in lease contracts, but they are expcted to grow in the future.
C103: 2018 | D103: 2019 | E103: 2020 | F103: 2021 | G103: 2022 | H103: 2023 | I103: 2024 | J103: 2025 | K103: 2026 | L103: 2027
B104: Right of Use assets Gross Book Value | C104: =CAPEX!X68 -> 4987953 | D104: =CAPEX!Y68 -> 5693553 | E104: =CAPEX!Z68 -> 5614366 | F104: =CAPEX!AA68 -> 5454167 | G104: =CAPEX!AB68 -> 5828167 | H104: =CAPEX!AC68 -> 6926167 | I104: =CAPEX!AD68 -> 7374167 | J104: =CAPEX!AE68 -> 8114167 | ... L104: =CAPEX!AG68 -> 9884167
B105: Delta right of use assets Gross Book Value | D105: =D104-C104 -> 705600 | E105: =E104-D104 -> -79187 | F105: =F104-E104 -> -160199 | G105: =G104-F104 -> 374000 | H105: =H104-G104 -> 1098000 | I105: =I104-H104 -> 448000 | J105: =J104-I104 -> 740000 | K105: =K104-J104 -> 750000 | L105: =L104-K104 -> 1020000
B106: Debt repayment of Lease Liabilities | H106: -279000 | I106: -548000 | J106: -657000 | K106: -673000 | L106: -713000
B107: Increase in Lease Libailties and Financial Liabilties | D107: =D105 -> 705600 | E107: =E105 -> -79187 | F107: =F105 -> -160199 | G107: =G105 -> 374000 | H107: =H105+H106 -> 819000 | I107: =I105+I106 -> -100000 | J107: =J105+J106 -> 83000 | K107: =K105+K106 -> 77000 | L107: =L105+L106 -> 307000
B110: Note 8: While in 2020 and 2021 no hedging strategies where implmented by latam, as demontrated by the fixed amount of hedge liabilties, we expect hedgiing activites will be settle in the future years, thus we assume a normal amount of hedgin liabilties coherent with 2019, and fixing its growht as revenues increases
B113: Note A: we input free cahs flwo evered hsitrical becase that'swhat we ahve calculted
B114: Note B: Bank loans are the most exposed to the risk premiumms, as they are negotiated more frequenlty, depsite filing for Ch. 11 other debt instruments are less sensible in the short term to the debt risk of Latam. Therefore we assume debt risk premium of Latam on bank loans decreasing gradually arriving to 2019 level in 2023.
B115: Note C: as lease laibilties are covered by the aassets leased, their risk premium is lower than unsecured debt, an pretty cosntant towards the time, we can assume it keep cosntat at 2019 evel in the future years.
B116: Note D: the effective rates on public bonds are 4.81% and 7.16% depending on the matrity of the debt and the negotiation we assume in the future ana verage fo these two aorund 6%
B118: Note E for simplicity we apply the marignal tax rate of the chile: 27%
B119: Note F: we assume an average payout ratio of 25%
B120: Note G: the increase in capital is given from 3Q 2022 release
B121: Note H the increase in captial is used to cover reatined losses
B122: Note I: the increas ein captial is used to carry back reserves to the level of 2018
...

Sheet CAPEX
A1: CAPEX
A5: Fleet reduction until 2022 | E5: 2019 | F5: 2020 | G5: 2021 | H5: 2022E | I5: 2023F | J5: 2024F | K5: 2025F | L5: 2026F | M5: 2027F | P5: Amortization
A6: 1) Rejection of 26 aircraft | D6: Cash fleet capex | E6: -601 | F6: 0 | G6: 0 | H6: 0 | I6: 0 | J6: 0 | K6: 0 | L6: 0 | M6: 0
A7: 2) Retirement of 11 older NB | D7: Non cash fleet capex | E7: -700 | F7: 0 | G7: -537 | H7: -374 | I7: -1098 | J7: -448 | K7: -740 | L7: -750 | M7: -1020
A8: 3) 15 B767s taken out of operation | D8: Non Fleet capex | E8: -1206 | F8: -426 | G8: -846 | H8: -915 | I8: -1165 | J8: -1301 | K8: -1068 | L8: -1024 | M8: -1068 | V8: Note 15 | W8: - Intangibles Assets Other than goodwill
A9: 4) Addition of 8 new leases into the fleet (2 A320, 1 B787-9) | D9: Others | E9: 309 | F9: 26 | G9: 124 | H9: 89 | I9: 50 | J9: 8 | K9: -66 | L9: -183 | M9: -374 | W9: As 31 December 2021 | X9: As December 31 2021 | Z9: 2022E | AA9: 2023F | AB9: 2024F | AC9: 2025F | AD9: 2026F | AE9: 2027F
D10: Investment cash flow | E10: =SUM(E6:E9) -> -2198 | F10: =SUM(F6:F9) -> -400 | G10: =SUM(G6:G9) -> -1259 | H10: =SUM(H6:H9) -> -1200 | I10: =SUM(I6:I9) -> -2213 | J10: =SUM(J6:J9) -> -1741 | K10: =SUM(K6:K9) -> -1874 | L10: =SUM(L6:L9) -> -1957 | M10: =SUM(M6:M9) -> -2462 | V10: Airport Slot | W10: 587214 | X10: 627742 | Z10: =$W$10 -> 587214 | AA10: =$W$10 -> 587214 | AB10: =$W$10 -> 587214 | AC10: =$W$10 -> 587214 | AD10: =$W$10 -> 587214 | AE10: =$W$10 -> 587214
A11: Fleet Simplification | D11: Capex | E11: =E7+E6 -> -1301 | F11: =F7+F6 -> 0 | G11: =G7+G6 -> -537 | H11: =H7+H6 -> -374 | I11: =I7+I6 -> -1098 | J11: =J7+J6 -> -448 | K11: =K7+K6 -> -740 | L11: =L7+L6 -> -750 | M11: =M7+M6 -> -1020 | V11: Loyalty programs | W11: 190542 | X11: 204615 | Z11: =$W$11 -> 190542 | AA11: =$W$11 -> 190542 | AB11: =$W$11 -> 190542 | AC11: =$W$11 -> 190542 | AD11: =$W$11 -> 190542 | AE11: =$W$11 -> 190542
A12: 1) withdrawal of 1 WB fleet type (A350) | V12: Computer software | W12: 136135 | X12: 139113 | Z12: =$W$12+$W$13 -> 241009 | AA12: =$W$12+$W$13 -> 241009 | AB12: =$W$12+$W$13 -> 241009 | AC12: =$W$12+$W$13 -> 241009 | AD12: =$W$12+$W$13 -> 241009 | AE12: =$W$12+$W$13 -> 241009
A13: 2) Consolidation of Brazil operation with B77 and B787 | D13: Aircraft Type | E13: Fleet as petition date | F13: Net +/- | G13: End of the year fleet | V13: Developing software | W13: 104874 | X13: 68521 | Z13: =SUM(Z10:Z12) -> 1018765 | AA13: =SUM(AA10:AA12) -> 1018765 | AB13: =SUM(AB10:AB12) -> 1018765 | AC13: =SUM(AC10:AC12) -> 1018765 | AD13: =SUM(AD10:AD12) -> 1018765 | AE13: =SUM(AE10:AE12) -> 1018765
G14: 2022 | H14: f2023 | I14: f2024 | J14: f2025 | K14: f2026 | L14: f2027 | V14: Trademarks (1) | W14: - | X14: 6340
A15: Source updated BP June 2022 | D15: Narrow Body | E15: =SUM(E16:E22) -> 249 | F15: =SUM(F16:F22) -> -15 | G15: =SUM(G16:G22) -> 234 | H15: =SUM(H16) -> 244 | I15: =SUM(I16) -> 223 | J15: =SUM(J16) -> 237 | K15: =SUM(K16) -> 234 | L15: =SUM(L16) -> 246 | V15: Other assets | W15: 127 | X15: 228
D16: A319 | E16: 46 | F16: -6 | G16: 40 | H16: 244 | I16: 223 | J16: 237 | K16: 234 | L16: 246 | V16: Total assets | W16: =SUM(W10:W15) -> 1018892 | X16: =SUM(X10:X15) -> 1046559
D17: A320 | E17: 141 | F17: -13 | G17: 128
D18: A320 neo | E18: 13 | F18: 4 | G18: 17 | V18: Amortization Computer software | W18: 162468
D19: A321 | E19: 49 | G19: 49 | V19: Value | W19: =528097 -> 528097
D20: A321 neo | W20: =W18/W19 -> 0.30764803
D21: A321 XLR | H21: =ABS(H7/H33) -> 23.375 | I21: =ABS(I7/I33) -> 52.285714 | J21: =ABS(J7/J33) -> 32 | K21: =ABS(K7/K33) -> 740 | L21: =ABS(L7/L33) -> 62.5 | V21: Capex Computer softwares | W21: =W18+W20*W13 -> 194732.28
D22: Δ | H22: =H15-G15 -> 10 | I22: =I15-H15 -> -21 | J22: =J15-I15 -> 14 | K22: =K15-J15 -> -3 | L22: =L15-K15 -> 12
D23: Wide body | E23: =SUM(E24:E28) -> 79 | F23: =SUM(F24:F28) -> -23 | G23: =SUM(G24:G28) -> 56 | H23: 56 | I23: 59 | J23: 59 | K23: 61 | L23: 61
D24: A350 | E24: 13 | F24: -13
D25: B767 | E25: 30 | F25: -15 | G25: 15
D26: B777 | E26: 10 | G26: 10
D27: B78-8 | E27: 10 | G27: 10
D28: B787-9 | E28: 16 | F28: 5 | G28: 21
D29: Δ | H29: =H23-G23 -> 0 | I29: =I23-H23 -> 3 | J29: =J23-I23 -> 0 | K29: =K23-J23 -> 2 | L29: =L23-K23 -> 0
D30: Pax fleet | E30: =E15+E23 -> 328 | F30: =SUM(F24:F28,F16:F22) -> -38 | G30: =G15+G23 -> 290 | H30: =H15+H23 -> 300 | I30: =I15+I23 -> 282 | J30: =J15+J23 -> 296 | K30: =K15+K23 -> 295 | L30: =L15+L23 -> 307
D31: Freighter | E31: 12 | F31: 4 | G31: 16 | H31: =H32-H30 -> 22 | I31: =I32-I30 -> 19 | J31: =J32-J30 -> 19 | K31: =K32-K30 -> 19 | L31: =L32-L30 -> 19
D32: Total Fleet | E32: =SUM(E30:E31) -> 340 | F32: =SUM(F30:F31) -> -34 | G32: =SUM(G30:G31) -> 306 | H32: 322 | I32: 301 | J32: 315 | K32: 314 | L32: 326
D33: Δ | H33: =H32-G32 -> 16 | I33: =I32-H32 -> -21 | J33: =J32-I32 -> 14 | K33: =K32-J32 -> -1 | L33: =L32-K32 -> 12
D34: (-) Pending sales
D35: (-) pending Conversions | F35: -6
D36: Operational Fleet | E36: =E32+SUM(E34:E35) -> 340 | F36: =F32+SUM(F34:F35) -> -40 | G36: =G32+SUM(G34:G35) -> 306 | H36: =H32+SUM(H34:H35) -> 322 | I36: =I32+SUM(I34:I35) -> 301 | J36: =J32+SUM(J34:J35) -> 315 | K36: =K32+SUM(K34:K35) -> 314 | L36: =L32+SUM(L34:L35) -> 326
AU45: 20
AY49: a | AZ49: b | BA49: c | BB49: d | BC49: e | BD49: f | BE49: g | BF49: h
AX51: 400000
AS52: e | AT52: f | AU52: g | AV52: h | AW52: i | AX52: l
AX53: 2024 Cabin Retrofit
X54: Gross Book Value | AH54: Acumulated Depreciation | AR54: Net Book Value
X55: 2018 | Y55: 2019 | Z55: 2020 | AA55: 2021 | AB55: 2022E | AC55: 2023F | AD55: 2024F | AE55: 2025F | AF55: 2026F | AG55: 2027F | AH55: 2018 | AI55: 2019 | AJ55: 2020 | AK55: 2021 | AL55: 2022E | AM55: 2023F | AN55: 2024F | AO55: 2025F | AP55: 2026F | AQ55: 2027F | AR55: 2018 | AS55: 2019 | AT55: 2020 | AU55: 2021 | AV55: 2022E | AW55: 2023F | AX55: 2024F | AY55: 2025F | AZ55: 2026F | BA55: 2027F
W56: Construction in progress | X56: 630320 | Y56: 372589 | Z56: 377961 | AA56: 473797 | AH56: - | AJ56: - | AK56: - | AR56: =X56 -> 630320 | AS56: =Y56 -> 372589 | AT56: =Z56 -> 377961 | AU56: =AA56 -> 473797 | AV56: =$AU$56 -> 473797 | AW56: =$AU$56 -> 473797 | AX56: =$AU$56 -> 473797 | AY56: =$AU$56 -> 473797 | AZ56: =$AU$56 -> 473797 | BA56: =$AU$56 -> 473797
W57: Land | X57: 45424 | Y57: 48406 | Z57: 42979 | AA57: 43276 | AH57: - | AJ57: - | AK57: - | AR57: =X57 -> 45424 | AS57: =Y57 -> 48406 | AT57: =Z57 -> 42979 | AU57: =AA57 -> 43276 | AV57: =AU57 -> 43276 | AW57: =AV57 -> 43276 | AX57: =AW57 -> 43276 | AY57: =AX57 -> 43276 | AZ57: =AY57 -> 43276 | BA57: =AZ57 -> 43276
W58: Buildings | X58: 179907 | Y58: 133488 | Z58: 123836 | AA58: 121972 | AH58: -67342 | AI58: -58626 | AJ58: -58629 | AK58: -61521 | AR58: =X58+AH58 -> 112565 | AS58: =Y58+AI58 -> 74862 | AT58: =Z58+AJ58 -> 65207 | AU58: =AA58+AK58 -> 60451 | AV58: =AU58+$AI$76 -> 60451 | AW58: =AV58+$AI$76 -> 60451 | AX58: =AW58+$AI$76 -> 60451 | AY58: =AX58+$AI$76 -> 60451 | AZ58: =AY58+$AI$76 -> 60451 | BA58: =AZ58+$AI$76 -> 60451
W59: Plant and equipment | X59: 13333837 | Y59: 13993044 | Z59: 12983173 | AA59: 11024722 | AH59: -4361337 | AI59: -4630001 | AJ59: -5292429 | AK59: -4462706 | AR59: =X59+AH59 -> 8972500 | AS59: =Y59+AI59 -> 9363043 | AT59: =Z59+AJ59 -> 7690744 | AU59: =AA59+AK59 -> 6562016 | AV59: =AU59 -> 6562016 | AW59: =AV59 -> 6562016 | AX59: =AW59 -> 6562016 | AY59: =AX59 -> 6562016 | AZ59: =AY59 -> 6562016 | BA59: =AZ59 -> 6562016
W60: Machinery | X60: 34253 | Y60: 33658 | Z60: 27402 | AA60: 25764 | AB60: =(AV60-AU60)*(1+ABS($AH$60-$AI$60)/$Y$60)+AA60+$AH$60-$AI$60 -> 28572.806 | AC60: =AW60-AV60+AB60 -> 29222.374 | AD60: =AX60-AW60+AC60 -> 29962.698 | AE60: =AY60-AX60+AD60 -> 30189.966 | AF60: =AZ60-AY60+AE60 -> 30404.147 | AG60: =BA60-AZ60+AF60 -> 30629.217 | AH60: -27659 | AI60: -28441 | AJ60: -23986 | AK60: -23501 | AR60: =X60+AH60 -> 6594 | AS60: =Y60+AI60 -> 5217 | AT60: =Z60+AJ60 -> 3416 | AU60: =AA60+AK60 -> 2263 | AV60: =(SUM('Forecast Drivers'!H25,'Forecast Drivers'!H68,'Forecast Drivers'!H113)/SUM('Forecast Drivers'!$E$25,'Forecast Drivers'!$E$68,'Forecast Drivers'!$E$113))*ABS($AS$60) -> 4243.7854 | AW60: =(SUM('Forecast Drivers'!I25,'Forecast Drivers'!I68,'Forecast Drivers'!I113)/SUM('Forecast Drivers'!$E$25,'Forecast Drivers'!$E$68,'Forecast Drivers'!$E$113))*ABS($AS$60) -> 4893.3534 | AX60: =(SUM('Forecast Drivers'!J25,'Forecast Drivers'!J68,'Forecast Drivers'!J113)/SUM('Forecast Drivers'!$E$25,'Forecast Drivers'!$E$68,'Forecast Drivers'!$E$113))*ABS($AS$60) -> 5633.6765 | AY60: =(SUM('Forecast Drivers'!K25,'Forecast Drivers'!K68,'Forecast Drivers'!K113)/SUM('Forecast Drivers'!$E$25,'Forecast Drivers'!$E$68,'Forecast Drivers'!$E$113))*ABS($AS$60) -> 5860.9455 | AZ60: =(SUM('Forecast Drivers'!L25,'Forecast Drivers'!L68,'Forecast Drivers'!L113)/SUM('Forecast Drivers'!$E$25,'Forecast Drivers'!$E$68,'Forecast Drivers'!$E$113))*ABS($AS$60) -> 6075.1258 | BA60: =(SUM('Forecast Drivers'!M25,'Forecast Drivers'!M68,'Forecast Drivers'!M113)/SUM('Forecast Drivers'!$E$25,'Forecast Drivers'!$E$68,'Forecast Drivers'!$E$113))*ABS($AS$60) -> 6300.1964
W61: ITE | X61: 160936 | Y61: 161992 | Z61: 147754 | AA61: 146986 | AB61: =AV61-AU61+AA61 -> 147050.3 | AC61: =AW61-AV61+AB61 -> 149637.12 | AD61: =AX61-AW61+AC61 -> 152585.36 | AE61: =AY61-AX61+AD61 -> 153490.43 | AF61: =AZ61-AY61+AE61 -> 154343.37 | AG61: =BA61-AZ61+AF61 -> 155239.68 | AH61: -138372 | AI61: -141216 | AJ61: -132923 | AK61: -130150 | AR61: =X61+AH61 -> 22564 | AS61: =Y61+AI61 -> 20776 | AT61: =Z61+AJ61 -> 14831 | AU61: =AA61+AK61 -> 16836 | AV61: =(SUM('Forecast Drivers'!H25,'Forecast Drivers'!H68,'Forecast Drivers'!H113)/SUM('Forecast Drivers'!$E$25,'Forecast Drivers'!$E$68,'Forecast Drivers'!$E$113))*ABS($AS$61) -> 16900.304 | AW61: =(SUM('Forecast Drivers'!I25,'Forecast Drivers'!I68,'Forecast Drivers'!I113)/SUM('Forecast Drivers'!$E$25,'Forecast Drivers'!$E$68,'Forecast Drivers'!$E$113))*ABS($AS$61) -> 19487.121 | AX61: =(SUM('Forecast Drivers'!J25,'Forecast Drivers'!J68,'Forecast Drivers'!J113)/SUM('Forecast Drivers'!$E$25,'Forecast Drivers'!$E$68,'Forecast Drivers'!$E$113))*ABS($AS$61) -> 22435.358 | AY61: =(SUM('Forecast Drivers'!K25,'Forecast Drivers'!K68,'Forecast Drivers'!K113)/SUM('Forecast Drivers'!$E$25,'Forecast Drivers'!$E$68,'Forecast Drivers'!$E$113))*ABS($AS$61) -> 23340.426 | AZ61: =(SUM('Forecast Drivers'!L25,'Forecast Drivers'!L68,'Forecast Drivers'!L113)/SUM('Forecast Drivers'!$E$25,'Forecast Drivers'!$E$68,'Forecast Drivers'!$E$113))*ABS($AS$61) -> 24193.37 | BA61: =(SUM('Forecast Drivers'!M25,'Forecast Drivers'!M68,'Forecast Drivers'!M113)/SUM('Forecast Drivers'!$E$25,'Forecast Drivers'!$E$68,'Forecast Drivers'!$E$113))*ABS($AS$61) -> 25089.684
W62: Fixed installations and accessories | X62: 182629 | Y62: 171469 | Z62: 154414 | AA62: 147402 | AH62: -111620 | AI62: -111635 | AJ62: -105215 | AK62: -108661 | AR62: =X62+AH62 -> 71009 | AS62: =Y62+AI62 -> 59834 | AT62: =Z62+AJ62 -> 49199 | AU62: =AA62+AK62 -> 38741 | AV62: =SUM('Forecast Drivers'!H25,'Forecast Drivers'!H68,'Forecast Drivers'!H113)/SUM('Forecast Drivers'!$E$25,'Forecast Drivers'!$E$68,'Forecast Drivers'!$E$113)*ABS($AS$62) -> 48672.159 | AW62: =SUM('Forecast Drivers'!I25,'Forecast Drivers'!I68,'Forecast Drivers'!I113)/SUM('Forecast Drivers'!$E$25,'Forecast Drivers'!$E$68,'Forecast Drivers'!$E$113)*ABS($AS$62) -> 56122.083 | AX62: =SUM('Forecast Drivers'!J25,'Forecast Drivers'!J68,'Forecast Drivers'!J113)/SUM('Forecast Drivers'!$E$25,'Forecast Drivers'!$E$68,'Forecast Drivers'!$E$113)*ABS($AS$62) -> 64612.881 | AY62: =SUM('Forecast Drivers'!K25,'Forecast Drivers'!K68,'Forecast Drivers'!K113)/SUM('Forecast Drivers'!$E$25,'Forecast Drivers'!$E$68,'Forecast Drivers'!$E$113)*ABS($AS$62) -> 67219.439 | AZ62: =SUM('Forecast Drivers'!L25,'Forecast Drivers'!L68,'Forecast Drivers'!L113)/SUM('Forecast Drivers'!$E$25,'Forecast Drivers'!$E$68,'Forecast Drivers'!$E$113)*ABS($AS$62) -> 69675.882 | BA62: =SUM('Forecast Drivers'!M25,'Forecast Drivers'!M68,'Forecast Drivers'!M113)/SUM('Forecast Drivers'!$E$25,'Forecast Drivers'!$E$68,'Forecast Drivers'!$E$113)*ABS($AS$62) -> 72257.226
W63: Motor veichles | X63: 69653 | Y63: 67060 | Z63: 49345 | AA63: 49186 | AB63: =AV63-AU63+AA63 -> 49899.98 | AC63: =AW63-AV63+AB63 -> 50738.305 | AD63: =AX63-AW63+AC63 -> 51693.758 | AE63: =AY63-AX63+AD63 -> 51987.069 | AF63: =AZ63-AY63+AE63 -> 52263.487 | AG63: =BA63-AZ63+AF63 -> 52553.961 | AH63: -60531 | AI63: -60327 | AJ63: -44140 | AK63: -44423 | AR63: =X63+AH63 -> 9122 | AS63: =Y63+AI63 -> 6733 | AT63: =Z63+AJ63 -> 5205 | AU63: =AA63+AK63 -> 4763 | AV63: =(SUM('Forecast Drivers'!H25,'Forecast Drivers'!H68,'Forecast Drivers'!H113)/SUM('Forecast Drivers'!$E$25,'Forecast Drivers'!$E$68,'Forecast Drivers'!$E$113))*ABS($AS$63) -> 5476.9804 | AW63: =(SUM('Forecast Drivers'!I25,'Forecast Drivers'!I68,'Forecast Drivers'!I113)/SUM('Forecast Drivers'!$E$25,'Forecast Drivers'!$E$68,'Forecast Drivers'!$E$113))*ABS($AS$63) -> 6315.3055 | AX63: =(SUM('Forecast Drivers'!J25,'Forecast Drivers'!J68,'Forecast Drivers'!J113)/SUM('Forecast Drivers'!$E$25,'Forecast Drivers'!$E$68,'Forecast Drivers'!$E$113))*ABS($AS$63) -> 7270.7579 | AY63: =(SUM('Forecast Drivers'!K25,'Forecast Drivers'!K68,'Forecast Drivers'!K113)/SUM('Forecast Drivers'!$E$25,'Forecast Drivers'!$E$68,'Forecast Drivers'!$E$113))*ABS($AS$63) -> 7564.0686 | AZ63: =(SUM('Forecast Drivers'!L25,'Forecast Drivers'!L68,'Forecast Drivers'!L113)/SUM('Forecast Drivers'!$E$25,'Forecast Drivers'!$E$68,'Forecast Drivers'!$E$113))*ABS($AS$63) -> 7840.4873 | BA63: =(SUM('Forecast Drivers'!M25,'Forecast Drivers'!M68,'Forecast Drivers'!M113)/SUM('Forecast Drivers'!$E$25,'Forecast Drivers'!$E$68,'Forecast Drivers'!$E$113))*ABS($AS$63) -> 8130.9607
W64: Lesehold improvements | X64: 211322 | Y64: 234249 | Z64: 201828 | AA64: 248733 | AH64: -128055 | AI64: -135789 | AJ64: -127420 | AK64: -115758 | AR64: =X64+AH64 -> 83267 | AS64: =Y64+AI64 -> 98460 | AT64: =Z64+AJ64 -> 74408 | AU64: =AA64+AK64 -> 132975 | AV64: =AU64 -> 132975 | AW64: =AV64 -> 132975 | AX64: =AW64 -> 132975 | AY64: =AX64 -> 132975 | AZ64: =AY64 -> 132975 | BA64: =AZ64 -> 132975
